Workbook
Name SegmentaciónDeDatos_Tamaño: #N/A
Name SegmentaciónDeDatos_Tiene_Anexo_2: #N/A

Sheet Detalle1
A1: Detalles para Cuenta de Nombre del requerimiento - Gerencia: Banca Digital, Mes_Cronograma: 2027 - 3, Estado Evaluación de Iniciativas: Pendiente de Atención
A3: Nombre del requerimiento | B3: Prioridad | C3: Orden de Atención | D3: Esfuerzo Estimado Desarrollo | E3: Tamaño | F3: Gerencia | G3: Subgerencia | H3: Sección | I3: Memorando 2026 | J3: Tiene Anexo 2 | K3: Categoría | L3: Estado Evaluación de Iniciativas | M3: Seccion TI | N3: Responsable de atención | O3: Gestor | P3: Comentario | Q3: Comienzo Desarrollo | R3: Fin Desarrollo | S3: Comienzo Calidad | T3: Fin Calidad | U3: Comienzo Producción | V3: Fin Producción | W3: Días Calendario | X3: Hay Fecha Inicio | Y3: Tiene esfuerzo | Z3: Indicador Fechas | AA3: Mes_Cronograma
A4: Adecuación del no cobro de comisión por reposición de Tarjeta de Débito por bloqueos de fraude | B4: 1 | C4: 14 | D4: 3 meses | E4: Mediano | F4: Banca Digital | G4: Canales Alternos | H4: Canales Virtuales | I4: MEMORANDO N° 00000091 - 2026-BN/3252 | J4: Sí | K4: Recomendación | L4: Pendiente de Atención | M4: Sistemas Bancarios | N4: Norma Fukunaga | O4: Omar Sarmiento | Q4: 46301 | R4: 46400 | S4: 46407 | T4: 46463 | U4: 46470 | V4: 46479 | W4: 178 | X4: Con Fecha | Y4: Con esfuerzo | Z4: 🟢 A tiempo | AA4: 2027 - 3
A5: Visa Mandatorio - Autorizaciones parciales para las transacciones AFT | B5: 1 | C5: 2 | D5: 4 meses | E5: Grande | F5: Banca Digital | G5: Canales Alternos | H5: Canales Virtuales | I5: MEMORANDO N° 00000091 -2026-BN/3252 | J5: Sí | K5: Mandatorio | L5: Pendiente de Atención | M5: Sistemas Bancarios | N5: Vladimir Cajavilca | O5: Omar Sarmiento | Q5: 46204 | R5: 46367 | S5: 46374 | T5: 46448 | U5: 46455 | V5: 46469 | W5: 265 | X5: Con Fecha | Y5: Con esfuerzo | Z5: 🟢 A tiempo | AA5: 2027 - 3
A6: Solicitud de Notificaciones | B6: 1 | C6: Por definir | D6: 4 meses | E6: Grande | F6: Banca Digital | G6: Canales Alternos | H6: Canales Virtuales | I6: MEMORANDO N° 00000518 - 2025-BN/3252 | J6: Sí | K6: Evolutivo | L6: Pendiente de Atención | M6: Soluciones Digitales | N6: Mario Carbajo | O6: Omar Sarmiento | Q6: 46204 | R6: 46367 | S6: 46374 | T6: 46448 | U6: 46455 | V6: 46469 | W6: 265 | X6: Con Fecha | Y6: Con esfuerzo | Z6: 🟢 A tiempo | AA6: 2027 - 3

Sheet ResumenTemporal
A3: Tabla 1 - Requerimientos que cuentan con anexo 2 por gerencias | B3: Tiene Anexo 2 ¿? | G3: Tabla 3 - Categorias de los requerimientos por gerencias | H3: Categoría
A4: Gerencia | B4: No | C4: Sí | D4: Total general | G4: Gerencia | H4: Correctivo | I4: Evolutivo | J4: Normativo | K4: Recomendación | L4: (en blanco) | M4: Mandatorio | N4: Total general
A5: Banca Digital | B5: 1 | C5: 50 | D5: 51 | G5: Banca Digital | H5: 5 | I5: 13 | J5: 7 | K5: 9 | L5: 1 | M5: 16 | N5: 51
A6: Finanzas y Tesorería | C6: 6 | D6: 6 | G6: Finanzas y Tesorería | I6: 1 | J6: 5 | N6: 6
A7: Operaciones | C7: 42 | D7: 42 | G7: Operaciones | H7: 2 | I7: 15 | J7: 1 | K7: 24 | N7: 42
A8: OPLAFT | C8: 2 | D8: 2 | G8: OPLAFT | I8: 2 | N8: 2
A9: Productos e Inclusión Financiera | C9: 16 | D9: 16 | G9: Productos e Inclusión Financiera | H9: 1 | I9: 5 | J9: 4 | K9: 6 | N9: 16
A10: Red de Agencias | C10: 2 | D10: 2 | G10: Red de Agencias | I10: 1 | J10: 1 | N10: 2
A11: Riesgos | C11: 6 | D11: 6 | G11: Riesgos | J11: 3 | K11: 3 | N11: 6
A12: Innovación y Transformación Digital | C12: 1 | D12: 1 | G12: Innovación y Transformación Digital | J12: 1 | N12: 1
A13: Administración y Logistica | C13: 2 | D13: 2 | G13: Administración y Logistica | I13: 1 | J13: 1 | N13: 2
A14: Total general | B14: 1 | C14: 127 | D14: 128 | G14: Total general | H14: 8 | I14: 38 | J14: 23 | K14: 42 | L14: 1 | M14: 16 | N14: 128
A26: Tabla 4 - Requerimientos según su tamaño y gerencia | B26: Tamaño
A27: Gerencia | B27: Grande | C27: Mediano | D27: Pequeño | E27: No definido | F27: Extra Grande | G27: Proyecto | H27: Total general
A28: Banca Digital | B28: 11 | C28: 29 | D28: 7 | E28: 4 | H28: 51
A29: Finanzas y Tesorería | B29: 1 | C29: 4 | D29: 1 | H29: 6
A30: Operaciones | B30: 8 | C30: 18 | D30: 3 | E30: 6 | F30: 7 | H30: 42
A31: OPLAFT | C31: 1 | D31: 1 | H31: 2
A32: Productos e Inclusión Financiera | C32: 11 | D32: 2 | F32: 3 | H32: 16
A33: Red de Agencias | C33: 1 | G33: 1 | H33: 2
A34: Riesgos | B34: 1 | C34: 2 | E34: 2 | G34: 1 | H34: 6
A35: Innovación y Transformación Digital | C35: 1 | H35: 1
A36: Administración y Logistica | C36: 1 | F36: 1 | H36: 2
A37: Total general | B37: 21 | C37: 68 | D37: 14 | E37: 12 | F37: 11 | G37: 2 | H37: 128
A44: Gerencia | B44: Tabla 5 - Requerimientos según su estado y gerencia
A45: Banca Digital | B45: 51
A46: Finanzas y Tesorería | B46: 6
A47: Operaciones | B47: 42
A48: OPLAFT | B48: 2
A49: Productos e Inclusión Financiera | B49: 16
A50: Red de Agencias | B50: 2
A51: Riesgos | B51: 6
A52: Innovación y Transformación Digital | B52: 1
A53: Administración y Logistica | B53: 2
A54: Total general | B54: 128
A61: Tabla 1 - Requerimientos que cuentan con anexo 2 por gerencias | B61: Tiene Anexo 2 ¿? | C61: Estado Evaluación de Iniciativas
B62: No | C62: Sí | G62: Total general
A63: Gerencia | B63: Observado | C63: Observado | D63: Pendiente de Atención | E63: Por evaluar | F63: Descartado
A64: Banca Digital | B64: 1 | D64: 46 | E64: 4 | G64: 51
A65: Operaciones | C65: 2 | D65: 36 | E65: 2 | F65: 2 | G65: 42
A66: Productos e Inclusión Financiera | C66: 2 | D66: 14 | G66: 16
A67: Riesgos | D67: 4 | E67: 2 | G67: 6
A68: Finanzas y Tesorería | D68: 6 | G68: 6
A69: Administración y Logistica | D69: 2 | G69: 2
A70: OPLAFT | D70: 2 | G70: 2
A71: Red de Agencias | D71: 2 | G71: 2
A72: Innovación y Transformación Digital | D72: 1 | G72: 1
A73: Total general | B73: 1 | C73: 4 | D73: 113 | E73: 8 | F73: 2 | G73: 128
A80: Tiene Anexo 2 ¿? | B80: Sí
A82: Tabla 1 - Requerimientos que cuentan con anexo 2 por gerencias | B82: Categoría
A83: Gerencia | B83: Correctivo | C83: Evolutivo | D83: Mandatorio | E83: Normativo | F83: Recomendación | G83: Total general
A84: Banca Digital | B84: 5 | C84: 13 | D84: 16 | E84: 7 | F84: 9 | G84: 50
A85: Operaciones | B85: 2 | C85: 15 | E85: 1 | F85: 24 | G85: 42
A86: Productos e Inclusión Financiera | B86: 1 | C86: 5 | E86: 4 | F86: 6 | G86: 16
A87: Riesgos | E87: 3 | F87: 3 | G87: 6
A88: Finanzas y Tesorería | C88: 1 | E88: 5 | G88: 6
A89: Administración y Logistica | C89: 1 | E89: 1 | G89: 2
A90: OPLAFT | C90: 2 | G90: 2
A91: Red de Agencias | C91: 1 | E91: 1 | G91: 2
A92: Innovación y Transformación Digital | E92: 1 | G92: 1
A93: Total general | B93: 8 | C93: 38 | D93: 16 | E93: 23 | F93: 42 | G93: 127
A101: Tiene Anexo 2 | B101: Sí
A102: Estado Evaluación de Iniciativas | B102: Pendiente de Atención
A104: Cuenta de Nombre del requerimiento | B104: Mes_Cronograma | V104: GERENCIAS | W104: 2026 | AA104: 2027 | AE104: 2028 | AI104: Por Definir | AJ104: Total general
A105: Gerencia | B105: 2026 - 10 | C105: 2026 - 11 | D105: 2026 - 12 | E105: 2026 - 9 | F105: 2027 - 1 | G105: 2027 - 10 | H105: 2027 - 11 | I105: 2027 - 12 | J105: 2027 - 2 | K105: 2027 - 3 | L105: 2027 - 4 | M105: 2027 - 5 | N105: 2027 - 6 | O105: 2027 - 7 | P105: 2027 - 8 | Q105: 2028 - 2 | R105: 2028 - 5 | S105: Total general | W105: 1er Trimestre | X105: 2do Trimestre | Y105: 3ro Trimestre | Z105: 4to Trimestre | AA105: 1er Trimestre | AB105: 2do Trimestre | AC105: 3ro Trimestre | AD105: 4to Trimestre | AE105: 1er Trimestre | AF105: 2do Trimestre | AG105: 3ro Trimestre | AH105: 4to Trimestre
A106: Administración y Logistica | F106: 1 | N106: 1 | S106: 2 | V106: Operaciones | W106: =IF(SUMIF($B$105:$R$105,"2026 - 1",$B106:$R106)+SUMIF($B$105:$R$105,"2026 - 2",$B106:$R106)+SUMIF($B$105:$R$105,"2026 - 3",$B106:$R106)=0,"",SUMIF($B$105:$R$105,"2026 - 1",$B106:$R106)+SUMIF($B$105:$R$105,"2026 - 2",$B106:$R106)+SUMIF($B$105:$R$105,"2026 - 3",$B106:$R106)) | X106: =IF(SUMIF($B$105:$R$105,"2026 - 4",$B106:$R106)+SUMIF($B$105:$R$105,"2026 - 5",$B106:$R106)+SUMIF($B$105:$R$105,"2026 - 6",$B106:$R106)=0,"",SUMIF($B$105:$R$105,"2026 - 4",$B106:$R106)+SUMIF($B$105:$R$105,"2026 - 5",$B106:$R106)+SUMIF($B$105:$R$105,"2026 - 6",$B106:$R106)) | Y106: =IF(SUMIF($A$106:$A$114,$V106,$E$106:$E$114)=0,"",SUMIF($A$106:$A$114,$V106,$E$106:$E$114)) -> 2 | Z106: =IF(SUMIF($A$106:$A$114,$V106,$B$106:$B$114)+SUMIF($A$106:$A$114,$V106,$C$106:$C$114)+SUMIF($A$106:$A$114,$V106,$D$106:$D$114)=0,"",SUMIF($A$106:$A$114,$V106,$B$106:$B$114)+SUMIF($A$106:$A$114,$V106,$C$106:$C$114)+SUMIF($A$106:$A$114,$V106,$D$106:$D$114)) -> 5 | AA106: =IF(SUMIF($A$106:$A$114,$V106,$F$106:$F$114)+SUMIF($A$106:$A$114,$V106,$J$106:$J$114)+SUMIF($A$106:$A$114,$V106,$K$106:$K$114)=0,"",SUMIF($A$106:$A$114,$V106,$F$106:$F$114)+SUMIF($A$106:$A$114,$V106,$J$106:$J$114)+SUMIF($A$106:$A$114,$V106,$K$106:$K$114)) -> 14 | AB106: =IF(SUMIF($A$106:$A$114,$V106,$L$106:$L$114)+SUMIF($A$106:$A$114,$V106,$M$106:$M$114)+SUMIF($A$106:$A$114,$V106,$N$106:$N$114)=0,"",SUMIF($A$106:$A$114,$V106,$L$106:$L$114)+SUMIF($A$106:$A$114,$V106,$M$106:$M$114)+SUMIF($A$106:$A$114,$V106,$N$106:$N$114)) -> 8 | AC106: =IF(SUMIF($A$106:$A$114,$V106,$O$106:$O$114)+SUMIF($A$106:$A$114,$V106,$P$106:$P$114)=0,"",SUMIF($A$106:$A$114,$V106,$O$106:$O$114)+SUMIF($A$106:$A$114,$V106,$P$106:$P$114)) -> 3 | AD106: =IF(SUMIF($A$106:$A$114,$V106,$G$106:$G$114)+SUMIF($A$106:$A$114,$V106,$H$106:$H$114)+SUMIF($A$106:$A$114,$V106,$I$106:$I$114)=0,"",SUMIF($A$106:$A$114,$V106,$G$106:$G$114)+SUMIF($A$106:$A$114,$V106,$H$106:$H$114)+SUMIF($A$106:$A$114,$V106,$I$106:$I$114)) -> 1 | AE106: =IF(SUMIF($A$106:$A$114,$V106,$Q$106:$Q$114)=0,"",SUMIF($A$106:$A$114,$V106,$Q$106:$Q$114)) -> 1 | AF106: =IF(SUMIF($A$106:$A$114,$V106,$R$106:$R$114)=0,"",SUMIF($A$106:$A$114,$V106,$R$106:$R$114)) -> 2 | AJ106: =SUM(W106:AI106) -> 36
A107: Banca Digital | B107: 2 | C107: 1 | D107: 5 | E107: 4 | F107: 7 | J107: 8 | K107: 7 | L107: 9 | M107: 2 | N107: 1 | S107: 46 | V107: Banca Digital | Y107: =IF(SUMIF($A$106:$A$114,$V107,$E$106:$E$114)=0,"",SUMIF($A$106:$A$114,$V107,$E$106:$E$114)) -> 4 | Z107: =IF(SUMIF($A$106:$A$114,$V107,$B$106:$B$114)+SUMIF($A$106:$A$114,$V107,$C$106:$C$114)+SUMIF($A$106:$A$114,$V107,$D$106:$D$114)=0,"",SUMIF($A$106:$A$114,$V107,$B$106:$B$114)+SUMIF($A$106:$A$114,$V107,$C$106:$C$114)+SUMIF($A$106:$A$114,$V107,$D$106:$D$114)) -> 8 | AA107: =IF(SUMIF($A$106:$A$114,$V107,$F$106:$F$114)+SUMIF($A$106:$A$114,$V107,$J$106:$J$114)+SUMIF($A$106:$A$114,$V107,$K$106:$K$114)=0,"",SUMIF($A$106:$A$114,$V107,$F$106:$F$114)+SUMIF($A$106:$A$114,$V107,$J$106:$J$114)+SUMIF($A$106:$A$114,$V107,$K$106:$K$114)) -> 22 | AB107: =IF(SUMIF($A$106:$A$114,$V107,$L$106:$L$114)+SUMIF($A$106:$A$114,$V107,$M$106:$M$114)+SUMIF($A$106:$A$114,$V107,$N$106:$N$114)=0,"",SUMIF($A$106:$A$114,$V107,$L$106:$L$114)+SUMIF($A$106:$A$114,$V107,$M$106:$M$114)+SUMIF($A$106:$A$114,$V107,$N$106:$N$114)) -> 12 | AC107: =IF(SUMIF($A$106:$A$114,$V107,$O$106:$O$114)+SUMIF($A$106:$A$114,$V107,$P$106:$P$114)=0,"",SUMIF($A$106:$A$114,$V107,$O$106:$O$114)+SUMIF($A$106:$A$114,$V107,$P$106:$P$114)) | AD107: =IF(SUMIF($A$106:$A$114,$V107,$G$106:$G$114)+SUMIF($A$106:$A$114,$V107,$H$106:$H$114)+SUMIF($A$106:$A$114,$V107,$I$106:$I$114)=0,"",SUMIF($A$106:$A$114,$V107,$G$106:$G$114)+SUMIF($A$106:$A$114,$V107,$H$106:$H$114)+SUMIF($A$106:$A$114,$V107,$I$106:$I$114)) | AE107: =IF(SUMIF($A$106:$A$114,$V107,$Q$106:$Q$114)=0,"",SUMIF($A$106:$A$114,$V107,$Q$106:$Q$114)) | AF107: =IF(SUMIF($A$106:$A$114,$V107,$R$106:$R$114)=0,"",SUMIF($A$106:$A$114,$V107,$R$106:$R$114)) | AJ107: =SUM(W107:AI107) -> 46
A108: Finanzas y Tesorería | E108: 1 | F108: 1 | I108: 2 | K108: 1 | L108: 1 | S108: 6 | V108: Productos e Inclusión Financiera | Y108: =IF(SUMIF($A$106:$A$114,$V108,$E$106:$E$114)=0,"",SUMIF($A$106:$A$114,$V108,$E$106:$E$114)) | Z108: =IF(SUMIF($A$106:$A$114,$V108,$B$106:$B$114)+SUMIF($A$106:$A$114,$V108,$C$106:$C$114)+SUMIF($A$106:$A$114,$V108,$D$106:$D$114)=0,"",SUMIF($A$106:$A$114,$V108,$B$106:$B$114)+SUMIF($A$106:$A$114,$V108,$C$106:$C$114)+SUMIF($A$106:$A$114,$V108,$D$106:$D$114)) -> 2 | AA108: =IF(SUMIF($A$106:$A$114,$V108,$F$106:$F$114)+SUMIF($A$106:$A$114,$V108,$J$106:$J$114)+SUMIF($A$106:$A$114,$V108,$K$106:$K$114)=0,"",SUMIF($A$106:$A$114,$V108,$F$106:$F$114)+SUMIF($A$106:$A$114,$V108,$J$106:$J$114)+SUMIF($A$106:$A$114,$V108,$K$106:$K$114)) -> 6 | AB108: =IF(SUMIF($A$106:$A$114,$V108,$L$106:$L$114)+SUMIF($A$106:$A$114,$V108,$M$106:$M$114)+SUMIF($A$106:$A$114,$V108,$N$106:$N$114)=0,"",SUMIF($A$106:$A$114,$V108,$L$106:$L$114)+SUMIF($A$106:$A$114,$V108,$M$106:$M$114)+SUMIF($A$106:$A$114,$V108,$N$106:$N$114)) -> 4 | AC108: =IF(SUMIF($A$106:$A$114,$V108,$O$106:$O$114)+SUMIF($A$106:$A$114,$V108,$P$106:$P$114)=0,"",SUMIF($A$106:$A$114,$V108,$O$106:$O$114)+SUMIF($A$106:$A$114,$V108,$P$106:$P$114)) -> 2 | AD108: =IF(SUMIF($A$106:$A$114,$V108,$G$106:$G$114)+SUMIF($A$106:$A$114,$V108,$H$106:$H$114)+SUMIF($A$106:$A$114,$V108,$I$106:$I$114)=0,"",SUMIF($A$106:$A$114,$V108,$G$106:$G$114)+SUMIF($A$106:$A$114,$V108,$H$106:$H$114)+SUMIF($A$106:$A$114,$V108,$I$106:$I$114)) | AE108: =IF(SUMIF($A$106:$A$114,$V108,$Q$106:$Q$114)=0,"",SUMIF($A$106:$A$114,$V108,$Q$106:$Q$114)) | AF108: =IF(SUMIF($A$106:$A$114,$V108,$R$106:$R$114)=0,"",SUMIF($A$106:$A$114,$V108,$R$106:$R$114)) | AJ108: =SUM(W108:AI108) -> 14
A109: Innovación y Transformación Digital | L109: 1 | S109: 1 | V109: Finanzas y Tesorería | Y109: =IF(SUMIF($A$106:$A$114,$V109,$E$106:$E$114)=0,"",SUMIF($A$106:$A$114,$V109,$E$106:$E$114)) -> 1 | Z109: =IF(SUMIF($A$106:$A$114,$V109,$B$106:$B$114)+SUMIF($A$106:$A$114,$V109,$C$106:$C$114)+SUMIF($A$106:$A$114,$V109,$D$106:$D$114)=0,"",SUMIF($A$106:$A$114,$V109,$B$106:$B$114)+SUMIF($A$106:$A$114,$V109,$C$106:$C$114)+SUMIF($A$106:$A$114,$V109,$D$106:$D$114)) | AA109: =IF(SUMIF($A$106:$A$114,$V109,$F$106:$F$114)+SUMIF($A$106:$A$114,$V109,$J$106:$J$114)+SUMIF($A$106:$A$114,$V109,$K$106:$K$114)=0,"",SUMIF($A$106:$A$114,$V109,$F$106:$F$114)+SUMIF($A$106:$A$114,$V109,$J$106:$J$114)+SUMIF($A$106:$A$114,$V109,$K$106:$K$114)) -> 2 | AB109: =IF(SUMIF($A$106:$A$114,$V109,$L$106:$L$114)+SUMIF($A$106:$A$114,$V109,$M$106:$M$114)+SUMIF($A$106:$A$114,$V109,$N$106:$N$114)=0,"",SUMIF($A$106:$A$114,$V109,$L$106:$L$114)+SUMIF($A$106:$A$114,$V109,$M$106:$M$114)+SUMIF($A$106:$A$114,$V109,$N$106:$N$114)) -> 1 | AC109: =IF(SUMIF($A$106:$A$114,$V109,$O$106:$O$114)+SUMIF($A$106:$A$114,$V109,$P$106:$P$114)=0,"",SUMIF($A$106:$A$114,$V109,$O$106:$O$114)+SUMIF($A$106:$A$114,$V109,$P$106:$P$114)) | AD109: =IF(SUMIF($A$106:$A$114,$V109,$G$106:$G$114)+SUMIF($A$106:$A$114,$V109,$H$106:$H$114)+SUMIF($A$106:$A$114,$V109,$I$106:$I$114)=0,"",SUMIF($A$106:$A$114,$V109,$G$106:$G$114)+SUMIF($A$106:$A$114,$V109,$H$106:$H$114)+SUMIF($A$106:$A$114,$V109,$I$106:$I$114)) -> 2 | AE109: =IF(SUMIF($A$106:$A$114,$V109,$Q$106:$Q$114)=0,"",SUMIF($A$106:$A$114,$V109,$Q$106:$Q$114)) | AF109: =IF(SUMIF($A$106:$A$114,$V109,$R$106:$R$114)=0,"",SUMIF($A$106:$A$114,$V109,$R$106:$R$114)) | AJ109: =SUM(W109:AI109) -> 6
A110: Operaciones | B110: 1 | C110: 1 | D110: 3 | E110: 2 | F110: 7 | H110: 1 | J110: 4 | K110: 3 | L110: 3 | M110: 3 | N110: 2 | O110: 2 | P110: 1 | Q110: 1 | R110: 2 | S110: 36 | V110: Riesgos | Y110: =IF(SUMIF($A$106:$A$114,$V110,$E$106:$E$114)=0,"",SUMIF($A$106:$A$114,$V110,$E$106:$E$114)) | Z110: =IF(SUMIF($A$106:$A$114,$V110,$B$106:$B$114)+SUMIF($A$106:$A$114,$V110,$C$106:$C$114)+SUMIF($A$106:$A$114,$V110,$D$106:$D$114)=0,"",SUMIF($A$106:$A$114,$V110,$B$106:$B$114)+SUMIF($A$106:$A$114,$V110,$C$106:$C$114)+SUMIF($A$106:$A$114,$V110,$D$106:$D$114)) | AA110: =IF(SUMIF($A$106:$A$114,$V110,$F$106:$F$114)+SUMIF($A$106:$A$114,$V110,$J$106:$J$114)+SUMIF($A$106:$A$114,$V110,$K$106:$K$114)=0,"",SUMIF($A$106:$A$114,$V110,$F$106:$F$114)+SUMIF($A$106:$A$114,$V110,$J$106:$J$114)+SUMIF($A$106:$A$114,$V110,$K$106:$K$114)) -> 2 | AB110: =IF(SUMIF($A$106:$A$114,$V110,$L$106:$L$114)+SUMIF($A$106:$A$114,$V110,$M$106:$M$114)+SUMIF($A$106:$A$114,$V110,$N$106:$N$114)=0,"",SUMIF($A$106:$A$114,$V110,$L$106:$L$114)+SUMIF($A$106:$A$114,$V110,$M$106:$M$114)+SUMIF($A$106:$A$114,$V110,$N$106:$N$114)) -> 1 | AC110: =IF(SUMIF($A$106:$A$114,$V110,$O$106:$O$114)+SUMIF($A$106:$A$114,$V110,$P$106:$P$114)=0,"",SUMIF($A$106:$A$114,$V110,$O$106:$O$114)+SUMIF($A$106:$A$114,$V110,$P$106:$P$114)) | AD110: =IF(SUMIF($A$106:$A$114,$V110,$G$106:$G$114)+SUMIF($A$106:$A$114,$V110,$H$106:$H$114)+SUMIF($A$106:$A$114,$V110,$I$106:$I$114)=0,"",SUMIF($A$106:$A$114,$V110,$G$106:$G$114)+SUMIF($A$106:$A$114,$V110,$H$106:$H$114)+SUMIF($A$106:$A$114,$V110,$I$106:$I$114)) -> 1 | AE110: =IF(SUMIF($A$106:$A$114,$V110,$Q$106:$Q$114)=0,"",SUMIF($A$106:$A$114,$V110,$Q$106:$Q$114)) | AF110: =IF(SUMIF($A$106:$A$114,$V110,$R$106:$R$114)=0,"",SUMIF($A$106:$A$114,$V110,$R$106:$R$114)) | AI110: 2 | AJ110: =SUM(W110:AI110) -> 6
A111: OPLAFT | J111: 1 | M111: 1 | S111: 2 | V111: Red de Agencias | Y111: =IF(SUMIF($A$106:$A$114,$V111,$E$106:$E$114)=0,"",SUMIF($A$106:$A$114,$V111,$E$106:$E$114)) | Z111: =IF(SUMIF($A$106:$A$114,$V111,$B$106:$B$114)+SUMIF($A$106:$A$114,$V111,$C$106:$C$114)+SUMIF($A$106:$A$114,$V111,$D$106:$D$114)=0,"",SUMIF($A$106:$A$114,$V111,$B$106:$B$114)+SUMIF($A$106:$A$114,$V111,$C$106:$C$114)+SUMIF($A$106:$A$114,$V111,$D$106:$D$114)) | AA111: =IF(SUMIF($A$106:$A$114,$V111,$F$106:$F$114)+SUMIF($A$106:$A$114,$V111,$J$106:$J$114)+SUMIF($A$106:$A$114,$V111,$K$106:$K$114)=0,"",SUMIF($A$106:$A$114,$V111,$F$106:$F$114)+SUMIF($A$106:$A$114,$V111,$J$106:$J$114)+SUMIF($A$106:$A$114,$V111,$K$106:$K$114)) -> 1 | AB111: =IF(SUMIF($A$106:$A$114,$V111,$L$106:$L$114)+SUMIF($A$106:$A$114,$V111,$M$106:$M$114)+SUMIF($A$106:$A$114,$V111,$N$106:$N$114)=0,"",SUMIF($A$106:$A$114,$V111,$L$106:$L$114)+SUMIF($A$106:$A$114,$V111,$M$106:$M$114)+SUMIF($A$106:$A$114,$V111,$N$106:$N$114)) | AC111: =IF(SUMIF($A$106:$A$114,$V111,$O$106:$O$114)+SUMIF($A$106:$A$114,$V111,$P$106:$P$114)=0,"",SUMIF($A$106:$A$114,$V111,$O$106:$O$114)+SUMIF($A$106:$A$114,$V111,$P$106:$P$114)) -> 1 | AD111: =IF(SUMIF($A$106:$A$114,$V111,$G$106:$G$114)+SUMIF($A$106:$A$114,$V111,$H$106:$H$114)+SUMIF($A$106:$A$114,$V111,$I$106:$I$114)=0,"",SUMIF($A$106:$A$114,$V111,$G$106:$G$114)+SUMIF($A$106:$A$114,$V111,$H$106:$H$114)+SUMIF($A$106:$A$114,$V111,$I$106:$I$114)) | AE111: =IF(SUMIF($A$106:$A$114,$V111,$Q$106:$Q$114)=0,"",SUMIF($A$106:$A$114,$V111,$Q$106:$Q$114)) | AF111: =IF(SUMIF($A$106:$A$114,$V111,$R$106:$R$114)=0,"",SUMIF($A$106:$A$114,$V111,$R$106:$R$114)) | AJ111: =SUM(W111:AI111) -> 2
A112: Productos e Inclusión Financiera | B112: 1 | C112: 1 | F112: 6 | L112: 2 | M112: 2 | O112: 2 | S112: 14 | V112: Administración y Logistica | Y112: =IF(SUMIF($A$106:$A$114,$V112,$E$106:$E$114)=0,"",SUMIF($A$106:$A$114,$V112,$E$106:$E$114)) | Z112: =IF(SUMIF($A$106:$A$114,$V112,$B$106:$B$114)+SUMIF($A$106:$A$114,$V112,$C$106:$C$114)+SUMIF($A$106:$A$114,$V112,$D$106:$D$114)=0,"",SUMIF($A$106:$A$114,$V112,$B$106:$B$114)+SUMIF($A$106:$A$114,$V112,$C$106:$C$114)+SUMIF($A$106:$A$114,$V112,$D$106:$D$114)) | AA112: =IF(SUMIF($A$106:$A$114,$V112,$F$106:$F$114)+SUMIF($A$106:$A$114,$V112,$J$106:$J$114)+SUMIF($A$106:$A$114,$V112,$K$106:$K$114)=0,"",SUMIF($A$106:$A$114,$V112,$F$106:$F$114)+SUMIF($A$106:$A$114,$V112,$J$106:$J$114)+SUMIF($A$106:$A$114,$V112,$K$106:$K$114)) -> 1 | AB112: =IF(SUMIF($A$106:$A$114,$V112,$L$106:$L$114)+SUMIF($A$106:$A$114,$V112,$M$106:$M$114)+SUMIF($A$106:$A$114,$V112,$N$106:$N$114)=0,"",SUMIF($A$106:$A$114,$V112,$L$106:$L$114)+SUMIF($A$106:$A$114,$V112,$M$106:$M$114)+SUMIF($A$106:$A$114,$V112,$N$106:$N$114)) -> 1 | AC112: =IF(SUMIF($A$106:$A$114,$V112,$O$106:$O$114)+SUMIF($A$106:$A$114,$V112,$P$106:$P$114)=0,"",SUMIF($A$106:$A$114,$V112,$O$106:$O$114)+SUMIF($A$106:$A$114,$V112,$P$106:$P$114)) | AD112: =IF(SUMIF($A$106:$A$114,$V112,$G$106:$G$114)+SUMIF($A$106:$A$114,$V112,$H$106:$H$114)+SUMIF($A$106:$A$114,$V112,$I$106:$I$114)=0,"",SUMIF($A$106:$A$114,$V112,$G$106:$G$114)+SUMIF($A$106:$A$114,$V112,$H$106:$H$114)+SUMIF($A$106:$A$114,$V112,$I$106:$I$114)) | AE112: =IF(SUMIF($A$106:$A$114,$V112,$Q$106:$Q$114)=0,"",SUMIF($A$106:$A$114,$V112,$Q$106:$Q$114)) | AF112: =IF(SUMIF($A$106:$A$114,$V112,$R$106:$R$114)=0,"",SUMIF($A$106:$A$114,$V112,$R$106:$R$114)) | AJ112: =SUM(W112:AI112) -> 2
A113: Red de Agencias | J113: 1 | P113: 1 | S113: 2 | V113: OPLAFT | Y113: =IF(SUMIF($A$106:$A$114,$V113,$E$106:$E$114)=0,"",SUMIF($A$106:$A$114,$V113,$E$106:$E$114)) | Z113: =IF(SUMIF($A$106:$A$114,$V113,$B$106:$B$114)+SUMIF($A$106:$A$114,$V113,$C$106:$C$114)+SUMIF($A$106:$A$114,$V113,$D$106:$D$114)=0,"",SUMIF($A$106:$A$114,$V113,$B$106:$B$114)+SUMIF($A$106:$A$114,$V113,$C$106:$C$114)+SUMIF($A$106:$A$114,$V113,$D$106:$D$114)) | AA113: =IF(SUMIF($A$106:$A$114,$V113,$F$106:$F$114)+SUMIF($A$106:$A$114,$V113,$J$106:$J$114)+SUMIF($A$106:$A$114,$V113,$K$106:$K$114)=0,"",SUMIF($A$106:$A$114,$V113,$F$106:$F$114)+SUMIF($A$106:$A$114,$V113,$J$106:$J$114)+SUMIF($A$106:$A$114,$V113,$K$106:$K$114)) -> 1 | AB113: =IF(SUMIF($A$106:$A$114,$V113,$L$106:$L$114)+SUMIF($A$106:$A$114,$V113,$M$106:$M$114)+SUMIF($A$106:$A$114,$V113,$N$106:$N$114)=0,"",SUMIF($A$106:$A$114,$V113,$L$106:$L$114)+SUMIF($A$106:$A$114,$V113,$M$106:$M$114)+SUMIF($A$106:$A$114,$V113,$N$106:$N$114)) -> 1 | AC113: =IF(SUMIF($A$106:$A$114,$V113,$O$106:$O$114)+SUMIF($A$106:$A$114,$V113,$P$106:$P$114)=0,"",SUMIF($A$106:$A$114,$V113,$O$106:$O$114)+SUMIF($A$106:$A$114,$V113,$P$106:$P$114)) | AD113: =IF(SUMIF($A$106:$A$114,$V113,$G$106:$G$114)+SUMIF($A$106:$A$114,$V113,$H$106:$H$114)+SUMIF($A$106:$A$114,$V113,$I$106:$I$114)=0,"",SUMIF($A$106:$A$114,$V113,$G$106:$G$114)+SUMIF($A$106:$A$114,$V113,$H$106:$H$114)+SUMIF($A$106:$A$114,$V113,$I$106:$I$114)) | AE113: =IF(SUMIF($A$106:$A$114,$V113,$Q$106:$Q$114)=0,"",SUMIF($A$106:$A$114,$V113,$Q$106:$Q$114)) | AF113: =IF(SUMIF($A$106:$A$114,$V113,$R$106:$R$114)=0,"",SUMIF($A$106:$A$114,$V113,$R$106:$R$114)) | AJ113: =SUM(W113:AI113) -> 2
A114: Riesgos | F114: 1 | G114: 1 | K114: 1 | M114: 1 | S114: 4 | V114: Innovación y Transformación Digital | Y114: =IF(SUMIF($A$106:$A$114,$V114,$E$106:$E$114)=0,"",SUMIF($A$106:$A$114,$V114,$E$106:$E$114)) | Z114: =IF(SUMIF($A$106:$A$114,$V114,$B$106:$B$114)+SUMIF($A$106:$A$114,$V114,$C$106:$C$114)+SUMIF($A$106:$A$114,$V114,$D$106:$D$114)=0,"",SUMIF($A$106:$A$114,$V114,$B$106:$B$114)+SUMIF($A$106:$A$114,$V114,$C$106:$C$114)+SUMIF($A$106:$A$114,$V114,$D$106:$D$114)) | AA114: =IF(SUMIF($A$106:$A$114,$V114,$F$106:$F$114)+SUMIF($A$106:$A$114,$V114,$J$106:$J$114)+SUMIF($A$106:$A$114,$V114,$K$106:$K$114)=0,"",SUMIF($A$106:$A$114,$V114,$F$106:$F$114)+SUMIF($A$106:$A$114,$V114,$J$106:$J$114)+SUMIF($A$106:$A$114,$V114,$K$106:$K$114)) | AB114: =IF(SUMIF($A$106:$A$114,$V114,$L$106:$L$114)+SUMIF($A$106:$A$114,$V114,$M$106:$M$114)+SUMIF($A$106:$A$114,$V114,$N$106:$N$114)=0,"",SUMIF($A$106:$A$114,$V114,$L$106:$L$114)+SUMIF($A$106:$A$114,$V114,$M$106:$M$114)+SUMIF($A$106:$A$114,$V114,$N$106:$N$114)) -> 1 | AC114: =IF(SUMIF($A$106:$A$114,$V114,$O$106:$O$114)+SUMIF($A$106:$A$114,$V114,$P$106:$P$114)=0,"",SUMIF($A$106:$A$114,$V114,$O$106:$O$114)+SUMIF($A$106:$A$114,$V114,$P$106:$P$114)) | AD114: =IF(SUMIF($A$106:$A$114,$V114,$G$106:$G$114)+SUMIF($A$106:$A$114,$V114,$H$106:$H$114)+SUMIF($A$106:$A$114,$V114,$I$106:$I$114)=0,"",SUMIF($A$106:$A$114,$V114,$G$106:$G$114)+SUMIF($A$106:$A$114,$V114,$H$106:$H$114)+SUMIF($A$106:$A$114,$V114,$I$106:$I$114)) | AE114: =IF(SUMIF($A$106:$A$114,$V114,$Q$106:$Q$114)=0,"",SUMIF($A$106:$A$114,$V114,$Q$106:$Q$114)) | AF114: =IF(SUMIF($A$106:$A$114,$V114,$R$106:$R$114)=0,"",SUMIF($A$106:$A$114,$V114,$R$106:$R$114)) | AJ114: =SUM(W114:AI114) -> 1
A115: Total general | B115: 4 | C115: 3 | D115: 8 | E115: 7 | F115: 23 | G115: 1 | H115: 1 | I115: 2 | J115: 14 | K115: 12 | L115: 16 | M115: 9 | N115: 4 | O115: 4 | P115: 2 | Q115: 1 | R115: 2 | S115: 113 | V115: Total general | W115: =SUM(W106:W114) -> 0 | X115: =SUM(X106:X114) -> 0 | Y115: =SUM(Y106:Y114) -> 7 | Z115: =SUM(Z106:Z114) -> 15 | AA115: =SUM(AA106:AA114) -> 49 | AB115: =SUM(AB106:AB114) -> 29 | AC115: =SUM(AC106:AC114) -> 6 | AD115: =SUM(AD106:AD114) -> 4 | ... AJ115: =SUM(AJ106:AJ114) -> 115

Sheet PRIORIDAD UNO
Q1: Leyenda - Comienzo Desarrollo | T1: Leyenda - Fechas
A2: =_xlfn.CONCAT("Total = ",COUNTA(PRIORIDAD_UNO[Nombre del requerimiento])) -> Total = 128 | Q2: 🟠: Tamaño no definido. | S2: ⚠️Error: No está registrado en hoja "Cálculos Manual".
Q3: 🟣: Iniciativa es un proyecto.
A4: Nombre del requerimiento | B4: Prioridad | C4: Orden de Atención | D4: Esfuerzo Estimado Desarrollo | E4: Tamaño | F4: Gerencia | G4: Subgerencia | H4: Sección | I4: Memorando 2026 | J4: Tiene Anexo 2 | K4: Categoría | L4: Estado Evaluación de Iniciativas | M4: Seccion TI | N4: Responsable de atención | O4: Gestor | P4: Comentario | Q4: Comienzo Desarrollo | R4: Fin Desarrollo | S4: Comienzo Calidad | T4: Fin Calidad | U4: Comienzo Producción | V4: Fin Producción | W4: Días Calendario | X4: Hay Fecha Inicio | Y4: Tiene esfuerzo | Z4: Indicador Fechas | AA4: Mes_Cronograma | AB4: Backlog ID
A5: Vulnerabilidad en la plataforma Pagalo.pe reportada por el equipo de Seguridad Informatica en la descarga de comprobantes de pago | B5: 1 | C5: 4 | D5: 1 mes | E5: =IF(OR(ISBLANK(PRIORIDAD_UNO[[#This Row],[Esfuerzo Estimado Desarrollo]]),PRIORIDAD_UNO[[#This Row],[Esfuerzo Estimado Desarrollo]]="No definido"),"No definido", IF(VALUE(TRIM(LEFT(PRIORIDAD_UNO[[#This Row],[Esfuerzo Estimado Desarrollo]],2)))<=1,"Pequeño", IF(VALUE(TRIM(LEFT(PRIORIDAD_UNO[[#This Row],[Esfuerzo Estimado Desarrollo]],2)))<=3,"Mediano", IF(VALUE(TRIM(LEFT(PRIORIDAD_UNO[[#This Row],[Esfuerzo Estimado Desarrollo]],2)))<=5,"Grande", IF(VALUE(TRIM(LEFT(PRIORIDAD_UNO[[#This Row],[Esfuerzo Estimado Desarrollo]],2)))<=7,"Extra Grande","Proyecto"))))) -> Pequeño | F5: Banca Digital | G5: Canales Alternos | H5: Canales Virtuales | I5: MEMORANDO N° 00000120 - 2026-BN/3252 | J5: Sí | K5: Evolutivo | L5: Por evaluar | M5: Sistemas Bancarios | N5: Eduardo Cárdenas | O5: Omar Sarmiento | R5: =IF(OR(PRIORIDAD_UNO[[#This Row],[Tamaño]]="No definido",ISBLANK(PRIORIDAD_UNO[[#This Row],[Comienzo Desarrollo]])),"",IF(ISBLANK( VLOOKUP(PRIORIDAD_UNO[[#This Row],[Nombre del requerimiento]],'Cálculos Manual'!A:F,6,FALSE)), WORKDAY(PRIORIDAD_UNO[[#This Row],[Comienzo Desarrollo]], IF(PRIORIDAD_UNO[[#This Row],[Tamaño]]="Pequeño",30,IF(PRIORIDAD_UNO[[#This Row],[Tamaño]]="Mediano",66,IF(PRIORIDAD_UNO[[#This Row],[Tamaño]]="Grande",110,IF(PRIORIDAD_UNO[[#This Row],[Tamaño]]="Extra Grande",154,176)))), FERIADOS[Fecha]), VLOOKUP(PRIORIDAD_UNO[[#This Row],[Nombre del requerimiento]],'Cálculos Manual'!A:F,6,FALSE))) | S5: =IF(PRIORIDAD_UNO[[#This Row],[Fin Desarrollo]]="","",IF(ISBLANK(VLOOKUP(PRIORIDAD_UNO[[#This Row],[Nombre del requerimiento]],'Cálculos Manual'!A:H,8,FALSE)),WORKDAY(PRIORIDAD_UNO[[#This Row],[Fin Desarrollo]],5,FERIADOS[Fecha]), VLOOKUP(PRIORIDAD_UNO[[#This Row],[Nombre del requerimiento]],'Cálculos Manual'!A:H,8,FALSE))) | T5: =IF(PRIORIDAD_UNO[[#This Row],[Comienzo Calidad]]="","",IF(ISBLANK(VLOOKUP(PRIORIDAD_UNO[[#This Row],[Nombre del requerimiento]],'Cálculos Manual'!A:J,10,FALSE)), WORKDAY(PRIORIDAD_UNO[[#This Row],[Comienzo Calidad]],IF(PRIORIDAD_UNO[[#This Row],[Tamaño]]="Pequeño",30,IF(PRIORIDAD_UNO[[#This Row],[Tamaño]]="Mediano",40,50)),FERIADOS[Fecha]), VLOOKUP(PRIORIDAD_UNO[[#This Row],[Nombre del requerimiento]],'Cálculos Manual'!A:J,10,FALSE))) | U5: =IF(PRIORIDAD_UNO[[#This Row],[Fin Calidad]]="","",IF(ISBLANK(VLOOKUP(PRIORIDAD_UNO[[#This Row],[Nombre del requerimiento]],'Cálculos Manual'!A:L,12,FALSE)), WORKDAY(PRIORIDAD_UNO[[#This Row],[Fin Calidad]],5,FERIADOS[Fecha]), VLOOKUP(PRIORIDAD_UNO[[#This Row],[Nombre del requerimiento]],'Cálculos Manual'!A:L,12,FALSE))) | V5: =IF(PRIORIDAD_UNO[[#This Row],[Comienzo Producción]]="","",IF(ISBLANK(VLOOKUP(PRIORIDAD_UNO[[#This Row],[Nombre del requerimiento]],'Cálculos Manual'!A:N,14,FALSE)), WORKDAY(PRIORIDAD_UNO[[#This Row],[Comienzo Producción]],IF(PRIORIDAD_UNO[[#This Row],[Tamaño]]="Grande",10,5),FERIADOS[Fecha]), VLOOKUP(PRIORIDAD_UNO[[#This Row],[Nombre del requerimiento]],'Cálculos Manual'!A:N,14,FALSE))) | W5: =IFERROR(PRIORIDAD_UNO[[#This Row],[Fin Producción]]-PRIORIDAD_UNO[[#This Row],[Comienzo Desarrollo]],"") | X5: =IF(ISBLANK(PRIORIDAD_UNO[[#This Row],[Comienzo Desarrollo]]),"Sin Fecha","Con Fecha") -> Sin Fecha | Y5: =IF(PRIORIDAD_UNO[[#This Row],[Esfuerzo Estimado Desarrollo]]="No definido","Sin esfuerzo","Con esfuerzo") -> Con esfuerzo | Z5: =IF(ISBLANK(PRIORIDAD_UNO[[#This Row],[Comienzo Desarrollo]]),"🔵 Sin Fecha", IF(PRIORIDAD_UNO[[#This Row],[Comienzo Desarrollo]]<TODAY(),"🔴 Vencido", IF(PRIORIDAD_UNO[[#This Row],[Comienzo Desarrollo]]=TODAY(),"🟡 Vence hoy", IF((PRIORIDAD_UNO[[#This Row],[Comienzo Desarrollo]]-TODAY())<=5,"🟠 Por vencer", "🟢 A tiempo")))) -> 🔵 Sin Fecha | AA5: =IF(PRIORIDAD_UNO[[#This Row],[Comienzo Producción]]="","Por Definir",_xlfn.CONCAT(YEAR(PRIORIDAD_UNO[[#This Row],[Comienzo Producción]])," - ", MONTH(PRIORIDAD_UNO[[#This Row],[Comienzo Producción]]))) -> Por Definir | AB5: No está
A6: Visa Mandatorio - Autorizaciones parciales para las transacciones AFT | B6: 1 | C6: 2 | D6: 4 meses | E6: =IF(OR(ISBLANK(PRIORIDAD_UNO[[#This Row],[Esfuerzo Estimado Desarrollo]]),PRIORIDAD_UNO[[#This Row],[Esfuerzo Estimado Desarrollo]]="No definido"),"No definido", IF(VALUE(TRIM(LEFT(PRIORIDAD_UNO[[#This Row],[Esfuerzo Estimado Desarrollo]],2)))<=1,"Pequeño", IF(VALUE(TRIM(LEFT(PRIORIDAD_UNO[[#This Row],[Esfuerzo Estimado Desarrollo]],2)))<=3,"Mediano", IF(VALUE(TRIM(LEFT(PRIORIDAD_UNO[[#This Row],[Esfuerzo Estimado Desarrollo]],2)))<=5,"Grande", IF(VALUE(TRIM(LEFT(PRIORIDAD_UNO[[#This Row],[Esfuerzo Estimado Desarrollo]],2)))<=7,"Extra Grande","Proyecto"))))) -> Grande | F6: Banca Digital | G6: Canales Alternos | H6: Canales Virtuales | I6: MEMORANDO N° 00000091 -2026-BN/3252 | J6: Sí | K6: Mandatorio | L6: Pendiente de Atención | M6: Sistemas Bancarios | N6: Vladimir Cajavilca | O6: Omar Sarmiento | Q6: 46204 | R6: =IF(OR(PRIORIDAD_UNO[[#This Row],[Tamaño]]="No definido",ISBLANK(PRIORIDAD_UNO[[#This Row],[Comienzo Desarrollo]])),"",IF(ISBLANK( VLOOKUP(PRIORIDAD_UNO[[#This Row],[Nombre del requerimiento]],'Cálculos Manual'!A:F,6,FALSE)), WORKDAY(PRIORIDAD_UNO[[#This Row],[Comienzo Desarrollo]], IF(PRIORIDAD_UNO[[#This Row],[Tamaño]]="Pequeño",30,IF(PRIORIDAD_UNO[[#This Row],[Tamaño]]="Mediano",66,IF(PRIORIDAD_UNO[[#This Row],[Tamaño]]="Grande",110,IF(PRIORIDAD_UNO[[#This Row],[Tamaño]]="Extra Grande",154,176)))), FERIADOS[Fecha]), VLOOKUP(PRIORIDAD_UNO[[#This Row],[Nombre del requerimiento]],'Cálculos Manual'!A:F,6,FALSE))) -> 46367 | S6: =IF(PRIORIDAD_UNO[[#This Row],[Fin Desarrollo]]="","",IF(ISBLANK(VLOOKUP(PRIORIDAD_UNO[[#This Row],[Nombre del requerimiento]],'Cálculos Manual'!A:H,8,FALSE)),WORKDAY(PRIORIDAD_UNO[[#This Row],[Fin Desarrollo]],5,FERIADOS[Fecha]), VLOOKUP(PRIORIDAD_UNO[[#This Row],[Nombre del requerimiento]],'Cálculos Manual'!A:H,8,FALSE))) -> 46374 | T6: =IF(PRIORIDAD_UNO[[#This Row],[Comienzo Calidad]]="","",IF(ISBLANK(VLOOKUP(PRIORIDAD_UNO[[#This Row],[Nombre del requerimiento]],'Cálculos Manual'!A:J,10,FALSE)), WORKDAY(PRIORIDAD_UNO[[#This Row],[Comienzo Calidad]],IF(PRIORIDAD_UNO[[#This Row],[Tamaño]]="Pequeño",30,IF(PRIORIDAD_UNO[[#This Row],[Tamaño]]="Mediano",40,50)),FERIADOS[Fecha]), VLOOKUP(PRIORIDAD_UNO[[#This Row],[Nombre del requerimiento]],'Cálculos Manual'!A:J,10,FALSE))) -> 46448 | U6: =IF(PRIORIDAD_UNO[[#This Row],[Fin Calidad]]="","",IF(ISBLANK(VLOOKUP(PRIORIDAD_UNO[[#This Row],[Nombre del requerimiento]],'Cálculos Manual'!A:L,12,FALSE)), WORKDAY(PRIORIDAD_UNO[[#This Row],[Fin Calidad]],5,FERIADOS[Fecha]), VLOOKUP(PRIORIDAD_UNO[[#This Row],[Nombre del requerimiento]],'Cálculos Manual'!A:L,12,FALSE))) -> 46455 | V6: =IF(PRIORIDAD_UNO[[#This Row],[Comienzo Producción]]="","",IF(ISBLANK(VLOOKUP(PRIORIDAD_UNO[[#This Row],[Nombre del requerimiento]],'Cálculos Manual'!A:N,14,FALSE)), WORKDAY(PRIORIDAD_UNO[[#This Row],[Comienzo Producción]],IF(PRIORIDAD_UNO[[#This Row],[Tamaño]]="Grande",10,5),FERIADOS[Fecha]), VLOOKUP(PRIORIDAD_UNO[[#This Row],[Nombre del requerimiento]],'Cálculos Manual'!A:N,14,FALSE))) -> 46469 | W6: =IFERROR(PRIORIDAD_UNO[[#This Row],[Fin Producción]]-PRIORIDAD_UNO[[#This Row],[Comienzo Desarrollo]],"") -> 265 | X6: =IF(ISBLANK(PRIORIDAD_UNO[[#This Row],[Comienzo Desarrollo]]),"Sin Fecha","Con Fecha") -> Con Fecha | Y6: =IF(PRIORIDAD_UNO[[#This Row],[Esfuerzo Estimado Desarrollo]]="No definido","Sin esfuerzo","Con esfuerzo") -> Con esfuerzo | Z6: =IF(ISBLANK(PRIORIDAD_UNO[[#This Row],[Comienzo Desarrollo]]),"🔵 Sin Fecha", IF(PRIORIDAD_UNO[[#This Row],[Comienzo Desarrollo]]<TODAY(),"🔴 Vencido", IF(PRIORIDAD_UNO[[#This Row],[Comienzo Desarrollo]]=TODAY(),"🟡 Vence hoy", IF((PRIORIDAD_UNO[[#This Row],[Comienzo Desarrollo]]-TODAY())<=5,"🟠 Por vencer", "🟢 A tiempo")))) -> 🟢 A tiempo | AA6: =IF(PRIORIDAD_UNO[[#This Row],[Comienzo Producción]]="","Por Definir",_xlfn.CONCAT(YEAR(PRIORIDAD_UNO[[#This Row],[Comienzo Producción]])," - ", MONTH(PRIORIDAD_UNO[[#This Row],[Comienzo Producción]]))) -> 2027 - 3 | AB6: 3327
A7: VCX el cual reemplaza al edit package - Mandatorio Visa | B7: 1 | C7: 6 | D7: 3 meses | E7: =IF(OR(ISBLANK(PRIORIDAD_UNO[[#This Row],[Esfuerzo Estimado Desarrollo]]),PRIORIDAD_UNO[[#This Row],[Esfuerzo Estimado Desarrollo]]="No definido"),"No definido", IF(VALUE(TRIM(LEFT(PRIORIDAD_UNO[[#This Row],[Esfuerzo Estimado Desarrollo]],2)))<=1,"Pequeño", IF(VALUE(TRIM(LEFT(PRIORIDAD_UNO[[#This Row],[Esfuerzo Estimado Desarrollo]],2)))<=3,"Mediano", IF(VALUE(TRIM(LEFT(PRIORIDAD_UNO[[#This Row],[Esfuerzo Estimado Desarrollo]],2)))<=5,"Grande", IF(VALUE(TRIM(LEFT(PRIORIDAD_UNO[[#This Row],[Esfuerzo Estimado Desarrollo]],2)))<=7,"Extra Grande","Proyecto"))))) -> Mediano | F7: Banca Digital | G7: Canales Alternos | H7: Canales Virtuales | I7: MEMORANDO N° 00000091 -2026-BN/3252 | J7: Sí | K7: Mandatorio | L7: Pendiente de Atención | M7: Sistemas Bancarios | N7: Vladimir Cajavilca | O7: Omar Sarmiento | Q7: 46113 | R7: =IF(OR(PRIORIDAD_UNO[[#This Row],[Tamaño]]="No definido",ISBLANK(PRIORIDAD_UNO[[#This Row],[Comienzo Desarrollo]])),"",IF(ISBLANK( VLOOKUP(PRIORIDAD_UNO[[#This Row],[Nombre del requerimiento]],'Cálculos Manual'!A:F,6,FALSE)), WORKDAY(PRIORIDAD_UNO[[#This Row],[Comienzo Desarrollo]], IF(PRIORIDAD_UNO[[#This Row],[Tamaño]]="Pequeño",30,IF(PRIORIDAD_UNO[[#This Row],[Tamaño]]="Mediano",66,IF(PRIORIDAD_UNO[[#This Row],[Tamaño]]="Grande",110,IF(PRIORIDAD_UNO[[#This Row],[Tamaño]]="Extra Grande",154,176)))), FERIADOS[Fecha]), VLOOKUP(PRIORIDAD_UNO[[#This Row],[Nombre del requerimiento]],'Cálculos Manual'!A:F,6,FALSE))) -> 46211 | S7: =IF(PRIORIDAD_UNO[[#This Row],[Fin Desarrollo]]="","",IF(ISBLANK(VLOOKUP(PRIORIDAD_UNO[[#This Row],[Nombre del requerimiento]],'Cálculos Manual'!A:H,8,FALSE)),WORKDAY(PRIORIDAD_UNO[[#This Row],[Fin Desarrollo]],5,FERIADOS[Fecha]), VLOOKUP(PRIORIDAD_UNO[[#This Row],[Nombre del requerimiento]],'Cálculos Manual'!A:H,8,FALSE))) -> 46218 | T7: =IF(PRIORIDAD_UNO[[#This Row],[Comienzo Calidad]]="","",IF(ISBLANK(VLOOKUP(PRIORIDAD_UNO[[#This Row],[Nombre del requerimiento]],'Cálculos Manual'!A:J,10,FALSE)), WORKDAY(PRIORIDAD_UNO[[#This Row],[Comienzo Calidad]],IF(PRIORIDAD_UNO[[#This Row],[Tamaño]]="Pequeño",30,IF(PRIORIDAD_UNO[[#This Row],[Tamaño]]="Mediano",40,50)),FERIADOS[Fecha]), VLOOKUP(PRIORIDAD_UNO[[#This Row],[Nombre del requerimiento]],'Cálculos Manual'!A:J,10,FALSE))) -> 46280 | U7: =IF(PRIORIDAD_UNO[[#This Row],[Fin Calidad]]="","",IF(ISBLANK(VLOOKUP(PRIORIDAD_UNO[[#This Row],[Nombre del requerimiento]],'Cálculos Manual'!A:L,12,FALSE)), WORKDAY(PRIORIDAD_UNO[[#This Row],[Fin Calidad]],5,FERIADOS[Fecha]), VLOOKUP(PRIORIDAD_UNO[[#This Row],[Nombre del requerimiento]],'Cálculos Manual'!A:L,12,FALSE))) -> 46287 | V7: =IF(PRIORIDAD_UNO[[#This Row],[Comienzo Producción]]="","",IF(ISBLANK(VLOOKUP(PRIORIDAD_UNO[[#This Row],[Nombre del requerimiento]],'Cálculos Manual'!A:N,14,FALSE)), WORKDAY(PRIORIDAD_UNO[[#This Row],[Comienzo Producción]],IF(PRIORIDAD_UNO[[#This Row],[Tamaño]]="Grande",10,5),FERIADOS[Fecha]), VLOOKUP(PRIORIDAD_UNO[[#This Row],[Nombre del requerimiento]],'Cálculos Manual'!A:N,14,FALSE))) -> 46294 | W7: =IFERROR(PRIORIDAD_UNO[[#This Row],[Fin Producción]]-PRIORIDAD_UNO[[#This Row],[Comienzo Desarrollo]],"") -> 181 | X7: =IF(ISBLANK(PRIORIDAD_UNO[[#This Row],[Comienzo Desarrollo]]),"Sin Fecha","Con Fecha") -> Con Fecha | Y7: =IF(PRIORIDAD_UNO[[#This Row],[Esfuerzo Estimado Desarrollo]]="No definido","Sin esfuerzo","Con esfuerzo") -> Con esfuerzo | Z7: =IF(ISBLANK(PRIORIDAD_UNO[[#This Row],[Comienzo Desarrollo]]),"🔵 Sin Fecha", IF(PRIORIDAD_UNO[[#This Row],[Comienzo Desarrollo]]<TODAY(),"🔴 Vencido", IF(PRIORIDAD_UNO[[#This Row],[Comienzo Desarrollo]]=TODAY(),"🟡 Vence hoy", IF((PRIORIDAD_UNO[[#This Row],[Comienzo Desarrollo]]-TODAY())<=5,"🟠 Por vencer", "🟢 A tiempo")))) -> 🔴 Vencido | AA7: =IF(PRIORIDAD_UNO[[#This Row],[Comienzo Producción]]="","Por Definir",_xlfn.CONCAT(YEAR(PRIORIDAD_UNO[[#This Row],[Comienzo Producción]])," - ", MONTH(PRIORIDAD_UNO[[#This Row],[Comienzo Producción]]))) -> 2026 - 9 | AB7: No está
A8: Transferencias Inmediatas Masivas vía CCE | B8: 1 | C8: 14 | D8: 4 meses | E8: =IF(OR(ISBLANK(PRIORIDAD_UNO[[#This Row],[Esfuerzo Estimado Desarrollo]]),PRIORIDAD_UNO[[#This Row],[Esfuerzo Estimado Desarrollo]]="No definido"),"No definido", IF(VALUE(TRIM(LEFT(PRIORIDAD_UNO[[#This Row],[Esfuerzo Estimado Desarrollo]],2)))<=1,"Pequeño", IF(VALUE(TRIM(LEFT(PRIORIDAD_UNO[[#This Row],[Esfuerzo Estimado Desarrollo]],2)))<=3,"Mediano", IF(VALUE(TRIM(LEFT(PRIORIDAD_UNO[[#This Row],[Esfuerzo Estimado Desarrollo]],2)))<=5,"Grande", IF(VALUE(TRIM(LEFT(PRIORIDAD_UNO[[#This Row],[Esfuerzo Estimado Desarrollo]],2)))<=7,"Extra Grande","Proyecto"))))) -> Grande | F8: Operaciones | G8: SubGerencia de Captaciones y Pagaduria | H8: Sistema de Pagos | I8: MEMORANDO N° 00000166 - 2025-BN/3116 | J8: Sí | K8: Recomendación | L8: Pendiente de Atención | M8: Sistemas Bancarios | N8: Waldo Basurto | O8: Junior Quicaño | P8: Anexo 2 indica que es un requerimiento evolutivo. | Q8: 46251 | R8: =IF(OR(PRIORIDAD_UNO[[#This Row],[Tamaño]]="No definido",ISBLANK(PRIORIDAD_UNO[[#This Row],[Comienzo Desarrollo]])),"",IF(ISBLANK( VLOOKUP(PRIORIDAD_UNO[[#This Row],[Nombre del requerimiento]],'Cálculos Manual'!A:F,6,FALSE)), WORKDAY(PRIORIDAD_UNO[[#This Row],[Comienzo Desarrollo]], IF(PRIORIDAD_UNO[[#This Row],[Tamaño]]="Pequeño",30,IF(PRIORIDAD_UNO[[#This Row],[Tamaño]]="Mediano",66,IF(PRIORIDAD_UNO[[#This Row],[Tamaño]]="Grande",110,IF(PRIORIDAD_UNO[[#This Row],[Tamaño]]="Extra Grande",154,176)))), FERIADOS[Fecha]), VLOOKUP(PRIORIDAD_UNO[[#This Row],[Nombre del requerimiento]],'Cálculos Manual'!A:F,6,FALSE))) -> 46412 | S8: =IF(PRIORIDAD_UNO[[#This Row],[Fin Desarrollo]]="","",IF(ISBLANK(VLOOKUP(PRIORIDAD_UNO[[#This Row],[Nombre del requerimiento]],'Cálculos Manual'!A:H,8,FALSE)),WORKDAY(PRIORIDAD_UNO[[#This Row],[Fin Desarrollo]],5,FERIADOS[Fecha]), VLOOKUP(PRIORIDAD_UNO[[#This Row],[Nombre del requerimiento]],'Cálculos Manual'!A:H,8,FALSE))) -> 46419 | T8: =IF(PRIORIDAD_UNO[[#This Row],[Comienzo Calidad]]="","",IF(ISBLANK(VLOOKUP(PRIORIDAD_UNO[[#This Row],[Nombre del requerimiento]],'Cálculos Manual'!A:J,10,FALSE)), WORKDAY(PRIORIDAD_UNO[[#This Row],[Comienzo Calidad]],IF(PRIORIDAD_UNO[[#This Row],[Tamaño]]="Pequeño",30,IF(PRIORIDAD_UNO[[#This Row],[Tamaño]]="Mediano",40,50)),FERIADOS[Fecha]), VLOOKUP(PRIORIDAD_UNO[[#This Row],[Nombre del requerimiento]],'Cálculos Manual'!A:J,10,FALSE))) -> 46491 | U8: =IF(PRIORIDAD_UNO[[#This Row],[Fin Calidad]]="","",IF(ISBLANK(VLOOKUP(PRIORIDAD_UNO[[#This Row],[Nombre del requerimiento]],'Cálculos Manual'!A:L,12,FALSE)), WORKDAY(PRIORIDAD_UNO[[#This Row],[Fin Calidad]],5,FERIADOS[Fecha]), VLOOKUP(PRIORIDAD_UNO[[#This Row],[Nombre del requerimiento]],'Cálculos Manual'!A:L,12,FALSE))) -> 46498 | V8: =IF(PRIORIDAD_UNO[[#This Row],[Comienzo Producción]]="","",IF(ISBLANK(VLOOKUP(PRIORIDAD_UNO[[#This Row],[Nombre del requerimiento]],'Cálculos Manual'!A:N,14,FALSE)), WORKDAY(PRIORIDAD_UNO[[#This Row],[Comienzo Producción]],IF(PRIORIDAD_UNO[[#This Row],[Tamaño]]="Grande",10,5),FERIADOS[Fecha]), VLOOKUP(PRIORIDAD_UNO[[#This Row],[Nombre del requerimiento]],'Cálculos Manual'!A:N,14,FALSE))) -> 46512 | W8: =IFERROR(PRIORIDAD_UNO[[#This Row],[Fin Producción]]-PRIORIDAD_UNO[[#This Row],[Comienzo Desarrollo]],"") -> 261 | X8: =IF(ISBLANK(PRIORIDAD_UNO[[#This Row],[Comienzo Desarrollo]]),"Sin Fecha","Con Fecha") -> Con Fecha | Y8: =IF(PRIORIDAD_UNO[[#This Row],[Esfuerzo Estimado Desarrollo]]="No definido","Sin esfuerzo","Con esfuerzo") -> Con esfuerzo | Z8: =IF(ISBLANK(PRIORIDAD_UNO[[#This Row],[Comienzo Desarrollo]]),"🔵 Sin Fecha", IF(PRIORIDAD_UNO[[#This Row],[Comienzo Desarrollo]]<TODAY(),"🔴 Vencido", IF(PRIORIDAD_UNO[[#This Row],[Comienzo Desarrollo]]=TODAY(),"🟡 Vence hoy", IF((PRIORIDAD_UNO[[#This Row],[Comienzo Desarrollo]]-TODAY())<=5,"🟠 Por vencer", "🟢 A tiempo")))) -> 🟢 A tiempo | AA8: =IF(PRIORIDAD_UNO[[#This Row],[Comienzo Producción]]="","Por Definir",_xlfn.CONCAT(YEAR(PRIORIDAD_UNO[[#This Row],[Comienzo Producción]])," - ", MONTH(PRIORIDAD_UNO[[#This Row],[Comienzo Producción]]))) -> 2027 - 4 | AB8: 3227
A9: Transferencias a contacto hacia Cuentas BN con consulta en Directorio Interno BN (SIX/STI) | B9: 1 | C9: 37 | D9: No definido | E9: =IF(OR(ISBLANK(PRIORIDAD_UNO[[#This Row],[Esfuerzo Estimado Desarrollo]]),PRIORIDAD_UNO[[#This Row],[Esfuerzo Estimado Desarrollo]]="No definido"),"No definido", IF(VALUE(TRIM(LEFT(PRIORIDAD_UNO[[#This Row],[Esfuerzo Estimado Desarrollo]],2)))<=1,"Pequeño", IF(VALUE(TRIM(LEFT(PRIORIDAD_UNO[[#This Row],[Esfuerzo Estimado Desarrollo]],2)))<=3,"Mediano", IF(VALUE(TRIM(LEFT(PRIORIDAD_UNO[[#This Row],[Esfuerzo Estimado Desarrollo]],2)))<=5,"Grande", IF(VALUE(TRIM(LEFT(PRIORIDAD_UNO[[#This Row],[Esfuerzo Estimado Desarrollo]],2)))<=7,"Extra Grande","Proyecto"))))) -> No definido | F9: Operaciones | G9: SubGerencia de Captaciones y Pagaduria | H9: Sistema de Pagos | I9: MEMORANDO N° 00000022 - 2026-BN/3116 | J9: Sí | K9: Evolutivo | L9: Observado | M9: Soluciones Digitales | N9: Mario Carbajo | O9: Junior Quicaño | P9: El tiempo estimado de implementación debe ser evaluado por el Proveedor Novatronic, coordinar con el área usuaria. Una vez nos confirmen la planificación de atención, estimaremos los plazos de atencion BN. | R9: =IF(OR(PRIORIDAD_UNO[[#This Row],[Tamaño]]="No definido",ISBLANK(PRIORIDAD_UNO[[#This Row],[Comienzo Desarrollo]])),"",IF(ISBLANK( VLOOKUP(PRIORIDAD_UNO[[#This Row],[Nombre del requerimiento]],'Cálculos Manual'!A:F,6,FALSE)), WORKDAY(PRIORIDAD_UNO[[#This Row],[Comienzo Desarrollo]], IF(PRIORIDAD_UNO[[#This Row],[Tamaño]]="Pequeño",30,IF(PRIORIDAD_UNO[[#This Row],[Tamaño]]="Mediano",66,IF(PRIORIDAD_UNO[[#This Row],[Tamaño]]="Grande",110,IF(PRIORIDAD_UNO[[#This Row],[Tamaño]]="Extra Grande",154,176)))), FERIADOS[Fecha]), VLOOKUP(PRIORIDAD_UNO[[#This Row],[Nombre del requerimiento]],'Cálculos Manual'!A:F,6,FALSE))) | S9: =IF(PRIORIDAD_UNO[[#This Row],[Fin Desarrollo]]="","",IF(ISBLANK(VLOOKUP(PRIORIDAD_UNO[[#This Row],[Nombre del requerimiento]],'Cálculos Manual'!A:H,8,FALSE)),WORKDAY(PRIORIDAD_UNO[[#This Row],[Fin Desarrollo]],5,FERIADOS[Fecha]), VLOOKUP(PRIORIDAD_UNO[[#This Row],[Nombre del requerimiento]],'Cálculos Manual'!A:H,8,FALSE))) | T9: =IF(PRIORIDAD_UNO[[#This Row],[Comienzo Calidad]]="","",IF(ISBLANK(VLOOKUP(PRIORIDAD_UNO[[#This Row],[Nombre del requerimiento]],'Cálculos Manual'!A:J,10,FALSE)), WORKDAY(PRIORIDAD_UNO[[#This Row],[Comienzo Calidad]],IF(PRIORIDAD_UNO[[#This Row],[Tamaño]]="Pequeño",30,IF(PRIORIDAD_UNO[[#This Row],[Tamaño]]="Mediano",40,50)),FERIADOS[Fecha]), VLOOKUP(PRIORIDAD_UNO[[#This Row],[Nombre del requerimiento]],'Cálculos Manual'!A:J,10,FALSE))) | U9: =IF(PRIORIDAD_UNO[[#This Row],[Fin Calidad]]="","",IF(ISBLANK(VLOOKUP(PRIORIDAD_UNO[[#This Row],[Nombre del requerimiento]],'Cálculos Manual'!A:L,12,FALSE)), WORKDAY(PRIORIDAD_UNO[[#This Row],[Fin Calidad]],5,FERIADOS[Fecha]), VLOOKUP(PRIORIDAD_UNO[[#This Row],[Nombre del requerimiento]],'Cálculos Manual'!A:L,12,FALSE))) | V9: =IF(PRIORIDAD_UNO[[#This Row],[Comienzo Producción]]="","",IF(ISBLANK(VLOOKUP(PRIORIDAD_UNO[[#This Row],[Nombre del requerimiento]],'Cálculos Manual'!A:N,14,FALSE)), WORKDAY(PRIORIDAD_UNO[[#This Row],[Comienzo Producción]],IF(PRIORIDAD_UNO[[#This Row],[Tamaño]]="Grande",10,5),FERIADOS[Fecha]), VLOOKUP(PRIORIDAD_UNO[[#This Row],[Nombre del requerimiento]],'Cálculos Manual'!A:N,14,FALSE))) | W9: =IFERROR(PRIORIDAD_UNO[[#This Row],[Fin Producción]]-PRIORIDAD_UNO[[#This Row],[Comienzo Desarrollo]],"") | X9: =IF(ISBLANK(PRIORIDAD_UNO[[#This Row],[Comienzo Desarrollo]]),"Sin Fecha","Con Fecha") -> Sin Fecha | Y9: =IF(PRIORIDAD_UNO[[#This Row],[Esfuerzo Estimado Desarrollo]]="No definido","Sin esfuerzo","Con esfuerzo") -> Sin esfuerzo | Z9: =IF(ISBLANK(PRIORIDAD_UNO[[#This Row],[Comienzo Desarrollo]]),"🔵 Sin Fecha", IF(PRIORIDAD_UNO[[#This Row],[Comienzo Desarrollo]]<TODAY(),"🔴 Vencido", IF(PRIORIDAD_UNO[[#This Row],[Comienzo Desarrollo]]=TODAY(),"🟡 Vence hoy", IF((PRIORIDAD_UNO[[#This Row],[Comienzo Desarrollo]]-TODAY())<=5,"🟠 Por vencer", "🟢 A tiempo")))) -> 🔵 Sin Fecha | AA9: =IF(PRIORIDAD_UNO[[#This Row],[Comienzo Producción]]="","Por Definir",_xlfn.CONCAT(YEAR(PRIORIDAD_UNO[[#This Row],[Comienzo Producción]])," - ", MONTH(PRIORIDAD_UNO[[#This Row],[Comienzo Producción]]))) -> Por Definir | AB9: No está
A10: Tasas preferenciales para Tarjeta de Crédito | B10: 1 | C10: 14 | D10: 3 meses | E10: =IF(OR(ISBLANK(PRIORIDAD_UNO[[#This Row],[Esfuerzo Estimado Desarrollo]]),PRIORIDAD_UNO[[#This Row],[Esfuerzo Estimado Desarrollo]]="No definido"),"No definido", IF(VALUE(TRIM(LEFT(PRIORIDAD_UNO[[#This Row],[Esfuerzo Estimado Desarrollo]],2)))<=1,"Pequeño", IF(VALUE(TRIM(LEFT(PRIORIDAD_UNO[[#This Row],[Esfuerzo Estimado Desarrollo]],2)))<=3,"Mediano", IF(VALUE(TRIM(LEFT(PRIORIDAD_UNO[[#This Row],[Esfuerzo Estimado Desarrollo]],2)))<=5,"Grande", IF(VALUE(TRIM(LEFT(PRIORIDAD_UNO[[#This Row],[Esfuerzo Estimado Desarrollo]],2)))<=7,"Extra Grande","Proyecto"))))) -> Mediano | F10: Productos e Inclusión Financiera | G10: Banca Personal | H10: Tarjeta de Crédito | I10: No | J10: Sí | K10: Normativo | L10: Pendiente de Atención | M10: Sistemas Bancarios | N10: Waldo Basurto / Fiorella Galvan | O10: Milagros Huamani | Q10: 46237 | R10: =IF(OR(PRIORIDAD_UNO[[#This Row],[Tamaño]]="No definido",ISBLANK(PRIORIDAD_UNO[[#This Row],[Comienzo Desarrollo]])),"",IF(ISBLANK( VLOOKUP(PRIORIDAD_UNO[[#This Row],[Nombre del requerimiento]],'Cálculos Manual'!A:F,6,FALSE)), WORKDAY(PRIORIDAD_UNO[[#This Row],[Comienzo Desarrollo]], IF(PRIORIDAD_UNO[[#This Row],[Tamaño]]="Pequeño",30,IF(PRIORIDAD_UNO[[#This Row],[Tamaño]]="Mediano",66,IF(PRIORIDAD_UNO[[#This Row],[Tamaño]]="Grande",110,IF(PRIORIDAD_UNO[[#This Row],[Tamaño]]="Extra Grande",154,176)))), FERIADOS[Fecha]), VLOOKUP(PRIORIDAD_UNO[[#This Row],[Nombre del requerimiento]],'Cálculos Manual'!A:F,6,FALSE))) -> 46331 | S10: =IF(PRIORIDAD_UNO[[#This Row],[Fin Desarrollo]]="","",IF(ISBLANK(VLOOKUP(PRIORIDAD_UNO[[#This Row],[Nombre del requerimiento]],'Cálculos Manual'!A:H,8,FALSE)),WORKDAY(PRIORIDAD_UNO[[#This Row],[Fin Desarrollo]],5,FERIADOS[Fecha]), VLOOKUP(PRIORIDAD_UNO[[#This Row],[Nombre del requerimiento]],'Cálculos Manual'!A:H,8,FALSE))) -> 46338 | T10: =IF(PRIORIDAD_UNO[[#This Row],[Comienzo Calidad]]="","",IF(ISBLANK(VLOOKUP(PRIORIDAD_UNO[[#This Row],[Nombre del requerimiento]],'Cálculos Manual'!A:J,10,FALSE)), WORKDAY(PRIORIDAD_UNO[[#This Row],[Comienzo Calidad]],IF(PRIORIDAD_UNO[[#This Row],[Tamaño]]="Pequeño",30,IF(PRIORIDAD_UNO[[#This Row],[Tamaño]]="Mediano",40,50)),FERIADOS[Fecha]), VLOOKUP(PRIORIDAD_UNO[[#This Row],[Nombre del requerimiento]],'Cálculos Manual'!A:J,10,FALSE))) -> 46400 | U10: =IF(PRIORIDAD_UNO[[#This Row],[Fin Calidad]]="","",IF(ISBLANK(VLOOKUP(PRIORIDAD_UNO[[#This Row],[Nombre del requerimiento]],'Cálculos Manual'!A:L,12,FALSE)), WORKDAY(PRIORIDAD_UNO[[#This Row],[Fin Calidad]],5,FERIADOS[Fecha]), VLOOKUP(PRIORIDAD_UNO[[#This Row],[Nombre del requerimiento]],'Cálculos Manual'!A:L,12,FALSE))) -> 46407 | V10: =IF(PRIORIDAD_UNO[[#This Row],[Comienzo Producción]]="","",IF(ISBLANK(VLOOKUP(PRIORIDAD_UNO[[#This Row],[Nombre del requerimiento]],'Cálculos Manual'!A:N,14,FALSE)), WORKDAY(PRIORIDAD_UNO[[#This Row],[Comienzo Producción]],IF(PRIORIDAD_UNO[[#This Row],[Tamaño]]="Grande",10,5),FERIADOS[Fecha]), VLOOKUP(PRIORIDAD_UNO[[#This Row],[Nombre del requerimiento]],'Cálculos Manual'!A:N,14,FALSE))) -> 46414 | W10: =IFERROR(PRIORIDAD_UNO[[#This Row],[Fin Producción]]-PRIORIDAD_UNO[[#This Row],[Comienzo Desarrollo]],"") -> 177 | X10: =IF(ISBLANK(PRIORIDAD_UNO[[#This Row],[Comienzo Desarrollo]]),"Sin Fecha","Con Fecha") -> Con Fecha | Y10: =IF(PRIORIDAD_UNO[[#This Row],[Esfuerzo Estimado Desarrollo]]="No definido","Sin esfuerzo","Con esfuerzo") -> Con esfuerzo | Z10: =IF(ISBLANK(PRIORIDAD_UNO[[#This Row],[Comienzo Desarrollo]]),"🔵 Sin Fecha", IF(PRIORIDAD_UNO[[#This Row],[Comienzo Desarrollo]]<TODAY(),"🔴 Vencido", IF(PRIORIDAD_UNO[[#This Row],[Comienzo Desarrollo]]=TODAY(),"🟡 Vence hoy", IF((PRIORIDAD_UNO[[#This Row],[Comienzo Desarrollo]]-TODAY())<=5,"🟠 Por vencer", "🟢 A tiempo")))) -> 🟢 A tiempo | AA10: =IF(PRIORIDAD_UNO[[#This Row],[Comienzo Producción]]="","Por Definir",_xlfn.CONCAT(YEAR(PRIORIDAD_UNO[[#This Row],[Comienzo Producción]])," - ", MONTH(PRIORIDAD_UNO[[#This Row],[Comienzo Producción]]))) -> 2027 - 1 | AB10: No está
A11: Solución integral a los casos de duplicidad de apertura de cuentas de Ahorro y casos de clientes sin datos y cuentas cruzadas | B11: 1 | C11: 19 | D11: 3 meses | E11: =IF(OR(ISBLANK(PRIORIDAD_UNO[[#This Row],[Esfuerzo Estimado Desarrollo]]),PRIORIDAD_UNO[[#This Row],[Esfuerzo Estimado Desarrollo]]="No definido"),"No definido", IF(VALUE(TRIM(LEFT(PRIORIDAD_UNO[[#This Row],[Esfuerzo Estimado Desarrollo]],2)))<=1,"Pequeño", IF(VALUE(TRIM(LEFT(PRIORIDAD_UNO[[#This Row],[Esfuerzo Estimado Desarrollo]],2)))<=3,"Mediano", IF(VALUE(TRIM(LEFT(PRIORIDAD_UNO[[#This Row],[Esfuerzo Estimado Desarrollo]],2)))<=5,"Grande", IF(VALUE(TRIM(LEFT(PRIORIDAD_UNO[[#This Row],[Esfuerzo Estimado Desarrollo]],2)))<=7,"Extra Grande","Proyecto"))))) -> Mediano | F11: Operaciones | G11: SubGerencia de Captaciones y Pagaduria | H11: Apertura de Cuentas | I11: MEMORANDO N° 00000364 - 2026-BN/3111 (Decía 2025) | J11: Sí | K11: Recomendación | L11: Pendiente de Atención | M11: Sistemas Bancarios | N11: Jhonny Rooca / Norma Fukunaga | O11: Junior Quicaño | P11: Recomendación: Falta sello. | Q11: 46223 | R11: =IF(OR(PRIORIDAD_UNO[[#This Row],[Tamaño]]="No definido",ISBLANK(PRIORIDAD_UNO[[#This Row],[Comienzo Desarrollo]])),"",IF(ISBLANK( VLOOKUP(PRIORIDAD_UNO[[#This Row],[Nombre del requerimiento]],'Cálculos Manual'!A:F,6,FALSE)), WORKDAY(PRIORIDAD_UNO[[#This Row],[Comienzo Desarrollo]], IF(PRIORIDAD_UNO[[#This Row],[Tamaño]]="Pequeño",30,IF(PRIORIDAD_UNO[[#This Row],[Tamaño]]="Mediano",66,IF(PRIORIDAD_UNO[[#This Row],[Tamaño]]="Grande",110,IF(PRIORIDAD_UNO[[#This Row],[Tamaño]]="Extra Grande",154,176)))), FERIADOS[Fecha]), VLOOKUP(PRIORIDAD_UNO[[#This Row],[Nombre del requerimiento]],'Cálculos Manual'!A:F,6,FALSE))) -> 46322 | S11: =IF(PRIORIDAD_UNO[[#This Row],[Fin Desarrollo]]="","",IF(ISBLANK(VLOOKUP(PRIORIDAD_UNO[[#This Row],[Nombre del requerimiento]],'Cálculos Manual'!A:H,8,FALSE)),WORKDAY(PRIORIDAD_UNO[[#This Row],[Fin Desarrollo]],5,FERIADOS[Fecha]), VLOOKUP(PRIORIDAD_UNO[[#This Row],[Nombre del requerimiento]],'Cálculos Manual'!A:H,8,FALSE))) -> 46329 | T11: =IF(PRIORIDAD_UNO[[#This Row],[Comienzo Calidad]]="","",IF(ISBLANK(VLOOKUP(PRIORIDAD_UNO[[#This Row],[Nombre del requerimiento]],'Cálculos Manual'!A:J,10,FALSE)), WORKDAY(PRIORIDAD_UNO[[#This Row],[Comienzo Calidad]],IF(PRIORIDAD_UNO[[#This Row],[Tamaño]]="Pequeño",30,IF(PRIORIDAD_UNO[[#This Row],[Tamaño]]="Mediano",40,50)),FERIADOS[Fecha]), VLOOKUP(PRIORIDAD_UNO[[#This Row],[Nombre del requerimiento]],'Cálculos Manual'!A:J,10,FALSE))) -> 46391 | U11: =IF(PRIORIDAD_UNO[[#This Row],[Fin Calidad]]="","",IF(ISBLANK(VLOOKUP(PRIORIDAD_UNO[[#This Row],[Nombre del requerimiento]],'Cálculos Manual'!A:L,12,FALSE)), WORKDAY(PRIORIDAD_UNO[[#This Row],[Fin Calidad]],5,FERIADOS[Fecha]), VLOOKUP(PRIORIDAD_UNO[[#This Row],[Nombre del requerimiento]],'Cálculos Manual'!A:L,12,FALSE))) -> 46398 | V11: =IF(PRIORIDAD_UNO[[#This Row],[Comienzo Producción]]="","",IF(ISBLANK(VLOOKUP(PRIORIDAD_UNO[[#This Row],[Nombre del requerimiento]],'Cálculos Manual'!A:N,14,FALSE)), WORKDAY(PRIORIDAD_UNO[[#This Row],[Comienzo Producción]],IF(PRIORIDAD_UNO[[#This Row],[Tamaño]]="Grande",10,5),FERIADOS[Fecha]), VLOOKUP(PRIORIDAD_UNO[[#This Row],[Nombre del requerimiento]],'Cálculos Manual'!A:N,14,FALSE))) -> 46405 | W11: =IFERROR(PRIORIDAD_UNO[[#This Row],[Fin Producción]]-PRIORIDAD_UNO[[#This Row],[Comienzo Desarrollo]],"") -> 182 | X11: =IF(ISBLANK(PRIORIDAD_UNO[[#This Row],[Comienzo Desarrollo]]),"Sin Fecha","Con Fecha") -> Con Fecha | Y11: =IF(PRIORIDAD_UNO[[#This Row],[Esfuerzo Estimado Desarrollo]]="No definido","Sin esfuerzo","Con esfuerzo") -> Con esfuerzo | Z11: =IF(ISBLANK(PRIORIDAD_UNO[[#This Row],[Comienzo Desarrollo]]),"🔵 Sin Fecha", IF(PRIORIDAD_UNO[[#This Row],[Comienzo Desarrollo]]<TODAY(),"🔴 Vencido", IF(PRIORIDAD_UNO[[#This Row],[Comienzo Desarrollo]]=TODAY(),"🟡 Vence hoy", IF((PRIORIDAD_UNO[[#This Row],[Comienzo Desarrollo]]-TODAY())<=5,"🟠 Por vencer", "🟢 A tiempo")))) -> 🟢 A tiempo | AA11: =IF(PRIORIDAD_UNO[[#This Row],[Comienzo Producción]]="","Por Definir",_xlfn.CONCAT(YEAR(PRIORIDAD_UNO[[#This Row],[Comienzo Producción]])," - ", MONTH(PRIORIDAD_UNO[[#This Row],[Comienzo Producción]]))) -> 2027 - 1 | AB11: No está
A12: Solicitud de Notificaciones | B12: 1 | C12: 1 | D12: 4 meses | E12: =IF(OR(ISBLANK(PRIORIDAD_UNO[[#This Row],[Esfuerzo Estimado Desarrollo]]),PRIORIDAD_UNO[[#This Row],[Esfuerzo Estimado Desarrollo]]="No definido"),"No definido", IF(VALUE(TRIM(LEFT(PRIORIDAD_UNO[[#This Row],[Esfuerzo Estimado Desarrollo]],2)))<=1,"Pequeño", IF(VALUE(TRIM(LEFT(PRIORIDAD_UNO[[#This Row],[Esfuerzo Estimado Desarrollo]],2)))<=3,"Mediano", IF(VALUE(TRIM(LEFT(PRIORIDAD_UNO[[#This Row],[Esfuerzo Estimado Desarrollo]],2)))<=5,"Grande", IF(VALUE(TRIM(LEFT(PRIORIDAD_UNO[[#This Row],[Esfuerzo Estimado Desarrollo]],2)))<=7,"Extra Grande","Proyecto"))))) -> Grande | F12: Banca Digital | G12: Canales Alternos | H12: Canales Virtuales | I12: MEMORANDO N° 00000518 - 2025-BN/3252 | J12: Sí | K12: Evolutivo | L12: Pendiente de Atención | M12: Soluciones Digitales | N12: Mario Carbajo | O12: Omar Sarmiento | Q12: 46204 | R12: =IF(OR(PRIORIDAD_UNO[[#This Row],[Tamaño]]="No definido",ISBLANK(PRIORIDAD_UNO[[#This Row],[Comienzo Desarrollo]])),"",IF(ISBLANK( VLOOKUP(PRIORIDAD_UNO[[#This Row],[Nombre del requerimiento]],'Cálculos Manual'!A:F,6,FALSE)), WORKDAY(PRIORIDAD_UNO[[#This Row],[Comienzo Desarrollo]], IF(PRIORIDAD_UNO[[#This Row],[Tamaño]]="Pequeño",30,IF(PRIORIDAD_UNO[[#This Row],[Tamaño]]="Mediano",66,IF(PRIORIDAD_UNO[[#This Row],[Tamaño]]="Grande",110,IF(PRIORIDAD_UNO[[#This Row],[Tamaño]]="Extra Grande",154,176)))), FERIADOS[Fecha]), VLOOKUP(PRIORIDAD_UNO[[#This Row],[Nombre del requerimiento]],'Cálculos Manual'!A:F,6,FALSE))) -> 46367 | S12: =IF(PRIORIDAD_UNO[[#This Row],[Fin Desarrollo]]="","",IF(ISBLANK(VLOOKUP(PRIORIDAD_UNO[[#This Row],[Nombre del requerimiento]],'Cálculos Manual'!A:H,8,FALSE)),WORKDAY(PRIORIDAD_UNO[[#This Row],[Fin Desarrollo]],5,FERIADOS[Fecha]), VLOOKUP(PRIORIDAD_UNO[[#This Row],[Nombre del requerimiento]],'Cálculos Manual'!A:H,8,FALSE))) -> 46374 | T12: =IF(PRIORIDAD_UNO[[#This Row],[Comienzo Calidad]]="","",IF(ISBLANK(VLOOKUP(PRIORIDAD_UNO[[#This Row],[Nombre del requerimiento]],'Cálculos Manual'!A:J,10,FALSE)), WORKDAY(PRIORIDAD_UNO[[#This Row],[Comienzo Calidad]],IF(PRIORIDAD_UNO[[#This Row],[Tamaño]]="Pequeño",30,IF(PRIORIDAD_UNO[[#This Row],[Tamaño]]="Mediano",40,50)),FERIADOS[Fecha]), VLOOKUP(PRIORIDAD_UNO[[#This Row],[Nombre del requerimiento]],'Cálculos Manual'!A:J,10,FALSE))) -> 46448 | U12: =IF(PRIORIDAD_UNO[[#This Row],[Fin Calidad]]="","",IF(ISBLANK(VLOOKUP(PRIORIDAD_UNO[[#This Row],[Nombre del requerimiento]],'Cálculos Manual'!A:L,12,FALSE)), WORKDAY(PRIORIDAD_UNO[[#This Row],[Fin Calidad]],5,FERIADOS[Fecha]), VLOOKUP(PRIORIDAD_UNO[[#This Row],[Nombre del requerimiento]],'Cálculos Manual'!A:L,12,FALSE))) -> 46455 | V12: =IF(PRIORIDAD_UNO[[#This Row],[Comienzo Producción]]="","",IF(ISBLANK(VLOOKUP(PRIORIDAD_UNO[[#This Row],[Nombre del requerimiento]],'Cálculos Manual'!A:N,14,FALSE)), WORKDAY(PRIORIDAD_UNO[[#This Row],[Comienzo Producción]],IF(PRIORIDAD_UNO[[#This Row],[Tamaño]]="Grande",10,5),FERIADOS[Fecha]), VLOOKUP(PRIORIDAD_UNO[[#This Row],[Nombre del requerimiento]],'Cálculos Manual'!A:N,14,FALSE))) -> 46469 | W12: =IFERROR(PRIORIDAD_UNO[[#This Row],[Fin Producción]]-PRIORIDAD_UNO[[#This Row],[Comienzo Desarrollo]],"") -> 265 | X12: =IF(ISBLANK(PRIORIDAD_UNO[[#This Row],[Comienzo Desarrollo]]),"Sin Fecha","Con Fecha") -> Con Fecha | Y12: =IF(PRIORIDAD_UNO[[#This Row],[Esfuerzo Estimado Desarrollo]]="No definido","Sin esfuerzo","Con esfuerzo") -> Con esfuerzo | Z12: =IF(ISBLANK(PRIORIDAD_UNO[[#This Row],[Comienzo Desarrollo]]),"🔵 Sin Fecha", IF(PRIORIDAD_UNO[[#This Row],[Comienzo Desarrollo]]<TODAY(),"🔴 Vencido", IF(PRIORIDAD_UNO[[#This Row],[Comienzo Desarrollo]]=TODAY(),"🟡 Vence hoy", IF((PRIORIDAD_UNO[[#This Row],[Comienzo Desarrollo]]-TODAY())<=5,"🟠 Por vencer", "🟢 A tiempo")))) -> 🟢 A tiempo | AA12: =IF(PRIORIDAD_UNO[[#This Row],[Comienzo Producción]]="","Por Definir",_xlfn.CONCAT(YEAR(PRIORIDAD_UNO[[#This Row],[Comienzo Producción]])," - ", MONTH(PRIORIDAD_UNO[[#This Row],[Comienzo Producción]]))) -> 2027 - 3 | AB12: 3141
A13: Solicita implementar cobro de comisión Adquirente Internacional VISA por uso en canal ATM del BN (Consultas y Retiros) | B13: 1 | C13: 9 | D13: 4 Meses | E13: =IF(OR(ISBLANK(PRIORIDAD_UNO[[#This Row],[Esfuerzo Estimado Desarrollo]]),PRIORIDAD_UNO[[#This Row],[Esfuerzo Estimado Desarrollo]]="No definido"),"No definido", IF(VALUE(TRIM(LEFT(PRIORIDAD_UNO[[#This Row],[Esfuerzo Estimado Desarrollo]],2)))<=1,"Pequeño", IF(VALUE(TRIM(LEFT(PRIORIDAD_UNO[[#This Row],[Esfuerzo Estimado Desarrollo]],2)))<=3,"Mediano", IF(VALUE(TRIM(LEFT(PRIORIDAD_UNO[[#This Row],[Esfuerzo Estimado Desarrollo]],2)))<=5,"Grande", IF(VALUE(TRIM(LEFT(PRIORIDAD_UNO[[#This Row],[Esfuerzo Estimado Desarrollo]],2)))<=7,"Extra Grande","Proyecto"))))) -> Grande | F13: Banca Digital | G13: Canales Alternos | H13: Canales Presenciales | I13: MEMORANDO N° 00000044 - 2026-BN/3251 | J13: Sí | K13: Correctivo | L13: Pendiente de Atención | M13: Sistemas Bancarios | N13: Vladimir Cajavilca | O13: Omar Sarmiento | Q13: 46266 | R13: =IF(OR(PRIORIDAD_UNO[[#This Row],[Tamaño]]="No definido",ISBLANK(PRIORIDAD_UNO[[#This Row],[Comienzo Desarrollo]])),"",IF(ISBLANK( VLOOKUP(PRIORIDAD_UNO[[#This Row],[Nombre del requerimiento]],'Cálculos Manual'!A:F,6,FALSE)), WORKDAY(PRIORIDAD_UNO[[#This Row],[Comienzo Desarrollo]], IF(PRIORIDAD_UNO[[#This Row],[Tamaño]]="Pequeño",30,IF(PRIORIDAD_UNO[[#This Row],[Tamaño]]="Mediano",66,IF(PRIORIDAD_UNO[[#This Row],[Tamaño]]="Grande",110,IF(PRIORIDAD_UNO[[#This Row],[Tamaño]]="Extra Grande",154,176)))), FERIADOS[Fecha]), VLOOKUP(PRIORIDAD_UNO[[#This Row],[Nombre del requerimiento]],'Cálculos Manual'!A:F,6,FALSE))) -> 46427 | S13: =IF(PRIORIDAD_UNO[[#This Row],[Fin Desarrollo]]="","",IF(ISBLANK(VLOOKUP(PRIORIDAD_UNO[[#This Row],[Nombre del requerimiento]],'Cálculos Manual'!A:H,8,FALSE)),WORKDAY(PRIORIDAD_UNO[[#This Row],[Fin Desarrollo]],5,FERIADOS[Fecha]), VLOOKUP(PRIORIDAD_UNO[[#This Row],[Nombre del requerimiento]],'Cálculos Manual'!A:H,8,FALSE))) -> 46434 | T13: =IF(PRIORIDAD_UNO[[#This Row],[Comienzo Calidad]]="","",IF(ISBLANK(VLOOKUP(PRIORIDAD_UNO[[#This Row],[Nombre del requerimiento]],'Cálculos Manual'!A:J,10,FALSE)), WORKDAY(PRIORIDAD_UNO[[#This Row],[Comienzo Calidad]],IF(PRIORIDAD_UNO[[#This Row],[Tamaño]]="Pequeño",30,IF(PRIORIDAD_UNO[[#This Row],[Tamaño]]="Mediano",40,50)),FERIADOS[Fecha]), VLOOKUP(PRIORIDAD_UNO[[#This Row],[Nombre del requerimiento]],'Cálculos Manual'!A:J,10,FALSE))) -> 46506 | U13: =IF(PRIORIDAD_UNO[[#This Row],[Fin Calidad]]="","",IF(ISBLANK(VLOOKUP(PRIORIDAD_UNO[[#This Row],[Nombre del requerimiento]],'Cálculos Manual'!A:L,12,FALSE)), WORKDAY(PRIORIDAD_UNO[[#This Row],[Fin Calidad]],5,FERIADOS[Fecha]), VLOOKUP(PRIORIDAD_UNO[[#This Row],[Nombre del requerimiento]],'Cálculos Manual'!A:L,12,FALSE))) -> 46513 | V13: =IF(PRIORIDAD_UNO[[#This Row],[Comienzo Producción]]="","",IF(ISBLANK(VLOOKUP(PRIORIDAD_UNO[[#This Row],[Nombre del requerimiento]],'Cálculos Manual'!A:N,14,FALSE)), WORKDAY(PRIORIDAD_UNO[[#This Row],[Comienzo Producción]],IF(PRIORIDAD_UNO[[#This Row],[Tamaño]]="Grande",10,5),FERIADOS[Fecha]), VLOOKUP(PRIORIDAD_UNO[[#This Row],[Nombre del requerimiento]],'Cálculos Manual'!A:N,14,FALSE))) -> 46527 | W13: =IFERROR(PRIORIDAD_UNO[[#This Row],[Fin Producción]]-PRIORIDAD_UNO[[#This Row],[Comienzo Desarrollo]],"") -> 261 | X13: =IF(ISBLANK(PRIORIDAD_UNO[[#This Row],[Comienzo Desarrollo]]),"Sin Fecha","Con Fecha") -> Con Fecha | Y13: =IF(PRIORIDAD_UNO[[#This Row],[Esfuerzo Estimado Desarrollo]]="No definido","Sin esfuerzo","Con esfuerzo") -> Con esfuerzo | Z13: =IF(ISBLANK(PRIORIDAD_UNO[[#This Row],[Comienzo Desarrollo]]),"🔵 Sin Fecha", IF(PRIORIDAD_UNO[[#This Row],[Comienzo Desarrollo]]<TODAY(),"🔴 Vencido", IF(PRIORIDAD_UNO[[#This Row],[Comienzo Desarrollo]]=TODAY(),"🟡 Vence hoy", IF((PRIORIDAD_UNO[[#This Row],[Comienzo Desarrollo]]-TODAY())<=5,"🟠 Por vencer", "🟢 A tiempo")))) -> 🟢 A tiempo | AA13: =IF(PRIORIDAD_UNO[[#This Row],[Comienzo Producción]]="","Por Definir",_xlfn.CONCAT(YEAR(PRIORIDAD_UNO[[#This Row],[Comienzo Producción]])," - ", MONTH(PRIORIDAD_UNO[[#This Row],[Comienzo Producción]]))) -> 2027 - 5 | AB13: 3200
A14: Sistema Antifraude en el servicio de Transferencias Interbancarias Inmediatas e Interoperabilidad | B14: 1 | C14: 20 | D14: 3 meses | E14: =IF(OR(ISBLANK(PRIORIDAD_UNO[[#This Row],[Esfuerzo Estimado Desarrollo]]),PRIORIDAD_UNO[[#This Row],[Esfuerzo Estimado Desarrollo]]="No definido"),"No definido", IF(VALUE(TRIM(LEFT(PRIORIDAD_UNO[[#This Row],[Esfuerzo Estimado Desarrollo]],2)))<=1,"Pequeño", IF(VALUE(TRIM(LEFT(PRIORIDAD_UNO[[#This Row],[Esfuerzo Estimado Desarrollo]],2)))<=3,"Mediano", IF(VALUE(TRIM(LEFT(PRIORIDAD_UNO[[#This Row],[Esfuerzo Estimado Desarrollo]],2)))<=5,"Grande", IF(VALUE(TRIM(LEFT(PRIORIDAD_UNO[[#This Row],[Esfuerzo Estimado Desarrollo]],2)))<=7,"Extra Grande","Proyecto"))))) -> Mediano | F14: Operaciones | G14: SubGerencia de Captaciones y Pagaduria | H14: Sistema de Pagos | I14: MEMORANDO N° 00000020 - 2026-BN/3116 | J14: Sí | K14: Recomendación | L14: Pendiente de Atención | M14: Soluciones Digitales | N14: Monica Campana | O14: Junior Quicaño | P14: El área usuaria priorizó su atención antes de iniciar el requerimiento de Masivas. Anexo 2 dice evolutivo. | Q14: 46188 | R14: =IF(OR(PRIORIDAD_UNO[[#This Row],[Tamaño]]="No definido",ISBLANK(PRIORIDAD_UNO[[#This Row],[Comienzo Desarrollo]])),"",IF(ISBLANK( VLOOKUP(PRIORIDAD_UNO[[#This Row],[Nombre del requerimiento]],'Cálculos Manual'!A:F,6,FALSE)), WORKDAY(PRIORIDAD_UNO[[#This Row],[Comienzo Desarrollo]], IF(PRIORIDAD_UNO[[#This Row],[Tamaño]]="Pequeño",30,IF(PRIORIDAD_UNO[[#This Row],[Tamaño]]="Mediano",66,IF(PRIORIDAD_UNO[[#This Row],[Tamaño]]="Grande",110,IF(PRIORIDAD_UNO[[#This Row],[Tamaño]]="Extra Grande",154,176)))), FERIADOS[Fecha]), VLOOKUP(PRIORIDAD_UNO[[#This Row],[Nombre del requerimiento]],'Cálculos Manual'!A:F,6,FALSE))) -> 46287 | S14: =IF(PRIORIDAD_UNO[[#This Row],[Fin Desarrollo]]="","",IF(ISBLANK(VLOOKUP(PRIORIDAD_UNO[[#This Row],[Nombre del requerimiento]],'Cálculos Manual'!A:H,8,FALSE)),WORKDAY(PRIORIDAD_UNO[[#This Row],[Fin Desarrollo]],5,FERIADOS[Fecha]), VLOOKUP(PRIORIDAD_UNO[[#This Row],[Nombre del requerimiento]],'Cálculos Manual'!A:H,8,FALSE))) -> 46294 | T14: =IF(PRIORIDAD_UNO[[#This Row],[Comienzo Calidad]]="","",IF(ISBLANK(VLOOKUP(PRIORIDAD_UNO[[#This Row],[Nombre del requerimiento]],'Cálculos Manual'!A:J,10,FALSE)), WORKDAY(PRIORIDAD_UNO[[#This Row],[Comienzo Calidad]],IF(PRIORIDAD_UNO[[#This Row],[Tamaño]]="Pequeño",30,IF(PRIORIDAD_UNO[[#This Row],[Tamaño]]="Mediano",40,50)),FERIADOS[Fecha]), VLOOKUP(PRIORIDAD_UNO[[#This Row],[Nombre del requerimiento]],'Cálculos Manual'!A:J,10,FALSE))) -> 46351 | U14: =IF(PRIORIDAD_UNO[[#This Row],[Fin Calidad]]="","",IF(ISBLANK(VLOOKUP(PRIORIDAD_UNO[[#This Row],[Nombre del requerimiento]],'Cálculos Manual'!A:L,12,FALSE)), WORKDAY(PRIORIDAD_UNO[[#This Row],[Fin Calidad]],5,FERIADOS[Fecha]), VLOOKUP(PRIORIDAD_UNO[[#This Row],[Nombre del requerimiento]],'Cálculos Manual'!A:L,12,FALSE))) -> 46358 | V14: =IF(PRIORIDAD_UNO[[#This Row],[Comienzo Producción]]="","",IF(ISBLANK(VLOOKUP(PRIORIDAD_UNO[[#This Row],[Nombre del requerimiento]],'Cálculos Manual'!A:N,14,FALSE)), WORKDAY(PRIORIDAD_UNO[[#This Row],[Comienzo Producción]],IF(PRIORIDAD_UNO[[#This Row],[Tamaño]]="Grande",10,5),FERIADOS[Fecha]), VLOOKUP(PRIORIDAD_UNO[[#This Row],[Nombre del requerimiento]],'Cálculos Manual'!A:N,14,FALSE))) -> 46367 | W14: =IFERROR(PRIORIDAD_UNO[[#This Row],[Fin Producción]]-PRIORIDAD_UNO[[#This Row],[Comienzo Desarrollo]],"") -> 179 | X14: =IF(ISBLANK(PRIORIDAD_UNO[[#This Row],[Comienzo Desarrollo]]),"Sin Fecha","Con Fecha") -> Con Fecha | Y14: =IF(PRIORIDAD_UNO[[#This Row],[Esfuerzo Estimado Desarrollo]]="No definido","Sin esfuerzo","Con esfuerzo") -> Con esfuerzo | Z14: =IF(ISBLANK(PRIORIDAD_UNO[[#This Row],[Comienzo Desarrollo]]),"🔵 Sin Fecha", IF(PRIORIDAD_UNO[[#This Row],[Comienzo Desarrollo]]<TODAY(),"🔴 Vencido", IF(PRIORIDAD_UNO[[#This Row],[Comienzo Desarrollo]]=TODAY(),"🟡 Vence hoy", IF((PRIORIDAD_UNO[[#This Row],[Comienzo Desarrollo]]-TODAY())<=5,"🟠 Por vencer", "🟢 A tiempo")))) -> 🟠 Por vencer | AA14: =IF(PRIORIDAD_UNO[[#This Row],[Comienzo Producción]]="","Por Definir",_xlfn.CONCAT(YEAR(PRIORIDAD_UNO[[#This Row],[Comienzo Producción]])," - ", MONTH(PRIORIDAD_UNO[[#This Row],[Comienzo Producción]]))) -> 2026 - 12 | AB14: No está
A15: SIRE Registro de Libro Diario | B15: 1 | C15: 3 | D15: 1 mes | E15: =IF(OR(ISBLANK(PRIORIDAD_UNO[[#This Row],[Esfuerzo Estimado Desarrollo]]),PRIORIDAD_UNO[[#This Row],[Esfuerzo Estimado Desarrollo]]="No definido"),"No definido", IF(VALUE(TRIM(LEFT(PRIORIDAD_UNO[[#This Row],[Esfuerzo Estimado Desarrollo]],2)))<=1,"Pequeño", IF(VALUE(TRIM(LEFT(PRIORIDAD_UNO[[#This Row],[Esfuerzo Estimado Desarrollo]],2)))<=3,"Mediano", IF(VALUE(TRIM(LEFT(PRIORIDAD_UNO[[#This Row],[Esfuerzo Estimado Desarrollo]],2)))<=5,"Grande", IF(VALUE(TRIM(LEFT(PRIORIDAD_UNO[[#This Row],[Esfuerzo Estimado Desarrollo]],2)))<=7,"Extra Grande","Proyecto"))))) -> Pequeño | F15: Finanzas y Tesorería | G15: Contabilidad | H15: Centralización y Procesamiento Contable | I15: MEMORANDO N° 00000006 - 2026-BN6215 | J15: Sí | K15: Normativo | L15: Pendiente de Atención | M15: Sistemas Administrativos | N15: Emerson Quecara | O15: Juan Carlos Zavaleta | P15: Equipo técnico en elaboración de crnograma | Q15: 46183 | R15: =IF(OR(PRIORIDAD_UNO[[#This Row],[Tamaño]]="No definido",ISBLANK(PRIORIDAD_UNO[[#This Row],[Comienzo Desarrollo]])),"",IF(ISBLANK( VLOOKUP(PRIORIDAD_UNO[[#This Row],[Nombre del requerimiento]],'Cálculos Manual'!A:F,6,FALSE)), WORKDAY(PRIORIDAD_UNO[[#This Row],[Comienzo Desarrollo]], IF(PRIORIDAD_UNO[[#This Row],[Tamaño]]="Pequeño",30,IF(PRIORIDAD_UNO[[#This Row],[Tamaño]]="Mediano",66,IF(PRIORIDAD_UNO[[#This Row],[Tamaño]]="Grande",110,IF(PRIORIDAD_UNO[[#This Row],[Tamaño]]="Extra Grande",154,176)))), FERIADOS[Fecha]), VLOOKUP(PRIORIDAD_UNO[[#This Row],[Nombre del requerimiento]],'Cálculos Manual'!A:F,6,FALSE))) -> 46227 | S15: =IF(PRIORIDAD_UNO[[#This Row],[Fin Desarrollo]]="","",IF(ISBLANK(VLOOKUP(PRIORIDAD_UNO[[#This Row],[Nombre del requerimiento]],'Cálculos Manual'!A:H,8,FALSE)),WORKDAY(PRIORIDAD_UNO[[#This Row],[Fin Desarrollo]],5,FERIADOS[Fecha]), VLOOKUP(PRIORIDAD_UNO[[#This Row],[Nombre del requerimiento]],'Cálculos Manual'!A:H,8,FALSE))) -> 46238 | T15: =IF(PRIORIDAD_UNO[[#This Row],[Comienzo Calidad]]="","",IF(ISBLANK(VLOOKUP(PRIORIDAD_UNO[[#This Row],[Nombre del requerimiento]],'Cálculos Manual'!A:J,10,FALSE)), WORKDAY(PRIORIDAD_UNO[[#This Row],[Comienzo Calidad]],IF(PRIORIDAD_UNO[[#This Row],[Tamaño]]="Pequeño",30,IF(PRIORIDAD_UNO[[#This Row],[Tamaño]]="Mediano",40,50)),FERIADOS[Fecha]), VLOOKUP(PRIORIDAD_UNO[[#This Row],[Nombre del requerimiento]],'Cálculos Manual'!A:J,10,FALSE))) -> 46281 | U15: =IF(PRIORIDAD_UNO[[#This Row],[Fin Calidad]]="","",IF(ISBLANK(VLOOKUP(PRIORIDAD_UNO[[#This Row],[Nombre del requerimiento]],'Cálculos Manual'!A:L,12,FALSE)), WORKDAY(PRIORIDAD_UNO[[#This Row],[Fin Calidad]],5,FERIADOS[Fecha]), VLOOKUP(PRIORIDAD_UNO[[#This Row],[Nombre del requerimiento]],'Cálculos Manual'!A:L,12,FALSE))) -> 46288 | V15: =IF(PRIORIDAD_UNO[[#This Row],[Comienzo Producción]]="","",IF(ISBLANK(VLOOKUP(PRIORIDAD_UNO[[#This Row],[Nombre del requerimiento]],'Cálculos Manual'!A:N,14,FALSE)), WORKDAY(PRIORIDAD_UNO[[#This Row],[Comienzo Producción]],IF(PRIORIDAD_UNO[[#This Row],[Tamaño]]="Grande",10,5),FERIADOS[Fecha]), VLOOKUP(PRIORIDAD_UNO[[#This Row],[Nombre del requerimiento]],'Cálculos Manual'!A:N,14,FALSE))) -> 46295 | W15: =IFERROR(PRIORIDAD_UNO[[#This Row],[Fin Producción]]-PRIORIDAD_UNO[[#This Row],[Comienzo Desarrollo]],"") -> 112 | X15: =IF(ISBLANK(PRIORIDAD_UNO[[#This Row],[Comienzo Desarrollo]]),"Sin Fecha","Con Fecha") -> Con Fecha | Y15: =IF(PRIORIDAD_UNO[[#This Row],[Esfuerzo Estimado Desarrollo]]="No definido","Sin esfuerzo","Con esfuerzo") -> Con esfuerzo | Z15: =IF(ISBLANK(PRIORIDAD_UNO[[#This Row],[Comienzo Desarrollo]]),"🔵 Sin Fecha", IF(PRIORIDAD_UNO[[#This Row],[Comienzo Desarrollo]]<TODAY(),"🔴 Vencido", IF(PRIORIDAD_UNO[[#This Row],[Comienzo Desarrollo]]=TODAY(),"🟡 Vence hoy", IF((PRIORIDAD_UNO[[#This Row],[Comienzo Desarrollo]]-TODAY())<=5,"🟠 Por vencer", "🟢 A tiempo")))) -> 🔴 Vencido | AA15: =IF(PRIORIDAD_UNO[[#This Row],[Comienzo Producción]]="","Por Definir",_xlfn.CONCAT(YEAR(PRIORIDAD_UNO[[#This Row],[Comienzo Producción]])," - ", MONTH(PRIORIDAD_UNO[[#This Row],[Comienzo Producción]]))) -> 2026 - 9 | AB15: 3265
A16: Separación funcional operativa contable de las remesas ATMs BN e islas Lima entre las Secciones Caja y Canales Presenciales. | B16: 1 | C16: 43 | D16: 7 meses | E16: =IF(OR(ISBLANK(PRIORIDAD_UNO[[#This Row],[Esfuerzo Estimado Desarrollo]]),PRIORIDAD_UNO[[#This Row],[Esfuerzo Estimado Desarrollo]]="No definido"),"No definido", IF(VALUE(TRIM(LEFT(PRIORIDAD_UNO[[#This Row],[Esfuerzo Estimado Desarrollo]],2)))<=1,"Pequeño", IF(VALUE(TRIM(LEFT(PRIORIDAD_UNO[[#This Row],[Esfuerzo Estimado Desarrollo]],2)))<=3,"Mediano", IF(VALUE(TRIM(LEFT(PRIORIDAD_UNO[[#This Row],[Esfuerzo Estimado Desarrollo]],2)))<=5,"Grande", IF(VALUE(TRIM(LEFT(PRIORIDAD_UNO[[#This Row],[Esfuerzo Estimado Desarrollo]],2)))<=7,"Extra Grande","Proyecto"))))) -> Extra Grande | F16: Operaciones | G16: Subgerencia Caja y Valores | H16: Caja y Valores en Custodia | I16: MEMORANDO N° 00000034 - 2026-BN/3131 | J16: Sí | K16: Evolutivo | L16: Pendiente de Atención | M16: Sistemas Administrativos | N16: Ricardo Cuba | O16: Junior Quicaño | Q16: 46300 | R16: =IF(OR(PRIORIDAD_UNO[[#This Row],[Tamaño]]="No definido",ISBLANK(PRIORIDAD_UNO[[#This Row],[Comienzo Desarrollo]])),"",IF(ISBLANK( VLOOKUP(PRIORIDAD_UNO[[#This Row],[Nombre del requerimiento]],'Cálculos Manual'!A:F,6,FALSE)), WORKDAY(PRIORIDAD_UNO[[#This Row],[Comienzo Desarrollo]], IF(PRIORIDAD_UNO[[#This Row],[Tamaño]]="Pequeño",30,IF(PRIORIDAD_UNO[[#This Row],[Tamaño]]="Mediano",66,IF(PRIORIDAD_UNO[[#This Row],[Tamaño]]="Grande",110,IF(PRIORIDAD_UNO[[#This Row],[Tamaño]]="Extra Grande",154,176)))), FERIADOS[Fecha]), VLOOKUP(PRIORIDAD_UNO[[#This Row],[Nombre del requerimiento]],'Cálculos Manual'!A:F,6,FALSE))) -> 46525 | S16: =IF(PRIORIDAD_UNO[[#This Row],[Fin Desarrollo]]="","",IF(ISBLANK(VLOOKUP(PRIORIDAD_UNO[[#This Row],[Nombre del requerimiento]],'Cálculos Manual'!A:H,8,FALSE)),WORKDAY(PRIORIDAD_UNO[[#This Row],[Fin Desarrollo]],5,FERIADOS[Fecha]), VLOOKUP(PRIORIDAD_UNO[[#This Row],[Nombre del requerimiento]],'Cálculos Manual'!A:H,8,FALSE))) -> 46532 | T16: =IF(PRIORIDAD_UNO[[#This Row],[Comienzo Calidad]]="","",IF(ISBLANK(VLOOKUP(PRIORIDAD_UNO[[#This Row],[Nombre del requerimiento]],'Cálculos Manual'!A:J,10,FALSE)), WORKDAY(PRIORIDAD_UNO[[#This Row],[Comienzo Calidad]],IF(PRIORIDAD_UNO[[#This Row],[Tamaño]]="Pequeño",30,IF(PRIORIDAD_UNO[[#This Row],[Tamaño]]="Mediano",40,50)),FERIADOS[Fecha]), VLOOKUP(PRIORIDAD_UNO[[#This Row],[Nombre del requerimiento]],'Cálculos Manual'!A:J,10,FALSE))) -> 46610 | U16: =IF(PRIORIDAD_UNO[[#This Row],[Fin Calidad]]="","",IF(ISBLANK(VLOOKUP(PRIORIDAD_UNO[[#This Row],[Nombre del requerimiento]],'Cálculos Manual'!A:L,12,FALSE)), WORKDAY(PRIORIDAD_UNO[[#This Row],[Fin Calidad]],5,FERIADOS[Fecha]), VLOOKUP(PRIORIDAD_UNO[[#This Row],[Nombre del requerimiento]],'Cálculos Manual'!A:L,12,FALSE))) -> 46617 | V16: =IF(PRIORIDAD_UNO[[#This Row],[Comienzo Producción]]="","",IF(ISBLANK(VLOOKUP(PRIORIDAD_UNO[[#This Row],[Nombre del requerimiento]],'Cálculos Manual'!A:N,14,FALSE)), WORKDAY(PRIORIDAD_UNO[[#This Row],[Comienzo Producción]],IF(PRIORIDAD_UNO[[#This Row],[Tamaño]]="Grande",10,5),FERIADOS[Fecha]), VLOOKUP(PRIORIDAD_UNO[[#This Row],[Nombre del requerimiento]],'Cálculos Manual'!A:N,14,FALSE))) -> 46624 | W16: =IFERROR(PRIORIDAD_UNO[[#This Row],[Fin Producción]]-PRIORIDAD_UNO[[#This Row],[Comienzo Desarrollo]],"") -> 324 | X16: =IF(ISBLANK(PRIORIDAD_UNO[[#This Row],[Comienzo Desarrollo]]),"Sin Fecha","Con Fecha") -> Con Fecha | Y16: =IF(PRIORIDAD_UNO[[#This Row],[Esfuerzo Estimado Desarrollo]]="No definido","Sin esfuerzo","Con esfuerzo") -> Con esfuerzo | Z16: =IF(ISBLANK(PRIORIDAD_UNO[[#This Row],[Comienzo Desarrollo]]),"🔵 Sin Fecha", IF(PRIORIDAD_UNO[[#This Row],[Comienzo Desarrollo]]<TODAY(),"🔴 Vencido", IF(PRIORIDAD_UNO[[#This Row],[Comienzo Desarrollo]]=TODAY(),"🟡 Vence hoy", IF((PRIORIDAD_UNO[[#This Row],[Comienzo Desarrollo]]-TODAY())<=5,"🟠 Por vencer", "🟢 A tiempo")))) -> 🟢 A tiempo | AA16: =IF(PRIORIDAD_UNO[[#This Row],[Comienzo Producción]]="","Por Definir",_xlfn.CONCAT(YEAR(PRIORIDAD_UNO[[#This Row],[Comienzo Producción]])," - ", MONTH(PRIORIDAD_UNO[[#This Row],[Comienzo Producción]]))) -> 2027 - 8 | AB16: 3247
A17: Rporte mensual de saldos de prestamos Multired conforme a los lineamientos del 16c Ratio de Financiación Neta estable | B17: 1 | C17: 6 | D17: 2 meses | E17: =IF(OR(ISBLANK(PRIORIDAD_UNO[[#This Row],[Esfuerzo Estimado Desarrollo]]),PRIORIDAD_UNO[[#This Row],[Esfuerzo Estimado Desarrollo]]="No definido"),"No definido", IF(VALUE(TRIM(LEFT(PRIORIDAD_UNO[[#This Row],[Esfuerzo Estimado Desarrollo]],2)))<=1,"Pequeño", IF(VALUE(TRIM(LEFT(PRIORIDAD_UNO[[#This Row],[Esfuerzo Estimado Desarrollo]],2)))<=3,"Mediano", IF(VALUE(TRIM(LEFT(PRIORIDAD_UNO[[#This Row],[Esfuerzo Estimado Desarrollo]],2)))<=5,"Grande", IF(VALUE(TRIM(LEFT(PRIORIDAD_UNO[[#This Row],[Esfuerzo Estimado Desarrollo]],2)))<=7,"Extra Grande","Proyecto"))))) -> Mediano | F17: Riesgos | G17: Riesgos Crediticios y Financieros | H17: Riesgos Financieros | I17: MEMORANDO N° 00000024 - 2026-BN/2193 | J17: Sí | K17: Normativo | L17: Pendiente de Atención | M17: Sistemas Bancarios | N17: Fiorella Galván | O17: María Barboza | Q17: 46237 | R17: =IF(OR(PRIORIDAD_UNO[[#This Row],[Tamaño]]="No definido",ISBLANK(PRIORIDAD_UNO[[#This Row],[Comienzo Desarrollo]])),"",IF(ISBLANK( VLOOKUP(PRIORIDAD_UNO[[#This Row],[Nombre del requerimiento]],'Cálculos Manual'!A:F,6,FALSE)), WORKDAY(PRIORIDAD_UNO[[#This Row],[Comienzo Desarrollo]], IF(PRIORIDAD_UNO[[#This Row],[Tamaño]]="Pequeño",30,IF(PRIORIDAD_UNO[[#This Row],[Tamaño]]="Mediano",66,IF(PRIORIDAD_UNO[[#This Row],[Tamaño]]="Grande",110,IF(PRIORIDAD_UNO[[#This Row],[Tamaño]]="Extra Grande",154,176)))), FERIADOS[Fecha]), VLOOKUP(PRIORIDAD_UNO[[#This Row],[Nombre del requerimiento]],'Cálculos Manual'!A:F,6,FALSE))) -> 46331 | S17: =IF(PRIORIDAD_UNO[[#This Row],[Fin Desarrollo]]="","",IF(ISBLANK(VLOOKUP(PRIORIDAD_UNO[[#This Row],[Nombre del requerimiento]],'Cálculos Manual'!A:H,8,FALSE)),WORKDAY(PRIORIDAD_UNO[[#This Row],[Fin Desarrollo]],5,FERIADOS[Fecha]), VLOOKUP(PRIORIDAD_UNO[[#This Row],[Nombre del requerimiento]],'Cálculos Manual'!A:H,8,FALSE))) -> 46338 | T17: =IF(PRIORIDAD_UNO[[#This Row],[Comienzo Calidad]]="","",IF(ISBLANK(VLOOKUP(PRIORIDAD_UNO[[#This Row],[Nombre del requerimiento]],'Cálculos Manual'!A:J,10,FALSE)), WORKDAY(PRIORIDAD_UNO[[#This Row],[Comienzo Calidad]],IF(PRIORIDAD_UNO[[#This Row],[Tamaño]]="Pequeño",30,IF(PRIORIDAD_UNO[[#This Row],[Tamaño]]="Mediano",40,50)),FERIADOS[Fecha]), VLOOKUP(PRIORIDAD_UNO[[#This Row],[Nombre del requerimiento]],'Cálculos Manual'!A:J,10,FALSE))) -> 46400 | U17: =IF(PRIORIDAD_UNO[[#This Row],[Fin Calidad]]="","",IF(ISBLANK(VLOOKUP(PRIORIDAD_UNO[[#This Row],[Nombre del requerimiento]],'Cálculos Manual'!A:L,12,FALSE)), WORKDAY(PRIORIDAD_UNO[[#This Row],[Fin Calidad]],5,FERIADOS[Fecha]), VLOOKUP(PRIORIDAD_UNO[[#This Row],[Nombre del requerimiento]],'Cálculos Manual'!A:L,12,FALSE))) -> 46407 | V17: =IF(PRIORIDAD_UNO[[#This Row],[Comienzo Producción]]="","",IF(ISBLANK(VLOOKUP(PRIORIDAD_UNO[[#This Row],[Nombre del requerimiento]],'Cálculos Manual'!A:N,14,FALSE)), WORKDAY(PRIORIDAD_UNO[[#This Row],[Comienzo Producción]],IF(PRIORIDAD_UNO[[#This Row],[Tamaño]]="Grande",10,5),FERIADOS[Fecha]), VLOOKUP(PRIORIDAD_UNO[[#This Row],[Nombre del requerimiento]],'Cálculos Manual'!A:N,14,FALSE))) -> 46414 | W17: =IFERROR(PRIORIDAD_UNO[[#This Row],[Fin Producción]]-PRIORIDAD_UNO[[#This Row],[Comienzo Desarrollo]],"") -> 177 | X17: =IF(ISBLANK(PRIORIDAD_UNO[[#This Row],[Comienzo Desarrollo]]),"Sin Fecha","Con Fecha") -> Con Fecha | Y17: =IF(PRIORIDAD_UNO[[#This Row],[Esfuerzo Estimado Desarrollo]]="No definido","Sin esfuerzo","Con esfuerzo") -> Con esfuerzo | Z17: =IF(ISBLANK(PRIORIDAD_UNO[[#This Row],[Comienzo Desarrollo]]),"🔵 Sin Fecha", IF(PRIORIDAD_UNO[[#This Row],[Comienzo Desarrollo]]<TODAY(),"🔴 Vencido", IF(PRIORIDAD_UNO[[#This Row],[Comienzo Desarrollo]]=TODAY(),"🟡 Vence hoy", IF((PRIORIDAD_UNO[[#This Row],[Comienzo Desarrollo]]-TODAY())<=5,"🟠 Por vencer", "🟢 A tiempo")))) -> 🟢 A tiempo | AA17: =IF(PRIORIDAD_UNO[[#This Row],[Comienzo Producción]]="","Por Definir",_xlfn.CONCAT(YEAR(PRIORIDAD_UNO[[#This Row],[Comienzo Producción]])," - ", MONTH(PRIORIDAD_UNO[[#This Row],[Comienzo Producción]]))) -> 2027 - 1 | AB17: No está
A18: Reverso automático en el canal Agente BN | B18: 1 | C18: 1 | D18: 2 meses | E18: =IF(OR(ISBLANK(PRIORIDAD_UNO[[#This Row],[Esfuerzo Estimado Desarrollo]]),PRIORIDAD_UNO[[#This Row],[Esfuerzo Estimado Desarrollo]]="No definido"),"No definido", IF(VALUE(TRIM(LEFT(PRIORIDAD_UNO[[#This Row],[Esfuerzo Estimado Desarrollo]],2)))<=1,"Pequeño", IF(VALUE(TRIM(LEFT(PRIORIDAD_UNO[[#This Row],[Esfuerzo Estimado Desarrollo]],2)))<=3,"Mediano", IF(VALUE(TRIM(LEFT(PRIORIDAD_UNO[[#This Row],[Esfuerzo Estimado Desarrollo]],2)))<=5,"Grande", IF(VALUE(TRIM(LEFT(PRIORIDAD_UNO[[#This Row],[Esfuerzo Estimado Desarrollo]],2)))<=7,"Extra Grande","Proyecto"))))) -> Mediano | F18: Banca Digital | G18: Canales Alternos | H18: Canales Presenciales | I18: MEMORANDO N° 00000044 -2026-BN/3251 | J18: Sí | K18: Correctivo | L18: Pendiente de Atención | M18: Sistemas Bancarios | N18: Vladimir Cajavilca | O18: Omar Sarmiento | P18: Backlog ID. 3194 | Q18: 46235 | R18: =IF(OR(PRIORIDAD_UNO[[#This Row],[Tamaño]]="No definido",ISBLANK(PRIORIDAD_UNO[[#This Row],[Comienzo Desarrollo]])),"",IF(ISBLANK( VLOOKUP(PRIORIDAD_UNO[[#This Row],[Nombre del requerimiento]],'Cálculos Manual'!A:F,6,FALSE)), WORKDAY(PRIORIDAD_UNO[[#This Row],[Comienzo Desarrollo]], IF(PRIORIDAD_UNO[[#This Row],[Tamaño]]="Pequeño",30,IF(PRIORIDAD_UNO[[#This Row],[Tamaño]]="Mediano",66,IF(PRIORIDAD_UNO[[#This Row],[Tamaño]]="Grande",110,IF(PRIORIDAD_UNO[[#This Row],[Tamaño]]="Extra Grande",154,176)))), FERIADOS[Fecha]), VLOOKUP(PRIORIDAD_UNO[[#This Row],[Nombre del requerimiento]],'Cálculos Manual'!A:F,6,FALSE))) -> 46330 | S18: =IF(PRIORIDAD_UNO[[#This Row],[Fin Desarrollo]]="","",IF(ISBLANK(VLOOKUP(PRIORIDAD_UNO[[#This Row],[Nombre del requerimiento]],'Cálculos Manual'!A:H,8,FALSE)),WORKDAY(PRIORIDAD_UNO[[#This Row],[Fin Desarrollo]],5,FERIADOS[Fecha]), VLOOKUP(PRIORIDAD_UNO[[#This Row],[Nombre del requerimiento]],'Cálculos Manual'!A:H,8,FALSE))) -> 46337 | T18: =IF(PRIORIDAD_UNO[[#This Row],[Comienzo Calidad]]="","",IF(ISBLANK(VLOOKUP(PRIORIDAD_UNO[[#This Row],[Nombre del requerimiento]],'Cálculos Manual'!A:J,10,FALSE)), WORKDAY(PRIORIDAD_UNO[[#This Row],[Comienzo Calidad]],IF(PRIORIDAD_UNO[[#This Row],[Tamaño]]="Pequeño",30,IF(PRIORIDAD_UNO[[#This Row],[Tamaño]]="Mediano",40,50)),FERIADOS[Fecha]), VLOOKUP(PRIORIDAD_UNO[[#This Row],[Nombre del requerimiento]],'Cálculos Manual'!A:J,10,FALSE))) -> 46399 | U18: =IF(PRIORIDAD_UNO[[#This Row],[Fin Calidad]]="","",IF(ISBLANK(VLOOKUP(PRIORIDAD_UNO[[#This Row],[Nombre del requerimiento]],'Cálculos Manual'!A:L,12,FALSE)), WORKDAY(PRIORIDAD_UNO[[#This Row],[Fin Calidad]],5,FERIADOS[Fecha]), VLOOKUP(PRIORIDAD_UNO[[#This Row],[Nombre del requerimiento]],'Cálculos Manual'!A:L,12,FALSE))) -> 46406 | V18: =IF(PRIORIDAD_UNO[[#This Row],[Comienzo Producción]]="","",IF(ISBLANK(VLOOKUP(PRIORIDAD_UNO[[#This Row],[Nombre del requerimiento]],'Cálculos Manual'!A:N,14,FALSE)), WORKDAY(PRIORIDAD_UNO[[#This Row],[Comienzo Producción]],IF(PRIORIDAD_UNO[[#This Row],[Tamaño]]="Grande",10,5),FERIADOS[Fecha]), VLOOKUP(PRIORIDAD_UNO[[#This Row],[Nombre del requerimiento]],'Cálculos Manual'!A:N,14,FALSE))) -> 46413 | W18: =IFERROR(PRIORIDAD_UNO[[#This Row],[Fin Producción]]-PRIORIDAD_UNO[[#This Row],[Comienzo Desarrollo]],"") -> 178 | X18: =IF(ISBLANK(PRIORIDAD_UNO[[#This Row],[Comienzo Desarrollo]]),"Sin Fecha","Con Fecha") -> Con Fecha | Y18: =IF(PRIORIDAD_UNO[[#This Row],[Esfuerzo Estimado Desarrollo]]="No definido","Sin esfuerzo","Con esfuerzo") -> Con esfuerzo | Z18: =IF(ISBLANK(PRIORIDAD_UNO[[#This Row],[Comienzo Desarrollo]]),"🔵 Sin Fecha", IF(PRIORIDAD_UNO[[#This Row],[Comienzo Desarrollo]]<TODAY(),"🔴 Vencido", IF(PRIORIDAD_UNO[[#This Row],[Comienzo Desarrollo]]=TODAY(),"🟡 Vence hoy", IF((PRIORIDAD_UNO[[#This Row],[Comienzo Desarrollo]]-TODAY())<=5,"🟠 Por vencer", "🟢 A tiempo")))) -> 🟢 A tiempo | AA18: =IF(PRIORIDAD_UNO[[#This Row],[Comienzo Producción]]="","Por Definir",_xlfn.CONCAT(YEAR(PRIORIDAD_UNO[[#This Row],[Comienzo Producción]])," - ", MONTH(PRIORIDAD_UNO[[#This Row],[Comienzo Producción]]))) -> 2027 - 1 | AB18: 3194
A19: Requerimiento de incorporación del control dual biométrico en las transacciones del servicio de giros 7510, 7600, 7700 y 7800. Se requiere implementación para atender recomendación de OAI. | B19: 1 | C19: 9 | D19: 3 meses | E19: =IF(OR(ISBLANK(PRIORIDAD_UNO[[#This Row],[Esfuerzo Estimado Desarrollo]]),PRIORIDAD_UNO[[#This Row],[Esfuerzo Estimado Desarrollo]]="No definido"),"No definido", IF(VALUE(TRIM(LEFT(PRIORIDAD_UNO[[#This Row],[Esfuerzo Estimado Desarrollo]],2)))<=1,"Pequeño", IF(VALUE(TRIM(LEFT(PRIORIDAD_UNO[[#This Row],[Esfuerzo Estimado Desarrollo]],2)))<=3,"Mediano", IF(VALUE(TRIM(LEFT(PRIORIDAD_UNO[[#This Row],[Esfuerzo Estimado Desarrollo]],2)))<=5,"Grande", IF(VALUE(TRIM(LEFT(PRIORIDAD_UNO[[#This Row],[Esfuerzo Estimado Desarrollo]],2)))<=7,"Extra Grande","Proyecto"))))) -> Mediano | F19: Operaciones | G19: Servicios Bancarios y Recaudación | H19: Recaudación y Corresponsalía | I19: MEMORANDO N° 00000029 - 2026-BN/3243 | J19: Sí | K19: Recomendación | L19: Pendiente de Atención | M19: Sistemas Bancarios | N19: Rossana Rojas | O19: Junior Quicaño | P19: Recomendación: Sellado. | Q19: 46174 | R19: =IF(OR(PRIORIDAD_UNO[[#This Row],[Tamaño]]="No definido",ISBLANK(PRIORIDAD_UNO[[#This Row],[Comienzo Desarrollo]])),"",IF(ISBLANK( VLOOKUP(PRIORIDAD_UNO[[#This Row],[Nombre del requerimiento]],'Cálculos Manual'!A:F,6,FALSE)), WORKDAY(PRIORIDAD_UNO[[#This Row],[Comienzo Desarrollo]], IF(PRIORIDAD_UNO[[#This Row],[Tamaño]]="Pequeño",30,IF(PRIORIDAD_UNO[[#This Row],[Tamaño]]="Mediano",66,IF(PRIORIDAD_UNO[[#This Row],[Tamaño]]="Grande",110,IF(PRIORIDAD_UNO[[#This Row],[Tamaño]]="Extra Grande",154,176)))), FERIADOS[Fecha]), VLOOKUP(PRIORIDAD_UNO[[#This Row],[Nombre del requerimiento]],'Cálculos Manual'!A:F,6,FALSE))) -> 46273 | S19: =IF(PRIORIDAD_UNO[[#This Row],[Fin Desarrollo]]="","",IF(ISBLANK(VLOOKUP(PRIORIDAD_UNO[[#This Row],[Nombre del requerimiento]],'Cálculos Manual'!A:H,8,FALSE)),WORKDAY(PRIORIDAD_UNO[[#This Row],[Fin Desarrollo]],5,FERIADOS[Fecha]), VLOOKUP(PRIORIDAD_UNO[[#This Row],[Nombre del requerimiento]],'Cálculos Manual'!A:H,8,FALSE))) -> 46280 | T19: =IF(PRIORIDAD_UNO[[#This Row],[Comienzo Calidad]]="","",IF(ISBLANK(VLOOKUP(PRIORIDAD_UNO[[#This Row],[Nombre del requerimiento]],'Cálculos Manual'!A:J,10,FALSE)), WORKDAY(PRIORIDAD_UNO[[#This Row],[Comienzo Calidad]],IF(PRIORIDAD_UNO[[#This Row],[Tamaño]]="Pequeño",30,IF(PRIORIDAD_UNO[[#This Row],[Tamaño]]="Mediano",40,50)),FERIADOS[Fecha]), VLOOKUP(PRIORIDAD_UNO[[#This Row],[Nombre del requerimiento]],'Cálculos Manual'!A:J,10,FALSE))) -> 46337 | U19: =IF(PRIORIDAD_UNO[[#This Row],[Fin Calidad]]="","",IF(ISBLANK(VLOOKUP(PRIORIDAD_UNO[[#This Row],[Nombre del requerimiento]],'Cálculos Manual'!A:L,12,FALSE)), WORKDAY(PRIORIDAD_UNO[[#This Row],[Fin Calidad]],5,FERIADOS[Fecha]), VLOOKUP(PRIORIDAD_UNO[[#This Row],[Nombre del requerimiento]],'Cálculos Manual'!A:L,12,FALSE))) -> 46344 | V19: =IF(PRIORIDAD_UNO[[#This Row],[Comienzo Producción]]="","",IF(ISBLANK(VLOOKUP(PRIORIDAD_UNO[[#This Row],[Nombre del requerimiento]],'Cálculos Manual'!A:N,14,FALSE)), WORKDAY(PRIORIDAD_UNO[[#This Row],[Comienzo Producción]],IF(PRIORIDAD_UNO[[#This Row],[Tamaño]]="Grande",10,5),FERIADOS[Fecha]), VLOOKUP(PRIORIDAD_UNO[[#This Row],[Nombre del requerimiento]],'Cálculos Manual'!A:N,14,FALSE))) -> 46351 | W19: =IFERROR(PRIORIDAD_UNO[[#This Row],[Fin Producción]]-PRIORIDAD_UNO[[#This Row],[Comienzo Desarrollo]],"") -> 177 | X19: =IF(ISBLANK(PRIORIDAD_UNO[[#This Row],[Comienzo Desarrollo]]),"Sin Fecha","Con Fecha") -> Con Fecha | Y19: =IF(PRIORIDAD_UNO[[#This Row],[Esfuerzo Estimado Desarrollo]]="No definido","Sin esfuerzo","Con esfuerzo") -> Con esfuerzo | Z19: =IF(ISBLANK(PRIORIDAD_UNO[[#This Row],[Comienzo Desarrollo]]),"🔵 Sin Fecha", IF(PRIORIDAD_UNO[[#This Row],[Comienzo Desarrollo]]<TODAY(),"🔴 Vencido", IF(PRIORIDAD_UNO[[#This Row],[Comienzo Desarrollo]]=TODAY(),"🟡 Vence hoy", IF((PRIORIDAD_UNO[[#This Row],[Comienzo Desarrollo]]-TODAY())<=5,"🟠 Por vencer", "🟢 A tiempo")))) -> 🔴 Vencido | AA19: =IF(PRIORIDAD_UNO[[#This Row],[Comienzo Producción]]="","Por Definir",_xlfn.CONCAT(YEAR(PRIORIDAD_UNO[[#This Row],[Comienzo Producción]])," - ", MONTH(PRIORIDAD_UNO[[#This Row],[Comienzo Producción]]))) -> 2026 - 11 | AB19: 3241
A20: Reportes por operaciones de reposicion de tarjetas en la red de agencias | B20: 1 | C20: 17 | D20: 2 meses | E20: =IF(OR(ISBLANK(PRIORIDAD_UNO[[#This Row],[Esfuerzo Estimado Desarrollo]]),PRIORIDAD_UNO[[#This Row],[Esfuerzo Estimado Desarrollo]]="No definido"),"No definido", IF(VALUE(TRIM(LEFT(PRIORIDAD_UNO[[#This Row],[Esfuerzo Estimado Desarrollo]],2)))<=1,"Pequeño", IF(VALUE(TRIM(LEFT(PRIORIDAD_UNO[[#This Row],[Esfuerzo Estimado Desarrollo]],2)))<=3,"Mediano", IF(VALUE(TRIM(LEFT(PRIORIDAD_UNO[[#This Row],[Esfuerzo Estimado Desarrollo]],2)))<=5,"Grande", IF(VALUE(TRIM(LEFT(PRIORIDAD_UNO[[#This Row],[Esfuerzo Estimado Desarrollo]],2)))<=7,"Extra Grande","Proyecto"))))) -> Mediano | F20: Banca Digital | G20: Canales Alternos | H20: Canales Virtuales | I20: MEMORANDO N° 00000091 -2026-BN/3252 | J20: Sí | K20: Evolutivo | L20: Pendiente de Atención | M20: Sistemas Bancarios | N20: Waldo Basurto | O20: Omar Sarmiento | Q20: 46238 | R20: =IF(OR(PRIORIDAD_UNO[[#This Row],[Tamaño]]="No definido",ISBLANK(PRIORIDAD_UNO[[#This Row],[Comienzo Desarrollo]])),"",IF(ISBLANK( VLOOKUP(PRIORIDAD_UNO[[#This Row],[Nombre del requerimiento]],'Cálculos Manual'!A:F,6,FALSE)), WORKDAY(PRIORIDAD_UNO[[#This Row],[Comienzo Desarrollo]], IF(PRIORIDAD_UNO[[#This Row],[Tamaño]]="Pequeño",30,IF(PRIORIDAD_UNO[[#This Row],[Tamaño]]="Mediano",66,IF(PRIORIDAD_UNO[[#This Row],[Tamaño]]="Grande",110,IF(PRIORIDAD_UNO[[#This Row],[Tamaño]]="Extra Grande",154,176)))), FERIADOS[Fecha]), VLOOKUP(PRIORIDAD_UNO[[#This Row],[Nombre del requerimiento]],'Cálculos Manual'!A:F,6,FALSE))) -> 46332 | S20: =IF(PRIORIDAD_UNO[[#This Row],[Fin Desarrollo]]="","",IF(ISBLANK(VLOOKUP(PRIORIDAD_UNO[[#This Row],[Nombre del requerimiento]],'Cálculos Manual'!A:H,8,FALSE)),WORKDAY(PRIORIDAD_UNO[[#This Row],[Fin Desarrollo]],5,FERIADOS[Fecha]), VLOOKUP(PRIORIDAD_UNO[[#This Row],[Nombre del requerimiento]],'Cálculos Manual'!A:H,8,FALSE))) -> 46339 | T20: =IF(PRIORIDAD_UNO[[#This Row],[Comienzo Calidad]]="","",IF(ISBLANK(VLOOKUP(PRIORIDAD_UNO[[#This Row],[Nombre del requerimiento]],'Cálculos Manual'!A:J,10,FALSE)), WORKDAY(PRIORIDAD_UNO[[#This Row],[Comienzo Calidad]],IF(PRIORIDAD_UNO[[#This Row],[Tamaño]]="Pequeño",30,IF(PRIORIDAD_UNO[[#This Row],[Tamaño]]="Mediano",40,50)),FERIADOS[Fecha]), VLOOKUP(PRIORIDAD_UNO[[#This Row],[Nombre del requerimiento]],'Cálculos Manual'!A:J,10,FALSE))) -> 46401 | U20: =IF(PRIORIDAD_UNO[[#This Row],[Fin Calidad]]="","",IF(ISBLANK(VLOOKUP(PRIORIDAD_UNO[[#This Row],[Nombre del requerimiento]],'Cálculos Manual'!A:L,12,FALSE)), WORKDAY(PRIORIDAD_UNO[[#This Row],[Fin Calidad]],5,FERIADOS[Fecha]), VLOOKUP(PRIORIDAD_UNO[[#This Row],[Nombre del requerimiento]],'Cálculos Manual'!A:L,12,FALSE))) -> 46408 | V20: =IF(PRIORIDAD_UNO[[#This Row],[Comienzo Producción]]="","",IF(ISBLANK(VLOOKUP(PRIORIDAD_UNO[[#This Row],[Nombre del requerimiento]],'Cálculos Manual'!A:N,14,FALSE)), WORKDAY(PRIORIDAD_UNO[[#This Row],[Comienzo Producción]],IF(PRIORIDAD_UNO[[#This Row],[Tamaño]]="Grande",10,5),FERIADOS[Fecha]), VLOOKUP(PRIORIDAD_UNO[[#This Row],[Nombre del requerimiento]],'Cálculos Manual'!A:N,14,FALSE))) -> 46415 | W20: =IFERROR(PRIORIDAD_UNO[[#This Row],[Fin Producción]]-PRIORIDAD_UNO[[#This Row],[Comienzo Desarrollo]],"") -> 177 | X20: =IF(ISBLANK(PRIORIDAD_UNO[[#This Row],[Comienzo Desarrollo]]),"Sin Fecha","Con Fecha") -> Con Fecha | Y20: =IF(PRIORIDAD_UNO[[#This Row],[Esfuerzo Estimado Desarrollo]]="No definido","Sin esfuerzo","Con esfuerzo") -> Con esfuerzo | Z20: =IF(ISBLANK(PRIORIDAD_UNO[[#This Row],[Comienzo Desarrollo]]),"🔵 Sin Fecha", IF(PRIORIDAD_UNO[[#This Row],[Comienzo Desarrollo]]<TODAY(),"🔴 Vencido", IF(PRIORIDAD_UNO[[#This Row],[Comienzo Desarrollo]]=TODAY(),"🟡 Vence hoy", IF((PRIORIDAD_UNO[[#This Row],[Comienzo Desarrollo]]-TODAY())<=5,"🟠 Por vencer", "🟢 A tiempo")))) -> 🟢 A tiempo | AA20: =IF(PRIORIDAD_UNO[[#This Row],[Comienzo Producción]]="","Por Definir",_xlfn.CONCAT(YEAR(PRIORIDAD_UNO[[#This Row],[Comienzo Producción]])," - ", MONTH(PRIORIDAD_UNO[[#This Row],[Comienzo Producción]]))) -> 2027 - 1 | AB20: 3349
A21: Reporteria de transacciones - 0208, 0201, 0210 | B21: 1 | C21: 2 | D21: 3 meses | E21: =IF(OR(ISBLANK(PRIORIDAD_UNO[[#This Row],[Esfuerzo Estimado Desarrollo]]),PRIORIDAD_UNO[[#This Row],[Esfuerzo Estimado Desarrollo]]="No definido"),"No definido", IF(VALUE(TRIM(LEFT(PRIORIDAD_UNO[[#This Row],[Esfuerzo Estimado Desarrollo]],2)))<=1,"Pequeño", IF(VALUE(TRIM(LEFT(PRIORIDAD_UNO[[#This Row],[Esfuerzo Estimado Desarrollo]],2)))<=3,"Mediano", IF(VALUE(TRIM(LEFT(PRIORIDAD_UNO[[#This Row],[Esfuerzo Estimado Desarrollo]],2)))<=5,"Grande", IF(VALUE(TRIM(LEFT(PRIORIDAD_UNO[[#This Row],[Esfuerzo Estimado Desarrollo]],2)))<=7,"Extra Grande","Proyecto"))))) -> Mediano | F21: Red de Agencias | G21: Red de Agencias | H21: Red de Agencias | I21: MEMORANDO N° 00000322 - 2026-BN/9700 | J21: Sí | K21: Evolutivo | L21: Pendiente de Atención | M21: Sistemas Bancarios | N21: Rossana Rojas | O21: María Barboza | Q21: 46266 | R21: =IF(OR(PRIORIDAD_UNO[[#This Row],[Tamaño]]="No definido",ISBLANK(PRIORIDAD_UNO[[#This Row],[Comienzo Desarrollo]])),"",IF(ISBLANK( VLOOKUP(PRIORIDAD_UNO[[#This Row],[Nombre del requerimiento]],'Cálculos Manual'!A:F,6,FALSE)), WORKDAY(PRIORIDAD_UNO[[#This Row],[Comienzo Desarrollo]], IF(PRIORIDAD_UNO[[#This Row],[Tamaño]]="Pequeño",30,IF(PRIORIDAD_UNO[[#This Row],[Tamaño]]="Mediano",66,IF(PRIORIDAD_UNO[[#This Row],[Tamaño]]="Grande",110,IF(PRIORIDAD_UNO[[#This Row],[Tamaño]]="Extra Grande",154,176)))), FERIADOS[Fecha]), VLOOKUP(PRIORIDAD_UNO[[#This Row],[Nombre del requerimiento]],'Cálculos Manual'!A:F,6,FALSE))) -> 46359 | S21: =IF(PRIORIDAD_UNO[[#This Row],[Fin Desarrollo]]="","",IF(ISBLANK(VLOOKUP(PRIORIDAD_UNO[[#This Row],[Nombre del requerimiento]],'Cálculos Manual'!A:H,8,FALSE)),WORKDAY(PRIORIDAD_UNO[[#This Row],[Fin Desarrollo]],5,FERIADOS[Fecha]), VLOOKUP(PRIORIDAD_UNO[[#This Row],[Nombre del requerimiento]],'Cálculos Manual'!A:H,8,FALSE))) -> 46370 | T21: =IF(PRIORIDAD_UNO[[#This Row],[Comienzo Calidad]]="","",IF(ISBLANK(VLOOKUP(PRIORIDAD_UNO[[#This Row],[Nombre del requerimiento]],'Cálculos Manual'!A:J,10,FALSE)), WORKDAY(PRIORIDAD_UNO[[#This Row],[Comienzo Calidad]],IF(PRIORIDAD_UNO[[#This Row],[Tamaño]]="Pequeño",30,IF(PRIORIDAD_UNO[[#This Row],[Tamaño]]="Mediano",40,50)),FERIADOS[Fecha]), VLOOKUP(PRIORIDAD_UNO[[#This Row],[Nombre del requerimiento]],'Cálculos Manual'!A:J,10,FALSE))) -> 46428 | U21: =IF(PRIORIDAD_UNO[[#This Row],[Fin Calidad]]="","",IF(ISBLANK(VLOOKUP(PRIORIDAD_UNO[[#This Row],[Nombre del requerimiento]],'Cálculos Manual'!A:L,12,FALSE)), WORKDAY(PRIORIDAD_UNO[[#This Row],[Fin Calidad]],5,FERIADOS[Fecha]), VLOOKUP(PRIORIDAD_UNO[[#This Row],[Nombre del requerimiento]],'Cálculos Manual'!A:L,12,FALSE))) -> 46435 | V21: =IF(PRIORIDAD_UNO[[#This Row],[Comienzo Producción]]="","",IF(ISBLANK(VLOOKUP(PRIORIDAD_UNO[[#This Row],[Nombre del requerimiento]],'Cálculos Manual'!A:N,14,FALSE)), WORKDAY(PRIORIDAD_UNO[[#This Row],[Comienzo Producción]],IF(PRIORIDAD_UNO[[#This Row],[Tamaño]]="Grande",10,5),FERIADOS[Fecha]), VLOOKUP(PRIORIDAD_UNO[[#This Row],[Nombre del requerimiento]],'Cálculos Manual'!A:N,14,FALSE))) -> 46442 | W21: =IFERROR(PRIORIDAD_UNO[[#This Row],[Fin Producción]]-PRIORIDAD_UNO[[#This Row],[Comienzo Desarrollo]],"") -> 176 | X21: =IF(ISBLANK(PRIORIDAD_UNO[[#This Row],[Comienzo Desarrollo]]),"Sin Fecha","Con Fecha") -> Con Fecha | Y21: =IF(PRIORIDAD_UNO[[#This Row],[Esfuerzo Estimado Desarrollo]]="No definido","Sin esfuerzo","Con esfuerzo") -> Con esfuerzo | Z21: =IF(ISBLANK(PRIORIDAD_UNO[[#This Row],[Comienzo Desarrollo]]),"🔵 Sin Fecha", IF(PRIORIDAD_UNO[[#This Row],[Comienzo Desarrollo]]<TODAY(),"🔴 Vencido", IF(PRIORIDAD_UNO[[#This Row],[Comienzo Desarrollo]]=TODAY(),"🟡 Vence hoy", IF((PRIORIDAD_UNO[[#This Row],[Comienzo Desarrollo]]-TODAY())<=5,"🟠 Por vencer", "🟢 A tiempo")))) -> 🟢 A tiempo | AA21: =IF(PRIORIDAD_UNO[[#This Row],[Comienzo Producción]]="","Por Definir",_xlfn.CONCAT(YEAR(PRIORIDAD_UNO[[#This Row],[Comienzo Producción]])," - ", MONTH(PRIORIDAD_UNO[[#This Row],[Comienzo Producción]]))) -> 2027 - 2 | AB21: No está
A22: Reporte NRT Control del Fraude | B22: 1 | C22: Por definir | D22: 3 meses | E22: =IF(OR(ISBLANK(PRIORIDAD_UNO[[#This Row],[Esfuerzo Estimado Desarrollo]]),PRIORIDAD_UNO[[#This Row],[Esfuerzo Estimado Desarrollo]]="No definido"),"No definido", IF(VALUE(TRIM(LEFT(PRIORIDAD_UNO[[#This Row],[Esfuerzo Estimado Desarrollo]],2)))<=1,"Pequeño", IF(VALUE(TRIM(LEFT(PRIORIDAD_UNO[[#This Row],[Esfuerzo Estimado Desarrollo]],2)))<=3,"Mediano", IF(VALUE(TRIM(LEFT(PRIORIDAD_UNO[[#This Row],[Esfuerzo Estimado Desarrollo]],2)))<=5,"Grande", IF(VALUE(TRIM(LEFT(PRIORIDAD_UNO[[#This Row],[Esfuerzo Estimado Desarrollo]],2)))<=7,"Extra Grande","Proyecto"))))) -> Mediano | F22: Banca Digital | G22: Canales Alternos | H22: Canales Virtuales | I22: MEMORANDO N° 00000002 - 2026-BN/3252 | J22: Sí | K22: Recomendación | L22: Pendiente de Atención | M22: Sistemas Bancarios | N22: Vladimir Cajavilca | O22: Omar Sarmiento | P22: No tiene definido Orden de Atención | Q22: 46204 | R22: =IF(OR(PRIORIDAD_UNO[[#This Row],[Tamaño]]="No definido",ISBLANK(PRIORIDAD_UNO[[#This Row],[Comienzo Desarrollo]])),"",IF(ISBLANK( VLOOKUP(PRIORIDAD_UNO[[#This Row],[Nombre del requerimiento]],'Cálculos Manual'!A:F,6,FALSE)), WORKDAY(PRIORIDAD_UNO[[#This Row],[Comienzo Desarrollo]], IF(PRIORIDAD_UNO[[#This Row],[Tamaño]]="Pequeño",30,IF(PRIORIDAD_UNO[[#This Row],[Tamaño]]="Mediano",66,IF(PRIORIDAD_UNO[[#This Row],[Tamaño]]="Grande",110,IF(PRIORIDAD_UNO[[#This Row],[Tamaño]]="Extra Grande",154,176)))), FERIADOS[Fecha]), VLOOKUP(PRIORIDAD_UNO[[#This Row],[Nombre del requerimiento]],'Cálculos Manual'!A:F,6,FALSE))) -> 46302 | S22: =IF(PRIORIDAD_UNO[[#This Row],[Fin Desarrollo]]="","",IF(ISBLANK(VLOOKUP(PRIORIDAD_UNO[[#This Row],[Nombre del requerimiento]],'Cálculos Manual'!A:H,8,FALSE)),WORKDAY(PRIORIDAD_UNO[[#This Row],[Fin Desarrollo]],5,FERIADOS[Fecha]), VLOOKUP(PRIORIDAD_UNO[[#This Row],[Nombre del requerimiento]],'Cálculos Manual'!A:H,8,FALSE))) -> 46310 | T22: =IF(PRIORIDAD_UNO[[#This Row],[Comienzo Calidad]]="","",IF(ISBLANK(VLOOKUP(PRIORIDAD_UNO[[#This Row],[Nombre del requerimiento]],'Cálculos Manual'!A:J,10,FALSE)), WORKDAY(PRIORIDAD_UNO[[#This Row],[Comienzo Calidad]],IF(PRIORIDAD_UNO[[#This Row],[Tamaño]]="Pequeño",30,IF(PRIORIDAD_UNO[[#This Row],[Tamaño]]="Mediano",40,50)),FERIADOS[Fecha]), VLOOKUP(PRIORIDAD_UNO[[#This Row],[Nombre del requerimiento]],'Cálculos Manual'!A:J,10,FALSE))) -> 46370 | U22: =IF(PRIORIDAD_UNO[[#This Row],[Fin Calidad]]="","",IF(ISBLANK(VLOOKUP(PRIORIDAD_UNO[[#This Row],[Nombre del requerimiento]],'Cálculos Manual'!A:L,12,FALSE)), WORKDAY(PRIORIDAD_UNO[[#This Row],[Fin Calidad]],5,FERIADOS[Fecha]), VLOOKUP(PRIORIDAD_UNO[[#This Row],[Nombre del requerimiento]],'Cálculos Manual'!A:L,12,FALSE))) -> 46377 | V22: =IF(PRIORIDAD_UNO[[#This Row],[Comienzo Producción]]="","",IF(ISBLANK(VLOOKUP(PRIORIDAD_UNO[[#This Row],[Nombre del requerimiento]],'Cálculos Manual'!A:N,14,FALSE)), WORKDAY(PRIORIDAD_UNO[[#This Row],[Comienzo Producción]],IF(PRIORIDAD_UNO[[#This Row],[Tamaño]]="Grande",10,5),FERIADOS[Fecha]), VLOOKUP(PRIORIDAD_UNO[[#This Row],[Nombre del requerimiento]],'Cálculos Manual'!A:N,14,FALSE))) -> 46385 | W22: =IFERROR(PRIORIDAD_UNO[[#This Row],[Fin Producción]]-PRIORIDAD_UNO[[#This Row],[Comienzo Desarrollo]],"") -> 181 | X22: =IF(ISBLANK(PRIORIDAD_UNO[[#This Row],[Comienzo Desarrollo]]),"Sin Fecha","Con Fecha") -> Con Fecha | Y22: =IF(PRIORIDAD_UNO[[#This Row],[Esfuerzo Estimado Desarrollo]]="No definido","Sin esfuerzo","Con esfuerzo") -> Con esfuerzo | Z22: =IF(ISBLANK(PRIORIDAD_UNO[[#This Row],[Comienzo Desarrollo]]),"🔵 Sin Fecha", IF(PRIORIDAD_UNO[[#This Row],[Comienzo Desarrollo]]<TODAY(),"🔴 Vencido", IF(PRIORIDAD_UNO[[#This Row],[Comienzo Desarrollo]]=TODAY(),"🟡 Vence hoy", IF((PRIORIDAD_UNO[[#This Row],[Comienzo Desarrollo]]-TODAY())<=5,"🟠 Por vencer", "🟢 A tiempo")))) -> 🟢 A tiempo | AA22: =IF(PRIORIDAD_UNO[[#This Row],[Comienzo Producción]]="","Por Definir",_xlfn.CONCAT(YEAR(PRIORIDAD_UNO[[#This Row],[Comienzo Producción]])," - ", MONTH(PRIORIDAD_UNO[[#This Row],[Comienzo Producción]]))) -> 2026 - 12 | AB22: 3187
A23: Reporte detallado de las notificacion de la comunciaciones por transacciones en ATMs | B23: 1 | C23: 11 | D23: 3 meses | E23: =IF(OR(ISBLANK(PRIORIDAD_UNO[[#This Row],[Esfuerzo Estimado Desarrollo]]),PRIORIDAD_UNO[[#This Row],[Esfuerzo Estimado Desarrollo]]="No definido"),"No definido", IF(VALUE(TRIM(LEFT(PRIORIDAD_UNO[[#This Row],[Esfuerzo Estimado Desarrollo]],2)))<=1,"Pequeño", IF(VALUE(TRIM(LEFT(PRIORIDAD_UNO[[#This Row],[Esfuerzo Estimado Desarrollo]],2)))<=3,"Mediano", IF(VALUE(TRIM(LEFT(PRIORIDAD_UNO[[#This Row],[Esfuerzo Estimado Desarrollo]],2)))<=5,"Grande", IF(VALUE(TRIM(LEFT(PRIORIDAD_UNO[[#This Row],[Esfuerzo Estimado Desarrollo]],2)))<=7,"Extra Grande","Proyecto"))))) -> Mediano | F23: Banca Digital | G23: Canales Alternos | H23: Canales Presenciales | I23: MEMORANDO N° 00000044 -2026-BN/3251 | J23: Sí | K23: Evolutivo | L23: Pendiente de Atención | M23: Sistemas Bancarios | N23: Eduardo Cárdenas | O23: Omar Sarmiento | Q23: 46336 | R23: =IF(OR(PRIORIDAD_UNO[[#This Row],[Tamaño]]="No definido",ISBLANK(PRIORIDAD_UNO[[#This Row],[Comienzo Desarrollo]])),"",IF(ISBLANK( VLOOKUP(PRIORIDAD_UNO[[#This Row],[Nombre del requerimiento]],'Cálculos Manual'!A:F,6,FALSE)), WORKDAY(PRIORIDAD_UNO[[#This Row],[Comienzo Desarrollo]], IF(PRIORIDAD_UNO[[#This Row],[Tamaño]]="Pequeño",30,IF(PRIORIDAD_UNO[[#This Row],[Tamaño]]="Mediano",66,IF(PRIORIDAD_UNO[[#This Row],[Tamaño]]="Grande",110,IF(PRIORIDAD_UNO[[#This Row],[Tamaño]]="Extra Grande",154,176)))), FERIADOS[Fecha]), VLOOKUP(PRIORIDAD_UNO[[#This Row],[Nombre del requerimiento]],'Cálculos Manual'!A:F,6,FALSE))) -> 46434 | S23: =IF(PRIORIDAD_UNO[[#This Row],[Fin Desarrollo]]="","",IF(ISBLANK(VLOOKUP(PRIORIDAD_UNO[[#This Row],[Nombre del requerimiento]],'Cálculos Manual'!A:H,8,FALSE)),WORKDAY(PRIORIDAD_UNO[[#This Row],[Fin Desarrollo]],5,FERIADOS[Fecha]), VLOOKUP(PRIORIDAD_UNO[[#This Row],[Nombre del requerimiento]],'Cálculos Manual'!A:H,8,FALSE))) -> 46441 | T23: =IF(PRIORIDAD_UNO[[#This Row],[Comienzo Calidad]]="","",IF(ISBLANK(VLOOKUP(PRIORIDAD_UNO[[#This Row],[Nombre del requerimiento]],'Cálculos Manual'!A:J,10,FALSE)), WORKDAY(PRIORIDAD_UNO[[#This Row],[Comienzo Calidad]],IF(PRIORIDAD_UNO[[#This Row],[Tamaño]]="Pequeño",30,IF(PRIORIDAD_UNO[[#This Row],[Tamaño]]="Mediano",40,50)),FERIADOS[Fecha]), VLOOKUP(PRIORIDAD_UNO[[#This Row],[Nombre del requerimiento]],'Cálculos Manual'!A:J,10,FALSE))) -> 46499 | U23: =IF(PRIORIDAD_UNO[[#This Row],[Fin Calidad]]="","",IF(ISBLANK(VLOOKUP(PRIORIDAD_UNO[[#This Row],[Nombre del requerimiento]],'Cálculos Manual'!A:L,12,FALSE)), WORKDAY(PRIORIDAD_UNO[[#This Row],[Fin Calidad]],5,FERIADOS[Fecha]), VLOOKUP(PRIORIDAD_UNO[[#This Row],[Nombre del requerimiento]],'Cálculos Manual'!A:L,12,FALSE))) -> 46506 | V23: =IF(PRIORIDAD_UNO[[#This Row],[Comienzo Producción]]="","",IF(ISBLANK(VLOOKUP(PRIORIDAD_UNO[[#This Row],[Nombre del requerimiento]],'Cálculos Manual'!A:N,14,FALSE)), WORKDAY(PRIORIDAD_UNO[[#This Row],[Comienzo Producción]],IF(PRIORIDAD_UNO[[#This Row],[Tamaño]]="Grande",10,5),FERIADOS[Fecha]), VLOOKUP(PRIORIDAD_UNO[[#This Row],[Nombre del requerimiento]],'Cálculos Manual'!A:N,14,FALSE))) -> 46513 | W23: =IFERROR(PRIORIDAD_UNO[[#This Row],[Fin Producción]]-PRIORIDAD_UNO[[#This Row],[Comienzo Desarrollo]],"") -> 177 | X23: =IF(ISBLANK(PRIORIDAD_UNO[[#This Row],[Comienzo Desarrollo]]),"Sin Fecha","Con Fecha") -> Con Fecha | Y23: =IF(PRIORIDAD_UNO[[#This Row],[Esfuerzo Estimado Desarrollo]]="No definido","Sin esfuerzo","Con esfuerzo") -> Con esfuerzo | Z23: =IF(ISBLANK(PRIORIDAD_UNO[[#This Row],[Comienzo Desarrollo]]),"🔵 Sin Fecha", IF(PRIORIDAD_UNO[[#This Row],[Comienzo Desarrollo]]<TODAY(),"🔴 Vencido", IF(PRIORIDAD_UNO[[#This Row],[Comienzo Desarrollo]]=TODAY(),"🟡 Vence hoy", IF((PRIORIDAD_UNO[[#This Row],[Comienzo Desarrollo]]-TODAY())<=5,"🟠 Por vencer", "🟢 A tiempo")))) -> 🟢 A tiempo | AA23: =IF(PRIORIDAD_UNO[[#This Row],[Comienzo Producción]]="","Por Definir",_xlfn.CONCAT(YEAR(PRIORIDAD_UNO[[#This Row],[Comienzo Producción]])," - ", MONTH(PRIORIDAD_UNO[[#This Row],[Comienzo Producción]]))) -> 2027 - 4 | AB23: 3196
A24: Reporte detallado de las notificacion de la comunciaciones por transacciones en Agente BN | B24: 1 | C24: 11 | D24: 3 meses | E24: =IF(OR(ISBLANK(PRIORIDAD_UNO[[#This Row],[Esfuerzo Estimado Desarrollo]]),PRIORIDAD_UNO[[#This Row],[Esfuerzo Estimado Desarrollo]]="No definido"),"No definido", IF(VALUE(TRIM(LEFT(PRIORIDAD_UNO[[#This Row],[Esfuerzo Estimado Desarrollo]],2)))<=1,"Pequeño", IF(VALUE(TRIM(LEFT(PRIORIDAD_UNO[[#This Row],[Esfuerzo Estimado Desarrollo]],2)))<=3,"Mediano", IF(VALUE(TRIM(LEFT(PRIORIDAD_UNO[[#This Row],[Esfuerzo Estimado Desarrollo]],2)))<=5,"Grande", IF(VALUE(TRIM(LEFT(PRIORIDAD_UNO[[#This Row],[Esfuerzo Estimado Desarrollo]],2)))<=7,"Extra Grande","Proyecto"))))) -> Mediano | F24: Banca Digital | G24: Canales Alternos | H24: Canales Presenciales | I24: MEMORANDO N° 00000044 -2026-BN/3251 | J24: Sí | K24: Normativo | L24: Pendiente de Atención | M24: Sistemas Bancarios | N24: Eduardo Cárdenas | O24: Omar Sarmiento | Q24: 46329 | R24: =IF(OR(PRIORIDAD_UNO[[#This Row],[Tamaño]]="No definido",ISBLANK(PRIORIDAD_UNO[[#This Row],[Comienzo Desarrollo]])),"",IF(ISBLANK( VLOOKUP(PRIORIDAD_UNO[[#This Row],[Nombre del requerimiento]],'Cálculos Manual'!A:F,6,FALSE)), WORKDAY(PRIORIDAD_UNO[[#This Row],[Comienzo Desarrollo]], IF(PRIORIDAD_UNO[[#This Row],[Tamaño]]="Pequeño",30,IF(PRIORIDAD_UNO[[#This Row],[Tamaño]]="Mediano",66,IF(PRIORIDAD_UNO[[#This Row],[Tamaño]]="Grande",110,IF(PRIORIDAD_UNO[[#This Row],[Tamaño]]="Extra Grande",154,176)))), FERIADOS[Fecha]), VLOOKUP(PRIORIDAD_UNO[[#This Row],[Nombre del requerimiento]],'Cálculos Manual'!A:F,6,FALSE))) -> 46427 | S24: =IF(PRIORIDAD_UNO[[#This Row],[Fin Desarrollo]]="","",IF(ISBLANK(VLOOKUP(PRIORIDAD_UNO[[#This Row],[Nombre del requerimiento]],'Cálculos Manual'!A:H,8,FALSE)),WORKDAY(PRIORIDAD_UNO[[#This Row],[Fin Desarrollo]],5,FERIADOS[Fecha]), VLOOKUP(PRIORIDAD_UNO[[#This Row],[Nombre del requerimiento]],'Cálculos Manual'!A:H,8,FALSE))) -> 46434 | T24: =IF(PRIORIDAD_UNO[[#This Row],[Comienzo Calidad]]="","",IF(ISBLANK(VLOOKUP(PRIORIDAD_UNO[[#This Row],[Nombre del requerimiento]],'Cálculos Manual'!A:J,10,FALSE)), WORKDAY(PRIORIDAD_UNO[[#This Row],[Comienzo Calidad]],IF(PRIORIDAD_UNO[[#This Row],[Tamaño]]="Pequeño",30,IF(PRIORIDAD_UNO[[#This Row],[Tamaño]]="Mediano",40,50)),FERIADOS[Fecha]), VLOOKUP(PRIORIDAD_UNO[[#This Row],[Nombre del requerimiento]],'Cálculos Manual'!A:J,10,FALSE))) -> 46492 | U24: =IF(PRIORIDAD_UNO[[#This Row],[Fin Calidad]]="","",IF(ISBLANK(VLOOKUP(PRIORIDAD_UNO[[#This Row],[Nombre del requerimiento]],'Cálculos Manual'!A:L,12,FALSE)), WORKDAY(PRIORIDAD_UNO[[#This Row],[Fin Calidad]],5,FERIADOS[Fecha]), VLOOKUP(PRIORIDAD_UNO[[#This Row],[Nombre del requerimiento]],'Cálculos Manual'!A:L,12,FALSE))) -> 46499 | V24: =IF(PRIORIDAD_UNO[[#This Row],[Comienzo Producción]]="","",IF(ISBLANK(VLOOKUP(PRIORIDAD_UNO[[#This Row],[Nombre del requerimiento]],'Cálculos Manual'!A:N,14,FALSE)), WORKDAY(PRIORIDAD_UNO[[#This Row],[Comienzo Producción]],IF(PRIORIDAD_UNO[[#This Row],[Tamaño]]="Grande",10,5),FERIADOS[Fecha]), VLOOKUP(PRIORIDAD_UNO[[#This Row],[Nombre del requerimiento]],'Cálculos Manual'!A:N,14,FALSE))) -> 46506 | W24: =IFERROR(PRIORIDAD_UNO[[#This Row],[Fin Producción]]-PRIORIDAD_UNO[[#This Row],[Comienzo Desarrollo]],"") -> 177 | X24: =IF(ISBLANK(PRIORIDAD_UNO[[#This Row],[Comienzo Desarrollo]]),"Sin Fecha","Con Fecha") -> Con Fecha | Y24: =IF(PRIORIDAD_UNO[[#This Row],[Esfuerzo Estimado Desarrollo]]="No definido","Sin esfuerzo","Con esfuerzo") -> Con esfuerzo | Z24: =IF(ISBLANK(PRIORIDAD_UNO[[#This Row],[Comienzo Desarrollo]]),"🔵 Sin Fecha", IF(PRIORIDAD_UNO[[#This Row],[Comienzo Desarrollo]]<TODAY(),"🔴 Vencido", IF(PRIORIDAD_UNO[[#This Row],[Comienzo Desarrollo]]=TODAY(),"🟡 Vence hoy", IF((PRIORIDAD_UNO[[#This Row],[Comienzo Desarrollo]]-TODAY())<=5,"🟠 Por vencer", "🟢 A tiempo")))) -> 🟢 A tiempo | AA24: =IF(PRIORIDAD_UNO[[#This Row],[Comienzo Producción]]="","Por Definir",_xlfn.CONCAT(YEAR(PRIORIDAD_UNO[[#This Row],[Comienzo Producción]])," - ", MONTH(PRIORIDAD_UNO[[#This Row],[Comienzo Producción]]))) -> 2027 - 4 | AB24: 3197
A25: Reporte de Modificaciones de datos de clientes - AUDITORIA EXTERNA | B25: 1 | C25: 27 | D25: 2 meses | E25: =IF(OR(ISBLANK(PRIORIDAD_UNO[[#This Row],[Esfuerzo Estimado Desarrollo]]),PRIORIDAD_UNO[[#This Row],[Esfuerzo Estimado Desarrollo]]="No definido"),"No definido", IF(VALUE(TRIM(LEFT(PRIORIDAD_UNO[[#This Row],[Esfuerzo Estimado Desarrollo]],2)))<=1,"Pequeño", IF(VALUE(TRIM(LEFT(PRIORIDAD_UNO[[#This Row],[Esfuerzo Estimado Desarrollo]],2)))<=3,"Mediano", IF(VALUE(TRIM(LEFT(PRIORIDAD_UNO[[#This Row],[Esfuerzo Estimado Desarrollo]],2)))<=5,"Grande", IF(VALUE(TRIM(LEFT(PRIORIDAD_UNO[[#This Row],[Esfuerzo Estimado Desarrollo]],2)))<=7,"Extra Grande","Proyecto"))))) -> Mediano | F25: Operaciones | G25: SubGerencia de Captaciones y Pagaduria | H25: Apertura de Cuentas | I25: MEMORANDO N° 00000142 - 2026-BN/3111 | J25: Sí | K25: Recomendación | L25: Pendiente de Atención | M25: Sistemas Bancarios | N25: Johnny Rocca | O25: Junior Quicaño | P25: El Anexo 2 indica Evolutivo. | Q25: 46237 | R25: =IF(OR(PRIORIDAD_UNO[[#This Row],[Tamaño]]="No definido",ISBLANK(PRIORIDAD_UNO[[#This Row],[Comienzo Desarrollo]])),"",IF(ISBLANK( VLOOKUP(PRIORIDAD_UNO[[#This Row],[Nombre del requerimiento]],'Cálculos Manual'!A:F,6,FALSE)), WORKDAY(PRIORIDAD_UNO[[#This Row],[Comienzo Desarrollo]], IF(PRIORIDAD_UNO[[#This Row],[Tamaño]]="Pequeño",30,IF(PRIORIDAD_UNO[[#This Row],[Tamaño]]="Mediano",66,IF(PRIORIDAD_UNO[[#This Row],[Tamaño]]="Grande",110,IF(PRIORIDAD_UNO[[#This Row],[Tamaño]]="Extra Grande",154,176)))), FERIADOS[Fecha]), VLOOKUP(PRIORIDAD_UNO[[#This Row],[Nombre del requerimiento]],'Cálculos Manual'!A:F,6,FALSE))) -> 46331 | S25: =IF(PRIORIDAD_UNO[[#This Row],[Fin Desarrollo]]="","",IF(ISBLANK(VLOOKUP(PRIORIDAD_UNO[[#This Row],[Nombre del requerimiento]],'Cálculos Manual'!A:H,8,FALSE)),WORKDAY(PRIORIDAD_UNO[[#This Row],[Fin Desarrollo]],5,FERIADOS[Fecha]), VLOOKUP(PRIORIDAD_UNO[[#This Row],[Nombre del requerimiento]],'Cálculos Manual'!A:H,8,FALSE))) -> 46338 | T25: =IF(PRIORIDAD_UNO[[#This Row],[Comienzo Calidad]]="","",IF(ISBLANK(VLOOKUP(PRIORIDAD_UNO[[#This Row],[Nombre del requerimiento]],'Cálculos Manual'!A:J,10,FALSE)), WORKDAY(PRIORIDAD_UNO[[#This Row],[Comienzo Calidad]],IF(PRIORIDAD_UNO[[#This Row],[Tamaño]]="Pequeño",30,IF(PRIORIDAD_UNO[[#This Row],[Tamaño]]="Mediano",40,50)),FERIADOS[Fecha]), VLOOKUP(PRIORIDAD_UNO[[#This Row],[Nombre del requerimiento]],'Cálculos Manual'!A:J,10,FALSE))) -> 46400 | U25: =IF(PRIORIDAD_UNO[[#This Row],[Fin Calidad]]="","",IF(ISBLANK(VLOOKUP(PRIORIDAD_UNO[[#This Row],[Nombre del requerimiento]],'Cálculos Manual'!A:L,12,FALSE)), WORKDAY(PRIORIDAD_UNO[[#This Row],[Fin Calidad]],5,FERIADOS[Fecha]), VLOOKUP(PRIORIDAD_UNO[[#This Row],[Nombre del requerimiento]],'Cálculos Manual'!A:L,12,FALSE))) -> 46407 | V25: =IF(PRIORIDAD_UNO[[#This Row],[Comienzo Producción]]="","",IF(ISBLANK(VLOOKUP(PRIORIDAD_UNO[[#This Row],[Nombre del requerimiento]],'Cálculos Manual'!A:N,14,FALSE)), WORKDAY(PRIORIDAD_UNO[[#This Row],[Comienzo Producción]],IF(PRIORIDAD_UNO[[#This Row],[Tamaño]]="Grande",10,5),FERIADOS[Fecha]), VLOOKUP(PRIORIDAD_UNO[[#This Row],[Nombre del requerimiento]],'Cálculos Manual'!A:N,14,FALSE))) -> 46414 | W25: =IFERROR(PRIORIDAD_UNO[[#This Row],[Fin Producción]]-PRIORIDAD_UNO[[#This Row],[Comienzo Desarrollo]],"") -> 177 | X25: =IF(ISBLANK(PRIORIDAD_UNO[[#This Row],[Comienzo Desarrollo]]),"Sin Fecha","Con Fecha") -> Con Fecha | Y25: =IF(PRIORIDAD_UNO[[#This Row],[Esfuerzo Estimado Desarrollo]]="No definido","Sin esfuerzo","Con esfuerzo") -> Con esfuerzo | Z25: =IF(ISBLANK(PRIORIDAD_UNO[[#This Row],[Comienzo Desarrollo]]),"🔵 Sin Fecha", IF(PRIORIDAD_UNO[[#This Row],[Comienzo Desarrollo]]<TODAY(),"🔴 Vencido", IF(PRIORIDAD_UNO[[#This Row],[Comienzo Desarrollo]]=TODAY(),"🟡 Vence hoy", IF((PRIORIDAD_UNO[[#This Row],[Comienzo Desarrollo]]-TODAY())<=5,"🟠 Por vencer", "🟢 A tiempo")))) -> 🟢 A tiempo | AA25: =IF(PRIORIDAD_UNO[[#This Row],[Comienzo Producción]]="","Por Definir",_xlfn.CONCAT(YEAR(PRIORIDAD_UNO[[#This Row],[Comienzo Producción]])," - ", MONTH(PRIORIDAD_UNO[[#This Row],[Comienzo Producción]]))) -> 2027 - 1 | AB25: No está
A26: Reporte de la funcionalidad del Canal ATM | B26: 1 | C26: 5 | D26: 3 meses | E26: =IF(OR(ISBLANK(PRIORIDAD_UNO[[#This Row],[Esfuerzo Estimado Desarrollo]]),PRIORIDAD_UNO[[#This Row],[Esfuerzo Estimado Desarrollo]]="No definido"),"No definido", IF(VALUE(TRIM(LEFT(PRIORIDAD_UNO[[#This Row],[Esfuerzo Estimado Desarrollo]],2)))<=1,"Pequeño", IF(VALUE(TRIM(LEFT(PRIORIDAD_UNO[[#This Row],[Esfuerzo Estimado Desarrollo]],2)))<=3,"Mediano", IF(VALUE(TRIM(LEFT(PRIORIDAD_UNO[[#This Row],[Esfuerzo Estimado Desarrollo]],2)))<=5,"Grande", IF(VALUE(TRIM(LEFT(PRIORIDAD_UNO[[#This Row],[Esfuerzo Estimado Desarrollo]],2)))<=7,"Extra Grande","Proyecto"))))) -> Mediano | F26: Banca Digital | G26: Canales Alternos | H26: Canales Presenciales | I26: MEMORANDO N° 00000044 -2026-BN/3251 | J26: Sí | K26: Normativo | L26: Pendiente de Atención | M26: Sistemas Bancarios | N26: Herbert Rojas | O26: Omar Sarmiento | Q26: 46252 | R26: =IF(OR(PRIORIDAD_UNO[[#This Row],[Tamaño]]="No definido",ISBLANK(PRIORIDAD_UNO[[#This Row],[Comienzo Desarrollo]])),"",IF(ISBLANK( VLOOKUP(PRIORIDAD_UNO[[#This Row],[Nombre del requerimiento]],'Cálculos Manual'!A:F,6,FALSE)), WORKDAY(PRIORIDAD_UNO[[#This Row],[Comienzo Desarrollo]], IF(PRIORIDAD_UNO[[#This Row],[Tamaño]]="Pequeño",30,IF(PRIORIDAD_UNO[[#This Row],[Tamaño]]="Mediano",66,IF(PRIORIDAD_UNO[[#This Row],[Tamaño]]="Grande",110,IF(PRIORIDAD_UNO[[#This Row],[Tamaño]]="Extra Grande",154,176)))), FERIADOS[Fecha]), VLOOKUP(PRIORIDAD_UNO[[#This Row],[Nombre del requerimiento]],'Cálculos Manual'!A:F,6,FALSE))) -> 46345 | S26: =IF(PRIORIDAD_UNO[[#This Row],[Fin Desarrollo]]="","",IF(ISBLANK(VLOOKUP(PRIORIDAD_UNO[[#This Row],[Nombre del requerimiento]],'Cálculos Manual'!A:H,8,FALSE)),WORKDAY(PRIORIDAD_UNO[[#This Row],[Fin Desarrollo]],5,FERIADOS[Fecha]), VLOOKUP(PRIORIDAD_UNO[[#This Row],[Nombre del requerimiento]],'Cálculos Manual'!A:H,8,FALSE))) -> 46352 | T26: =IF(PRIORIDAD_UNO[[#This Row],[Comienzo Calidad]]="","",IF(ISBLANK(VLOOKUP(PRIORIDAD_UNO[[#This Row],[Nombre del requerimiento]],'Cálculos Manual'!A:J,10,FALSE)), WORKDAY(PRIORIDAD_UNO[[#This Row],[Comienzo Calidad]],IF(PRIORIDAD_UNO[[#This Row],[Tamaño]]="Pequeño",30,IF(PRIORIDAD_UNO[[#This Row],[Tamaño]]="Mediano",40,50)),FERIADOS[Fecha]), VLOOKUP(PRIORIDAD_UNO[[#This Row],[Nombre del requerimiento]],'Cálculos Manual'!A:J,10,FALSE))) -> 46414 | U26: =IF(PRIORIDAD_UNO[[#This Row],[Fin Calidad]]="","",IF(ISBLANK(VLOOKUP(PRIORIDAD_UNO[[#This Row],[Nombre del requerimiento]],'Cálculos Manual'!A:L,12,FALSE)), WORKDAY(PRIORIDAD_UNO[[#This Row],[Fin Calidad]],5,FERIADOS[Fecha]), VLOOKUP(PRIORIDAD_UNO[[#This Row],[Nombre del requerimiento]],'Cálculos Manual'!A:L,12,FALSE))) -> 46421 | V26: =IF(PRIORIDAD_UNO[[#This Row],[Comienzo Producción]]="","",IF(ISBLANK(VLOOKUP(PRIORIDAD_UNO[[#This Row],[Nombre del requerimiento]],'Cálculos Manual'!A:N,14,FALSE)), WORKDAY(PRIORIDAD_UNO[[#This Row],[Comienzo Producción]],IF(PRIORIDAD_UNO[[#This Row],[Tamaño]]="Grande",10,5),FERIADOS[Fecha]), VLOOKUP(PRIORIDAD_UNO[[#This Row],[Nombre del requerimiento]],'Cálculos Manual'!A:N,14,FALSE))) -> 46428 | W26: =IFERROR(PRIORIDAD_UNO[[#This Row],[Fin Producción]]-PRIORIDAD_UNO[[#This Row],[Comienzo Desarrollo]],"") -> 176 | X26: =IF(ISBLANK(PRIORIDAD_UNO[[#This Row],[Comienzo Desarrollo]]),"Sin Fecha","Con Fecha") -> Con Fecha | Y26: =IF(PRIORIDAD_UNO[[#This Row],[Esfuerzo Estimado Desarrollo]]="No definido","Sin esfuerzo","Con esfuerzo") -> Con esfuerzo | Z26: =IF(ISBLANK(PRIORIDAD_UNO[[#This Row],[Comienzo Desarrollo]]),"🔵 Sin Fecha", IF(PRIORIDAD_UNO[[#This Row],[Comienzo Desarrollo]]<TODAY(),"🔴 Vencido", IF(PRIORIDAD_UNO[[#This Row],[Comienzo Desarrollo]]=TODAY(),"🟡 Vence hoy", IF((PRIORIDAD_UNO[[#This Row],[Comienzo Desarrollo]]-TODAY())<=5,"🟠 Por vencer", "🟢 A tiempo")))) -> 🟢 A tiempo | AA26: =IF(PRIORIDAD_UNO[[#This Row],[Comienzo Producción]]="","Por Definir",_xlfn.CONCAT(YEAR(PRIORIDAD_UNO[[#This Row],[Comienzo Producción]])," - ", MONTH(PRIORIDAD_UNO[[#This Row],[Comienzo Producción]]))) -> 2027 - 2 | AB26: No está
A27: Reporte de la funcionalidad del Canal Agente BN | B27: 1 | C27: 5 | D27: 3 meses | E27: =IF(OR(ISBLANK(PRIORIDAD_UNO[[#This Row],[Esfuerzo Estimado Desarrollo]]),PRIORIDAD_UNO[[#This Row],[Esfuerzo Estimado Desarrollo]]="No definido"),"No definido", IF(VALUE(TRIM(LEFT(PRIORIDAD_UNO[[#This Row],[Esfuerzo Estimado Desarrollo]],2)))<=1,"Pequeño", IF(VALUE(TRIM(LEFT(PRIORIDAD_UNO[[#This Row],[Esfuerzo Estimado Desarrollo]],2)))<=3,"Mediano", IF(VALUE(TRIM(LEFT(PRIORIDAD_UNO[[#This Row],[Esfuerzo Estimado Desarrollo]],2)))<=5,"Grande", IF(VALUE(TRIM(LEFT(PRIORIDAD_UNO[[#This Row],[Esfuerzo Estimado Desarrollo]],2)))<=7,"Extra Grande","Proyecto"))))) -> Mediano | F27: Banca Digital | G27: Canales Alternos | H27: Canales Presenciales | I27: MEMORANDO N° 00000044 -2026-BN/3251 | J27: Sí | K27: Normativo | L27: Pendiente de Atención | M27: Sistemas Bancarios | N27: Vladimir Cajavilca | O27: Omar Sarmiento | Q27: 46252 | R27: =IF(OR(PRIORIDAD_UNO[[#This Row],[Tamaño]]="No definido",ISBLANK(PRIORIDAD_UNO[[#This Row],[Comienzo Desarrollo]])),"",IF(ISBLANK( VLOOKUP(PRIORIDAD_UNO[[#This Row],[Nombre del requerimiento]],'Cálculos Manual'!A:F,6,FALSE)), WORKDAY(PRIORIDAD_UNO[[#This Row],[Comienzo Desarrollo]], IF(PRIORIDAD_UNO[[#This Row],[Tamaño]]="Pequeño",30,IF(PRIORIDAD_UNO[[#This Row],[Tamaño]]="Mediano",66,IF(PRIORIDAD_UNO[[#This Row],[Tamaño]]="Grande",110,IF(PRIORIDAD_UNO[[#This Row],[Tamaño]]="Extra Grande",154,176)))), FERIADOS[Fecha]), VLOOKUP(PRIORIDAD_UNO[[#This Row],[Nombre del requerimiento]],'Cálculos Manual'!A:F,6,FALSE))) -> 46345 | S27: =IF(PRIORIDAD_UNO[[#This Row],[Fin Desarrollo]]="","",IF(ISBLANK(VLOOKUP(PRIORIDAD_UNO[[#This Row],[Nombre del requerimiento]],'Cálculos Manual'!A:H,8,FALSE)),WORKDAY(PRIORIDAD_UNO[[#This Row],[Fin Desarrollo]],5,FERIADOS[Fecha]), VLOOKUP(PRIORIDAD_UNO[[#This Row],[Nombre del requerimiento]],'Cálculos Manual'!A:H,8,FALSE))) -> 46352 | T27: =IF(PRIORIDAD_UNO[[#This Row],[Comienzo Calidad]]="","",IF(ISBLANK(VLOOKUP(PRIORIDAD_UNO[[#This Row],[Nombre del requerimiento]],'Cálculos Manual'!A:J,10,FALSE)), WORKDAY(PRIORIDAD_UNO[[#This Row],[Comienzo Calidad]],IF(PRIORIDAD_UNO[[#This Row],[Tamaño]]="Pequeño",30,IF(PRIORIDAD_UNO[[#This Row],[Tamaño]]="Mediano",40,50)),FERIADOS[Fecha]), VLOOKUP(PRIORIDAD_UNO[[#This Row],[Nombre del requerimiento]],'Cálculos Manual'!A:J,10,FALSE))) -> 46414 | U27: =IF(PRIORIDAD_UNO[[#This Row],[Fin Calidad]]="","",IF(ISBLANK(VLOOKUP(PRIORIDAD_UNO[[#This Row],[Nombre del requerimiento]],'Cálculos Manual'!A:L,12,FALSE)), WORKDAY(PRIORIDAD_UNO[[#This Row],[Fin Calidad]],5,FERIADOS[Fecha]), VLOOKUP(PRIORIDAD_UNO[[#This Row],[Nombre del requerimiento]],'Cálculos Manual'!A:L,12,FALSE))) -> 46421 | V27: =IF(PRIORIDAD_UNO[[#This Row],[Comienzo Producción]]="","",IF(ISBLANK(VLOOKUP(PRIORIDAD_UNO[[#This Row],[Nombre del requerimiento]],'Cálculos Manual'!A:N,14,FALSE)), WORKDAY(PRIORIDAD_UNO[[#This Row],[Comienzo Producción]],IF(PRIORIDAD_UNO[[#This Row],[Tamaño]]="Grande",10,5),FERIADOS[Fecha]), VLOOKUP(PRIORIDAD_UNO[[#This Row],[Nombre del requerimiento]],'Cálculos Manual'!A:N,14,FALSE))) -> 46428 | W27: =IFERROR(PRIORIDAD_UNO[[#This Row],[Fin Producción]]-PRIORIDAD_UNO[[#This Row],[Comienzo Desarrollo]],"") -> 176 | X27: =IF(ISBLANK(PRIORIDAD_UNO[[#This Row],[Comienzo Desarrollo]]),"Sin Fecha","Con Fecha") -> Con Fecha | Y27: =IF(PRIORIDAD_UNO[[#This Row],[Esfuerzo Estimado Desarrollo]]="No definido","Sin esfuerzo","Con esfuerzo") -> Con esfuerzo | Z27: =IF(ISBLANK(PRIORIDAD_UNO[[#This Row],[Comienzo Desarrollo]]),"🔵 Sin Fecha", IF(PRIORIDAD_UNO[[#This Row],[Comienzo Desarrollo]]<TODAY(),"🔴 Vencido", IF(PRIORIDAD_UNO[[#This Row],[Comienzo Desarrollo]]=TODAY(),"🟡 Vence hoy", IF((PRIORIDAD_UNO[[#This Row],[Comienzo Desarrollo]]-TODAY())<=5,"🟠 Por vencer", "🟢 A tiempo")))) -> 🟢 A tiempo | AA27: =IF(PRIORIDAD_UNO[[#This Row],[Comienzo Producción]]="","Por Definir",_xlfn.CONCAT(YEAR(PRIORIDAD_UNO[[#This Row],[Comienzo Producción]])," - ", MONTH(PRIORIDAD_UNO[[#This Row],[Comienzo Producción]]))) -> 2027 - 2 | AB27: 3333
A28: Reporte de Clientes con clave de internet | B28: 1 | C28: 1 | D28: 1 mes | E28: =IF(OR(ISBLANK(PRIORIDAD_UNO[[#This Row],[Esfuerzo Estimado Desarrollo]]),PRIORIDAD_UNO[[#This Row],[Esfuerzo Estimado Desarrollo]]="No definido"),"No definido", IF(VALUE(TRIM(LEFT(PRIORIDAD_UNO[[#This Row],[Esfuerzo Estimado Desarrollo]],2)))<=1,"Pequeño", IF(VALUE(TRIM(LEFT(PRIORIDAD_UNO[[#This Row],[Esfuerzo Estimado Desarrollo]],2)))<=3,"Mediano", IF(VALUE(TRIM(LEFT(PRIORIDAD_UNO[[#This Row],[Esfuerzo Estimado Desarrollo]],2)))<=5,"Grande", IF(VALUE(TRIM(LEFT(PRIORIDAD_UNO[[#This Row],[Esfuerzo Estimado Desarrollo]],2)))<=7,"Extra Grande","Proyecto"))))) -> Pequeño | F28: Banca Digital | G28: Canales Alternos | H28: Canales Virtuales | I28: MEMORANDO N° 00000130 - 2026-BN-3252 | J28: Sí | K28: Evolutivo | L28: Pendiente de Atención | M28: Soluciones Digitales | N28: Mario Carbajo | O28: Omar Sarmiento | P28: Backlog ID. 3355 | Q28: 46181 | R28: =IF(OR(PRIORIDAD_UNO[[#This Row],[Tamaño]]="No definido",ISBLANK(PRIORIDAD_UNO[[#This Row],[Comienzo Desarrollo]])),"",IF(ISBLANK( VLOOKUP(PRIORIDAD_UNO[[#This Row],[Nombre del requerimiento]],'Cálculos Manual'!A:F,6,FALSE)), WORKDAY(PRIORIDAD_UNO[[#This Row],[Comienzo Desarrollo]], IF(PRIORIDAD_UNO[[#This Row],[Tamaño]]="Pequeño",30,IF(PRIORIDAD_UNO[[#This Row],[Tamaño]]="Mediano",66,IF(PRIORIDAD_UNO[[#This Row],[Tamaño]]="Grande",110,IF(PRIORIDAD_UNO[[#This Row],[Tamaño]]="Extra Grande",154,176)))), FERIADOS[Fecha]), VLOOKUP(PRIORIDAD_UNO[[#This Row],[Nombre del requerimiento]],'Cálculos Manual'!A:F,6,FALSE))) -> 46224 | S28: =IF(PRIORIDAD_UNO[[#This Row],[Fin Desarrollo]]="","",IF(ISBLANK(VLOOKUP(PRIORIDAD_UNO[[#This Row],[Nombre del requerimiento]],'Cálculos Manual'!A:H,8,FALSE)),WORKDAY(PRIORIDAD_UNO[[#This Row],[Fin Desarrollo]],5,FERIADOS[Fecha]), VLOOKUP(PRIORIDAD_UNO[[#This Row],[Nombre del requerimiento]],'Cálculos Manual'!A:H,8,FALSE))) -> 46234 | T28: =IF(PRIORIDAD_UNO[[#This Row],[Comienzo Calidad]]="","",IF(ISBLANK(VLOOKUP(PRIORIDAD_UNO[[#This Row],[Nombre del requerimiento]],'Cálculos Manual'!A:J,10,FALSE)), WORKDAY(PRIORIDAD_UNO[[#This Row],[Comienzo Calidad]],IF(PRIORIDAD_UNO[[#This Row],[Tamaño]]="Pequeño",30,IF(PRIORIDAD_UNO[[#This Row],[Tamaño]]="Mediano",40,50)),FERIADOS[Fecha]), VLOOKUP(PRIORIDAD_UNO[[#This Row],[Nombre del requerimiento]],'Cálculos Manual'!A:J,10,FALSE))) -> 46279 | U28: =IF(PRIORIDAD_UNO[[#This Row],[Fin Calidad]]="","",IF(ISBLANK(VLOOKUP(PRIORIDAD_UNO[[#This Row],[Nombre del requerimiento]],'Cálculos Manual'!A:L,12,FALSE)), WORKDAY(PRIORIDAD_UNO[[#This Row],[Fin Calidad]],5,FERIADOS[Fecha]), VLOOKUP(PRIORIDAD_UNO[[#This Row],[Nombre del requerimiento]],'Cálculos Manual'!A:L,12,FALSE))) -> 46286 | V28: =IF(PRIORIDAD_UNO[[#This Row],[Comienzo Producción]]="","",IF(ISBLANK(VLOOKUP(PRIORIDAD_UNO[[#This Row],[Nombre del requerimiento]],'Cálculos Manual'!A:N,14,FALSE)), WORKDAY(PRIORIDAD_UNO[[#This Row],[Comienzo Producción]],IF(PRIORIDAD_UNO[[#This Row],[Tamaño]]="Grande",10,5),FERIADOS[Fecha]), VLOOKUP(PRIORIDAD_UNO[[#This Row],[Nombre del requerimiento]],'Cálculos Manual'!A:N,14,FALSE))) -> 46293 | W28: =IFERROR(PRIORIDAD_UNO[[#This Row],[Fin Producción]]-PRIORIDAD_UNO[[#This Row],[Comienzo Desarrollo]],"") -> 112 | X28: =IF(ISBLANK(PRIORIDAD_UNO[[#This Row],[Comienzo Desarrollo]]),"Sin Fecha","Con Fecha") -> Con Fecha | Y28: =IF(PRIORIDAD_UNO[[#This Row],[Esfuerzo Estimado Desarrollo]]="No definido","Sin esfuerzo","Con esfuerzo") -> Con esfuerzo | Z28: =IF(ISBLANK(PRIORIDAD_UNO[[#This Row],[Comienzo Desarrollo]]),"🔵 Sin Fecha", IF(PRIORIDAD_UNO[[#This Row],[Comienzo Desarrollo]]<TODAY(),"🔴 Vencido", IF(PRIORIDAD_UNO[[#This Row],[Comienzo Desarrollo]]=TODAY(),"🟡 Vence hoy", IF((PRIORIDAD_UNO[[#This Row],[Comienzo Desarrollo]]-TODAY())<=5,"🟠 Por vencer", "🟢 A tiempo")))) -> 🔴 Vencido | AA28: =IF(PRIORIDAD_UNO[[#This Row],[Comienzo Producción]]="","Por Definir",_xlfn.CONCAT(YEAR(PRIORIDAD_UNO[[#This Row],[Comienzo Producción]])," - ", MONTH(PRIORIDAD_UNO[[#This Row],[Comienzo Producción]]))) -> 2026 - 9 | AB28: 3355
A29: Reporte de accesos al sistema de Emulación - DA00 | B29: 1 | C29: Por definir | D29: 3 meses | E29: =IF(OR(ISBLANK(PRIORIDAD_UNO[[#This Row],[Esfuerzo Estimado Desarrollo]]),PRIORIDAD_UNO[[#This Row],[Esfuerzo Estimado Desarrollo]]="No definido"),"No definido", IF(VALUE(TRIM(LEFT(PRIORIDAD_UNO[[#This Row],[Esfuerzo Estimado Desarrollo]],2)))<=1,"Pequeño", IF(VALUE(TRIM(LEFT(PRIORIDAD_UNO[[#This Row],[Esfuerzo Estimado Desarrollo]],2)))<=3,"Mediano", IF(VALUE(TRIM(LEFT(PRIORIDAD_UNO[[#This Row],[Esfuerzo Estimado Desarrollo]],2)))<=5,"Grande", IF(VALUE(TRIM(LEFT(PRIORIDAD_UNO[[#This Row],[Esfuerzo Estimado Desarrollo]],2)))<=7,"Extra Grande","Proyecto"))))) -> Mediano | F29: Banca Digital | G29: Canales Alternos | H29: Mesa de Ayuda | I29: MEMORANDO N° 00000045 - 2026-BN/3151 | J29: Sí | K29: Recomendación | L29: Pendiente de Atención | M29: Sistemas Bancarios | N29: Norma Fukunaga | O29: Omar Sarmiento | Q29: 46237 | R29: =IF(OR(PRIORIDAD_UNO[[#This Row],[Tamaño]]="No definido",ISBLANK(PRIORIDAD_UNO[[#This Row],[Comienzo Desarrollo]])),"",IF(ISBLANK( VLOOKUP(PRIORIDAD_UNO[[#This Row],[Nombre del requerimiento]],'Cálculos Manual'!A:F,6,FALSE)), WORKDAY(PRIORIDAD_UNO[[#This Row],[Comienzo Desarrollo]], IF(PRIORIDAD_UNO[[#This Row],[Tamaño]]="Pequeño",30,IF(PRIORIDAD_UNO[[#This Row],[Tamaño]]="Mediano",66,IF(PRIORIDAD_UNO[[#This Row],[Tamaño]]="Grande",110,IF(PRIORIDAD_UNO[[#This Row],[Tamaño]]="Extra Grande",154,176)))), FERIADOS[Fecha]), VLOOKUP(PRIORIDAD_UNO[[#This Row],[Nombre del requerimiento]],'Cálculos Manual'!A:F,6,FALSE))) -> 46331 | S29: =IF(PRIORIDAD_UNO[[#This Row],[Fin Desarrollo]]="","",IF(ISBLANK(VLOOKUP(PRIORIDAD_UNO[[#This Row],[Nombre del requerimiento]],'Cálculos Manual'!A:H,8,FALSE)),WORKDAY(PRIORIDAD_UNO[[#This Row],[Fin Desarrollo]],5,FERIADOS[Fecha]), VLOOKUP(PRIORIDAD_UNO[[#This Row],[Nombre del requerimiento]],'Cálculos Manual'!A:H,8,FALSE))) -> 46338 | T29: =IF(PRIORIDAD_UNO[[#This Row],[Comienzo Calidad]]="","",IF(ISBLANK(VLOOKUP(PRIORIDAD_UNO[[#This Row],[Nombre del requerimiento]],'Cálculos Manual'!A:J,10,FALSE)), WORKDAY(PRIORIDAD_UNO[[#This Row],[Comienzo Calidad]],IF(PRIORIDAD_UNO[[#This Row],[Tamaño]]="Pequeño",30,IF(PRIORIDAD_UNO[[#This Row],[Tamaño]]="Mediano",40,50)),FERIADOS[Fecha]), VLOOKUP(PRIORIDAD_UNO[[#This Row],[Nombre del requerimiento]],'Cálculos Manual'!A:J,10,FALSE))) -> 46400 | U29: =IF(PRIORIDAD_UNO[[#This Row],[Fin Calidad]]="","",IF(ISBLANK(VLOOKUP(PRIORIDAD_UNO[[#This Row],[Nombre del requerimiento]],'Cálculos Manual'!A:L,12,FALSE)), WORKDAY(PRIORIDAD_UNO[[#This Row],[Fin Calidad]],5,FERIADOS[Fecha]), VLOOKUP(PRIORIDAD_UNO[[#This Row],[Nombre del requerimiento]],'Cálculos Manual'!A:L,12,FALSE))) -> 46407 | V29: =IF(PRIORIDAD_UNO[[#This Row],[Comienzo Producción]]="","",IF(ISBLANK(VLOOKUP(PRIORIDAD_UNO[[#This Row],[Nombre del requerimiento]],'Cálculos Manual'!A:N,14,FALSE)), WORKDAY(PRIORIDAD_UNO[[#This Row],[Comienzo Producción]],IF(PRIORIDAD_UNO[[#This Row],[Tamaño]]="Grande",10,5),FERIADOS[Fecha]), VLOOKUP(PRIORIDAD_UNO[[#This Row],[Nombre del requerimiento]],'Cálculos Manual'!A:N,14,FALSE))) -> 46414 | W29: =IFERROR(PRIORIDAD_UNO[[#This Row],[Fin Producción]]-PRIORIDAD_UNO[[#This Row],[Comienzo Desarrollo]],"") -> 177 | X29: =IF(ISBLANK(PRIORIDAD_UNO[[#This Row],[Comienzo Desarrollo]]),"Sin Fecha","Con Fecha") -> Con Fecha | Y29: =IF(PRIORIDAD_UNO[[#This Row],[Esfuerzo Estimado Desarrollo]]="No definido","Sin esfuerzo","Con esfuerzo") -> Con esfuerzo | Z29: =IF(ISBLANK(PRIORIDAD_UNO[[#This Row],[Comienzo Desarrollo]]),"🔵 Sin Fecha", IF(PRIORIDAD_UNO[[#This Row],[Comienzo Desarrollo]]<TODAY(),"🔴 Vencido", IF(PRIORIDAD_UNO[[#This Row],[Comienzo Desarrollo]]=TODAY(),"🟡 Vence hoy", IF((PRIORIDAD_UNO[[#This Row],[Comienzo Desarrollo]]-TODAY())<=5,"🟠 Por vencer", "🟢 A tiempo")))) -> 🟢 A tiempo | AA29: =IF(PRIORIDAD_UNO[[#This Row],[Comienzo Producción]]="","Por Definir",_xlfn.CONCAT(YEAR(PRIORIDAD_UNO[[#This Row],[Comienzo Producción]])," - ", MONTH(PRIORIDAD_UNO[[#This Row],[Comienzo Producción]]))) -> 2027 - 1 | AB29: Revisar 3144
A30: Reporte de Accesos al Sistema BDUC | B30: 1 | C30: 3 | E30: =IF(OR(ISBLANK(PRIORIDAD_UNO[[#This Row],[Esfuerzo Estimado Desarrollo]]),PRIORIDAD_UNO[[#This Row],[Esfuerzo Estimado Desarrollo]]="No definido"),"No definido", IF(VALUE(TRIM(LEFT(PRIORIDAD_UNO[[#This Row],[Esfuerzo Estimado Desarrollo]],2)))<=1,"Pequeño", IF(VALUE(TRIM(LEFT(PRIORIDAD_UNO[[#This Row],[Esfuerzo Estimado Desarrollo]],2)))<=3,"Mediano", IF(VALUE(TRIM(LEFT(PRIORIDAD_UNO[[#This Row],[Esfuerzo Estimado Desarrollo]],2)))<=5,"Grande", IF(VALUE(TRIM(LEFT(PRIORIDAD_UNO[[#This Row],[Esfuerzo Estimado Desarrollo]],2)))<=7,"Extra Grande","Proyecto"))))) -> No definido | F30: Banca Digital | G30: Canales Alternos | H30: Mesa de Ayuda | I30: MEMORANDO N° 00000045 - 2026-BN/3151 | J30: Sí | K30: Recomendación | L30: Por evaluar | M30: Sistemas Bancarios | N30: Jhonny Rooca | O30: Omar Sarmiento | R30: =IF(OR(PRIORIDAD_UNO[[#This Row],[Tamaño]]="No definido",ISBLANK(PRIORIDAD_UNO[[#This Row],[Comienzo Desarrollo]])),"",IF(ISBLANK( VLOOKUP(PRIORIDAD_UNO[[#This Row],[Nombre del requerimiento]],'Cálculos Manual'!A:F,6,FALSE)), WORKDAY(PRIORIDAD_UNO[[#This Row],[Comienzo Desarrollo]], IF(PRIORIDAD_UNO[[#This Row],[Tamaño]]="Pequeño",30,IF(PRIORIDAD_UNO[[#This Row],[Tamaño]]="Mediano",66,IF(PRIORIDAD_UNO[[#This Row],[Tamaño]]="Grande",110,IF(PRIORIDAD_UNO[[#This Row],[Tamaño]]="Extra Grande",154,176)))), FERIADOS[Fecha]), VLOOKUP(PRIORIDAD_UNO[[#This Row],[Nombre del requerimiento]],'Cálculos Manual'!A:F,6,FALSE))) | S30: =IF(PRIORIDAD_UNO[[#This Row],[Fin Desarrollo]]="","",IF(ISBLANK(VLOOKUP(PRIORIDAD_UNO[[#This Row],[Nombre del requerimiento]],'Cálculos Manual'!A:H,8,FALSE)),WORKDAY(PRIORIDAD_UNO[[#This Row],[Fin Desarrollo]],5,FERIADOS[Fecha]), VLOOKUP(PRIORIDAD_UNO[[#This Row],[Nombre del requerimiento]],'Cálculos Manual'!A:H,8,FALSE))) | T30: =IF(PRIORIDAD_UNO[[#This Row],[Comienzo Calidad]]="","",IF(ISBLANK(VLOOKUP(PRIORIDAD_UNO[[#This Row],[Nombre del requerimiento]],'Cálculos Manual'!A:J,10,FALSE)), WORKDAY(PRIORIDAD_UNO[[#This Row],[Comienzo Calidad]],IF(PRIORIDAD_UNO[[#This Row],[Tamaño]]="Pequeño",30,IF(PRIORIDAD_UNO[[#This Row],[Tamaño]]="Mediano",40,50)),FERIADOS[Fecha]), VLOOKUP(PRIORIDAD_UNO[[#This Row],[Nombre del requerimiento]],'Cálculos Manual'!A:J,10,FALSE))) | U30: =IF(PRIORIDAD_UNO[[#This Row],[Fin Calidad]]="","",IF(ISBLANK(VLOOKUP(PRIORIDAD_UNO[[#This Row],[Nombre del requerimiento]],'Cálculos Manual'!A:L,12,FALSE)), WORKDAY(PRIORIDAD_UNO[[#This Row],[Fin Calidad]],5,FERIADOS[Fecha]), VLOOKUP(PRIORIDAD_UNO[[#This Row],[Nombre del requerimiento]],'Cálculos Manual'!A:L,12,FALSE))) | V30: =IF(PRIORIDAD_UNO[[#This Row],[Comienzo Producción]]="","",IF(ISBLANK(VLOOKUP(PRIORIDAD_UNO[[#This Row],[Nombre del requerimiento]],'Cálculos Manual'!A:N,14,FALSE)), WORKDAY(PRIORIDAD_UNO[[#This Row],[Comienzo Producción]],IF(PRIORIDAD_UNO[[#This Row],[Tamaño]]="Grande",10,5),FERIADOS[Fecha]), VLOOKUP(PRIORIDAD_UNO[[#This Row],[Nombre del requerimiento]],'Cálculos Manual'!A:N,14,FALSE))) | W30: =IFERROR(PRIORIDAD_UNO[[#This Row],[Fin Producción]]-PRIORIDAD_UNO[[#This Row],[Comienzo Desarrollo]],"") | X30: =IF(ISBLANK(PRIORIDAD_UNO[[#This Row],[Comienzo Desarrollo]]),"Sin Fecha","Con Fecha") -> Sin Fecha | Y30: =IF(PRIORIDAD_UNO[[#This Row],[Esfuerzo Estimado Desarrollo]]="No definido","Sin esfuerzo","Con esfuerzo") -> Con esfuerzo | Z30: =IF(ISBLANK(PRIORIDAD_UNO[[#This Row],[Comienzo Desarrollo]]),"🔵 Sin Fecha", IF(PRIORIDAD_UNO[[#This Row],[Comienzo Desarrollo]]<TODAY(),"🔴 Vencido", IF(PRIORIDAD_UNO[[#This Row],[Comienzo Desarrollo]]=TODAY(),"🟡 Vence hoy", IF((PRIORIDAD_UNO[[#This Row],[Comienzo Desarrollo]]-TODAY())<=5,"🟠 Por vencer", "🟢 A tiempo")))) -> 🔵 Sin Fecha | AA30: =IF(PRIORIDAD_UNO[[#This Row],[Comienzo Producción]]="","Por Definir",_xlfn.CONCAT(YEAR(PRIORIDAD_UNO[[#This Row],[Comienzo Producción]])," - ", MONTH(PRIORIDAD_UNO[[#This Row],[Comienzo Producción]]))) -> Por Definir | AB30: No está
A31: Renovación Préstamos Canales Banca Movil, Banca Internet | B31: 1 | C31: 4 | D31: 3 meses | E31: =IF(OR(ISBLANK(PRIORIDAD_UNO[[#This Row],[Esfuerzo Estimado Desarrollo]]),PRIORIDAD_UNO[[#This Row],[Esfuerzo Estimado Desarrollo]]="No definido"),"No definido", IF(VALUE(TRIM(LEFT(PRIORIDAD_UNO[[#This Row],[Esfuerzo Estimado Desarrollo]],2)))<=1,"Pequeño", IF(VALUE(TRIM(LEFT(PRIORIDAD_UNO[[#This Row],[Esfuerzo Estimado Desarrollo]],2)))<=3,"Mediano", IF(VALUE(TRIM(LEFT(PRIORIDAD_UNO[[#This Row],[Esfuerzo Estimado Desarrollo]],2)))<=5,"Grande", IF(VALUE(TRIM(LEFT(PRIORIDAD_UNO[[#This Row],[Esfuerzo Estimado Desarrollo]],2)))<=7,"Extra Grande","Proyecto"))))) -> Mediano | F31: Productos e Inclusión Financiera | G31: Banca Personal | H31: Préstamo Multired | I31: MEMORANDO N° 00000084 - 2026-BN/3347 | J31: Sí | K31: Recomendación | L31: Observado | M31: Soluciones Digitales | N31: Marilú Cordova | O31: Milagros Huamani | P31: Gerencia TI indicó que no se debe de desarrollar ninguna funcionabilidad nueva en las aplicaciones actules de Banca Movil y Homebankig. | R31: =IF(OR(PRIORIDAD_UNO[[#This Row],[Tamaño]]="No definido",ISBLANK(PRIORIDAD_UNO[[#This Row],[Comienzo Desarrollo]])),"",IF(ISBLANK( VLOOKUP(PRIORIDAD_UNO[[#This Row],[Nombre del requerimiento]],'Cálculos Manual'!A:F,6,FALSE)), WORKDAY(PRIORIDAD_UNO[[#This Row],[Comienzo Desarrollo]], IF(PRIORIDAD_UNO[[#This Row],[Tamaño]]="Pequeño",30,IF(PRIORIDAD_UNO[[#This Row],[Tamaño]]="Mediano",66,IF(PRIORIDAD_UNO[[#This Row],[Tamaño]]="Grande",110,IF(PRIORIDAD_UNO[[#This Row],[Tamaño]]="Extra Grande",154,176)))), FERIADOS[Fecha]), VLOOKUP(PRIORIDAD_UNO[[#This Row],[Nombre del requerimiento]],'Cálculos Manual'!A:F,6,FALSE))) | S31: =IF(PRIORIDAD_UNO[[#This Row],[Fin Desarrollo]]="","",IF(ISBLANK(VLOOKUP(PRIORIDAD_UNO[[#This Row],[Nombre del requerimiento]],'Cálculos Manual'!A:H,8,FALSE)),WORKDAY(PRIORIDAD_UNO[[#This Row],[Fin Desarrollo]],5,FERIADOS[Fecha]), VLOOKUP(PRIORIDAD_UNO[[#This Row],[Nombre del requerimiento]],'Cálculos Manual'!A:H,8,FALSE))) | T31: =IF(PRIORIDAD_UNO[[#This Row],[Comienzo Calidad]]="","",IF(ISBLANK(VLOOKUP(PRIORIDAD_UNO[[#This Row],[Nombre del requerimiento]],'Cálculos Manual'!A:J,10,FALSE)), WORKDAY(PRIORIDAD_UNO[[#This Row],[Comienzo Calidad]],IF(PRIORIDAD_UNO[[#This Row],[Tamaño]]="Pequeño",30,IF(PRIORIDAD_UNO[[#This Row],[Tamaño]]="Mediano",40,50)),FERIADOS[Fecha]), VLOOKUP(PRIORIDAD_UNO[[#This Row],[Nombre del requerimiento]],'Cálculos Manual'!A:J,10,FALSE))) | U31: =IF(PRIORIDAD_UNO[[#This Row],[Fin Calidad]]="","",IF(ISBLANK(VLOOKUP(PRIORIDAD_UNO[[#This Row],[Nombre del requerimiento]],'Cálculos Manual'!A:L,12,FALSE)), WORKDAY(PRIORIDAD_UNO[[#This Row],[Fin Calidad]],5,FERIADOS[Fecha]), VLOOKUP(PRIORIDAD_UNO[[#This Row],[Nombre del requerimiento]],'Cálculos Manual'!A:L,12,FALSE))) | V31: =IF(PRIORIDAD_UNO[[#This Row],[Comienzo Producción]]="","",IF(ISBLANK(VLOOKUP(PRIORIDAD_UNO[[#This Row],[Nombre del requerimiento]],'Cálculos Manual'!A:N,14,FALSE)), WORKDAY(PRIORIDAD_UNO[[#This Row],[Comienzo Producción]],IF(PRIORIDAD_UNO[[#This Row],[Tamaño]]="Grande",10,5),FERIADOS[Fecha]), VLOOKUP(PRIORIDAD_UNO[[#This Row],[Nombre del requerimiento]],'Cálculos Manual'!A:N,14,FALSE))) | W31: =IFERROR(PRIORIDAD_UNO[[#This Row],[Fin Producción]]-PRIORIDAD_UNO[[#This Row],[Comienzo Desarrollo]],"") | X31: =IF(ISBLANK(PRIORIDAD_UNO[[#This Row],[Comienzo Desarrollo]]),"Sin Fecha","Con Fecha") -> Sin Fecha | Y31: =IF(PRIORIDAD_UNO[[#This Row],[Esfuerzo Estimado Desarrollo]]="No definido","Sin esfuerzo","Con esfuerzo") -> Con esfuerzo | Z31: =IF(ISBLANK(PRIORIDAD_UNO[[#This Row],[Comienzo Desarrollo]]),"🔵 Sin Fecha", IF(PRIORIDAD_UNO[[#This Row],[Comienzo Desarrollo]]<TODAY(),"🔴 Vencido", IF(PRIORIDAD_UNO[[#This Row],[Comienzo Desarrollo]]=TODAY(),"🟡 Vence hoy", IF((PRIORIDAD_UNO[[#This Row],[Comienzo Desarrollo]]-TODAY())<=5,"🟠 Por vencer", "🟢 A tiempo")))) -> 🔵 Sin Fecha | AA31: =IF(PRIORIDAD_UNO[[#This Row],[Comienzo Producción]]="","Por Definir",_xlfn.CONCAT(YEAR(PRIORIDAD_UNO[[#This Row],[Comienzo Producción]])," - ", MONTH(PRIORIDAD_UNO[[#This Row],[Comienzo Producción]]))) -> Por Definir | AB31: No está
A32: Registro de Entidad 0813 - CMAC Tacna en el sistema de transferencias Interbancarias e Interoperabilidad CCE | B32: 1 | C32: 22 | D32: 1 mes | E32: =IF(OR(ISBLANK(PRIORIDAD_UNO[[#This Row],[Esfuerzo Estimado Desarrollo]]),PRIORIDAD_UNO[[#This Row],[Esfuerzo Estimado Desarrollo]]="No definido"),"No definido", IF(VALUE(TRIM(LEFT(PRIORIDAD_UNO[[#This Row],[Esfuerzo Estimado Desarrollo]],2)))<=1,"Pequeño", IF(VALUE(TRIM(LEFT(PRIORIDAD_UNO[[#This Row],[Esfuerzo Estimado Desarrollo]],2)))<=3,"Mediano", IF(VALUE(TRIM(LEFT(PRIORIDAD_UNO[[#This Row],[Esfuerzo Estimado Desarrollo]],2)))<=5,"Grande", IF(VALUE(TRIM(LEFT(PRIORIDAD_UNO[[#This Row],[Esfuerzo Estimado Desarrollo]],2)))<=7,"Extra Grande","Proyecto"))))) -> Pequeño | F32: Operaciones | G32: SubGerencia de Captaciones y Pagaduria | H32: Sistema de Pagos | I32: MEMORANDO N° 00000140 - 2025-BN/3116 | J32: Sí | K32: Recomendación | L32: Pendiente de Atención | M32: Soluciones Digitales | N32: Monica Campana | O32: Junior Quicaño | P32: Anexo 2 dice evolutivo. | Q32: 46174 | R32: =IF(OR(PRIORIDAD_UNO[[#This Row],[Tamaño]]="No definido",ISBLANK(PRIORIDAD_UNO[[#This Row],[Comienzo Desarrollo]])),"",IF(ISBLANK( VLOOKUP(PRIORIDAD_UNO[[#This Row],[Nombre del requerimiento]],'Cálculos Manual'!A:F,6,FALSE)), WORKDAY(PRIORIDAD_UNO[[#This Row],[Comienzo Desarrollo]], IF(PRIORIDAD_UNO[[#This Row],[Tamaño]]="Pequeño",30,IF(PRIORIDAD_UNO[[#This Row],[Tamaño]]="Mediano",66,IF(PRIORIDAD_UNO[[#This Row],[Tamaño]]="Grande",110,IF(PRIORIDAD_UNO[[#This Row],[Tamaño]]="Extra Grande",154,176)))), FERIADOS[Fecha]), VLOOKUP(PRIORIDAD_UNO[[#This Row],[Nombre del requerimiento]],'Cálculos Manual'!A:F,6,FALSE))) -> 46217 | S32: =IF(PRIORIDAD_UNO[[#This Row],[Fin Desarrollo]]="","",IF(ISBLANK(VLOOKUP(PRIORIDAD_UNO[[#This Row],[Nombre del requerimiento]],'Cálculos Manual'!A:H,8,FALSE)),WORKDAY(PRIORIDAD_UNO[[#This Row],[Fin Desarrollo]],5,FERIADOS[Fecha]), VLOOKUP(PRIORIDAD_UNO[[#This Row],[Nombre del requerimiento]],'Cálculos Manual'!A:H,8,FALSE))) -> 46224 | T32: =IF(PRIORIDAD_UNO[[#This Row],[Comienzo Calidad]]="","",IF(ISBLANK(VLOOKUP(PRIORIDAD_UNO[[#This Row],[Nombre del requerimiento]],'Cálculos Manual'!A:J,10,FALSE)), WORKDAY(PRIORIDAD_UNO[[#This Row],[Comienzo Calidad]],IF(PRIORIDAD_UNO[[#This Row],[Tamaño]]="Pequeño",30,IF(PRIORIDAD_UNO[[#This Row],[Tamaño]]="Mediano",40,50)),FERIADOS[Fecha]), VLOOKUP(PRIORIDAD_UNO[[#This Row],[Nombre del requerimiento]],'Cálculos Manual'!A:J,10,FALSE))) -> 46272 | U32: =IF(PRIORIDAD_UNO[[#This Row],[Fin Calidad]]="","",IF(ISBLANK(VLOOKUP(PRIORIDAD_UNO[[#This Row],[Nombre del requerimiento]],'Cálculos Manual'!A:L,12,FALSE)), WORKDAY(PRIORIDAD_UNO[[#This Row],[Fin Calidad]],5,FERIADOS[Fecha]), VLOOKUP(PRIORIDAD_UNO[[#This Row],[Nombre del requerimiento]],'Cálculos Manual'!A:L,12,FALSE))) -> 46279 | V32: =IF(PRIORIDAD_UNO[[#This Row],[Comienzo Producción]]="","",IF(ISBLANK(VLOOKUP(PRIORIDAD_UNO[[#This Row],[Nombre del requerimiento]],'Cálculos Manual'!A:N,14,FALSE)), WORKDAY(PRIORIDAD_UNO[[#This Row],[Comienzo Producción]],IF(PRIORIDAD_UNO[[#This Row],[Tamaño]]="Grande",10,5),FERIADOS[Fecha]), VLOOKUP(PRIORIDAD_UNO[[#This Row],[Nombre del requerimiento]],'Cálculos Manual'!A:N,14,FALSE))) -> 46286 | W32: =IFERROR(PRIORIDAD_UNO[[#This Row],[Fin Producción]]-PRIORIDAD_UNO[[#This Row],[Comienzo Desarrollo]],"") -> 112 | X32: =IF(ISBLANK(PRIORIDAD_UNO[[#This Row],[Comienzo Desarrollo]]),"Sin Fecha","Con Fecha") -> Con Fecha | Y32: =IF(PRIORIDAD_UNO[[#This Row],[Esfuerzo Estimado Desarrollo]]="No definido","Sin esfuerzo","Con esfuerzo") -> Con esfuerzo | Z32: =IF(ISBLANK(PRIORIDAD_UNO[[#This Row],[Comienzo Desarrollo]]),"🔵 Sin Fecha", IF(PRIORIDAD_UNO[[#This Row],[Comienzo Desarrollo]]<TODAY(),"🔴 Vencido", IF(PRIORIDAD_UNO[[#This Row],[Comienzo Desarrollo]]=TODAY(),"🟡 Vence hoy", IF((PRIORIDAD_UNO[[#This Row],[Comienzo Desarrollo]]-TODAY())<=5,"🟠 Por vencer", "🟢 A tiempo")))) -> 🔴 Vencido | AA32: =IF(PRIORIDAD_UNO[[#This Row],[Comienzo Producción]]="","Por Definir",_xlfn.CONCAT(YEAR(PRIORIDAD_UNO[[#This Row],[Comienzo Producción]])," - ", MONTH(PRIORIDAD_UNO[[#This Row],[Comienzo Producción]]))) -> 2026 - 9 | AB32: No está
A33: Reclasificación codigo 82 | B33: 1 | C33: 3 | D33: 3 meses | E33: =IF(OR(ISBLANK(PRIORIDAD_UNO[[#This Row],[Esfuerzo Estimado Desarrollo]]),PRIORIDAD_UNO[[#This Row],[Esfuerzo Estimado Desarrollo]]="No definido"),"No definido", IF(VALUE(TRIM(LEFT(PRIORIDAD_UNO[[#This Row],[Esfuerzo Estimado Desarrollo]],2)))<=1,"Pequeño", IF(VALUE(TRIM(LEFT(PRIORIDAD_UNO[[#This Row],[Esfuerzo Estimado Desarrollo]],2)))<=3,"Mediano", IF(VALUE(TRIM(LEFT(PRIORIDAD_UNO[[#This Row],[Esfuerzo Estimado Desarrollo]],2)))<=5,"Grande", IF(VALUE(TRIM(LEFT(PRIORIDAD_UNO[[#This Row],[Esfuerzo Estimado Desarrollo]],2)))<=7,"Extra Grande","Proyecto"))))) -> Mediano | F33: Banca Digital | G33: Canales Alternos | H33: Canales Presenciales | I33: MEMORANDO N° 00000044 - 2026-BN/3251 | J33: Sí | K33: Correctivo | L33: Pendiente de Atención | M33: Sistemas Bancarios | N33: Vladimir Cajavilca | O33: Omar Sarmiento | Q33: 46266 | R33: =IF(OR(PRIORIDAD_UNO[[#This Row],[Tamaño]]="No definido",ISBLANK(PRIORIDAD_UNO[[#This Row],[Comienzo Desarrollo]])),"",IF(ISBLANK( VLOOKUP(PRIORIDAD_UNO[[#This Row],[Nombre del requerimiento]],'Cálculos Manual'!A:F,6,FALSE)), WORKDAY(PRIORIDAD_UNO[[#This Row],[Comienzo Desarrollo]], IF(PRIORIDAD_UNO[[#This Row],[Tamaño]]="Pequeño",30,IF(PRIORIDAD_UNO[[#This Row],[Tamaño]]="Mediano",66,IF(PRIORIDAD_UNO[[#This Row],[Tamaño]]="Grande",110,IF(PRIORIDAD_UNO[[#This Row],[Tamaño]]="Extra Grande",154,176)))), FERIADOS[Fecha]), VLOOKUP(PRIORIDAD_UNO[[#This Row],[Nombre del requerimiento]],'Cálculos Manual'!A:F,6,FALSE))) -> 46359 | S33: =IF(PRIORIDAD_UNO[[#This Row],[Fin Desarrollo]]="","",IF(ISBLANK(VLOOKUP(PRIORIDAD_UNO[[#This Row],[Nombre del requerimiento]],'Cálculos Manual'!A:H,8,FALSE)),WORKDAY(PRIORIDAD_UNO[[#This Row],[Fin Desarrollo]],5,FERIADOS[Fecha]), VLOOKUP(PRIORIDAD_UNO[[#This Row],[Nombre del requerimiento]],'Cálculos Manual'!A:H,8,FALSE))) -> 46370 | T33: =IF(PRIORIDAD_UNO[[#This Row],[Comienzo Calidad]]="","",IF(ISBLANK(VLOOKUP(PRIORIDAD_UNO[[#This Row],[Nombre del requerimiento]],'Cálculos Manual'!A:J,10,FALSE)), WORKDAY(PRIORIDAD_UNO[[#This Row],[Comienzo Calidad]],IF(PRIORIDAD_UNO[[#This Row],[Tamaño]]="Pequeño",30,IF(PRIORIDAD_UNO[[#This Row],[Tamaño]]="Mediano",40,50)),FERIADOS[Fecha]), VLOOKUP(PRIORIDAD_UNO[[#This Row],[Nombre del requerimiento]],'Cálculos Manual'!A:J,10,FALSE))) -> 46428 | U33: =IF(PRIORIDAD_UNO[[#This Row],[Fin Calidad]]="","",IF(ISBLANK(VLOOKUP(PRIORIDAD_UNO[[#This Row],[Nombre del requerimiento]],'Cálculos Manual'!A:L,12,FALSE)), WORKDAY(PRIORIDAD_UNO[[#This Row],[Fin Calidad]],5,FERIADOS[Fecha]), VLOOKUP(PRIORIDAD_UNO[[#This Row],[Nombre del requerimiento]],'Cálculos Manual'!A:L,12,FALSE))) -> 46435 | V33: =IF(PRIORIDAD_UNO[[#This Row],[Comienzo Producción]]="","",IF(ISBLANK(VLOOKUP(PRIORIDAD_UNO[[#This Row],[Nombre del requerimiento]],'Cálculos Manual'!A:N,14,FALSE)), WORKDAY(PRIORIDAD_UNO[[#This Row],[Comienzo Producción]],IF(PRIORIDAD_UNO[[#This Row],[Tamaño]]="Grande",10,5),FERIADOS[Fecha]), VLOOKUP(PRIORIDAD_UNO[[#This Row],[Nombre del requerimiento]],'Cálculos Manual'!A:N,14,FALSE))) -> 46442 | W33: =IFERROR(PRIORIDAD_UNO[[#This Row],[Fin Producción]]-PRIORIDAD_UNO[[#This Row],[Comienzo Desarrollo]],"") -> 176 | X33: =IF(ISBLANK(PRIORIDAD_UNO[[#This Row],[Comienzo Desarrollo]]),"Sin Fecha","Con Fecha") -> Con Fecha | Y33: =IF(PRIORIDAD_UNO[[#This Row],[Esfuerzo Estimado Desarrollo]]="No definido","Sin esfuerzo","Con esfuerzo") -> Con esfuerzo | Z33: =IF(ISBLANK(PRIORIDAD_UNO[[#This Row],[Comienzo Desarrollo]]),"🔵 Sin Fecha", IF(PRIORIDAD_UNO[[#This Row],[Comienzo Desarrollo]]<TODAY(),"🔴 Vencido", IF(PRIORIDAD_UNO[[#This Row],[Comienzo Desarrollo]]=TODAY(),"🟡 Vence hoy", IF((PRIORIDAD_UNO[[#This Row],[Comienzo Desarrollo]]-TODAY())<=5,"🟠 Por vencer", "🟢 A tiempo")))) -> 🟢 A tiempo | AA33: =IF(PRIORIDAD_UNO[[#This Row],[Comienzo Producción]]="","Por Definir",_xlfn.CONCAT(YEAR(PRIORIDAD_UNO[[#This Row],[Comienzo Producción]])," - ", MONTH(PRIORIDAD_UNO[[#This Row],[Comienzo Producción]]))) -> 2027 - 2 | AB33: No está
A34: Realizar la inscripción de nuevos códigos y conceptos de pagos de la Universidad Nacional de Piura, así como cambiar las denominaciones señaladas. | B34: 1 | C34: 45 | D34: 1 mes | E34: =IF(OR(ISBLANK(PRIORIDAD_UNO[[#This Row],[Esfuerzo Estimado Desarrollo]]),PRIORIDAD_UNO[[#This Row],[Esfuerzo Estimado Desarrollo]]="No definido"),"No definido", IF(VALUE(TRIM(LEFT(PRIORIDAD_UNO[[#This Row],[Esfuerzo Estimado Desarrollo]],2)))<=1,"Pequeño", IF(VALUE(TRIM(LEFT(PRIORIDAD_UNO[[#This Row],[Esfuerzo Estimado Desarrollo]],2)))<=3,"Mediano", IF(VALUE(TRIM(LEFT(PRIORIDAD_UNO[[#This Row],[Esfuerzo Estimado Desarrollo]],2)))<=5,"Grande", IF(VALUE(TRIM(LEFT(PRIORIDAD_UNO[[#This Row],[Esfuerzo Estimado Desarrollo]],2)))<=7,"Extra Grande","Proyecto"))))) -> Pequeño | F34: Operaciones | G34: Servicios Bancarios y Recaudación | H34: Recaudación y Corresponsalía | I34: MEMORANDO N° 00000018 - 2026-BN/3243 | J34: Sí | K34: Evolutivo | L34: Pendiente de Atención | M34: Sistemas Bancarios | N34: Rossana Rojas | O34: Junior Quicaño | P34: Rutinario , solcitar aprobación tiene trámite 2025-T0901 | Q34: 46174 | R34: =IF(OR(PRIORIDAD_UNO[[#This Row],[Tamaño]]="No definido",ISBLANK(PRIORIDAD_UNO[[#This Row],[Comienzo Desarrollo]])),"",IF(ISBLANK( VLOOKUP(PRIORIDAD_UNO[[#This Row],[Nombre del requerimiento]],'Cálculos Manual'!A:F,6,FALSE)), WORKDAY(PRIORIDAD_UNO[[#This Row],[Comienzo Desarrollo]], IF(PRIORIDAD_UNO[[#This Row],[Tamaño]]="Pequeño",30,IF(PRIORIDAD_UNO[[#This Row],[Tamaño]]="Mediano",66,IF(PRIORIDAD_UNO[[#This Row],[Tamaño]]="Grande",110,IF(PRIORIDAD_UNO[[#This Row],[Tamaño]]="Extra Grande",154,176)))), FERIADOS[Fecha]), VLOOKUP(PRIORIDAD_UNO[[#This Row],[Nombre del requerimiento]],'Cálculos Manual'!A:F,6,FALSE))) -> 46217 | S34: =IF(PRIORIDAD_UNO[[#This Row],[Fin Desarrollo]]="","",IF(ISBLANK(VLOOKUP(PRIORIDAD_UNO[[#This Row],[Nombre del requerimiento]],'Cálculos Manual'!A:H,8,FALSE)),WORKDAY(PRIORIDAD_UNO[[#This Row],[Fin Desarrollo]],5,FERIADOS[Fecha]), VLOOKUP(PRIORIDAD_UNO[[#This Row],[Nombre del requerimiento]],'Cálculos Manual'!A:H,8,FALSE))) -> 46224 | T34: =IF(PRIORIDAD_UNO[[#This Row],[Comienzo Calidad]]="","",IF(ISBLANK(VLOOKUP(PRIORIDAD_UNO[[#This Row],[Nombre del requerimiento]],'Cálculos Manual'!A:J,10,FALSE)), WORKDAY(PRIORIDAD_UNO[[#This Row],[Comienzo Calidad]],IF(PRIORIDAD_UNO[[#This Row],[Tamaño]]="Pequeño",30,IF(PRIORIDAD_UNO[[#This Row],[Tamaño]]="Mediano",40,50)),FERIADOS[Fecha]), VLOOKUP(PRIORIDAD_UNO[[#This Row],[Nombre del requerimiento]],'Cálculos Manual'!A:J,10,FALSE))) -> 46272 | U34: =IF(PRIORIDAD_UNO[[#This Row],[Fin Calidad]]="","",IF(ISBLANK(VLOOKUP(PRIORIDAD_UNO[[#This Row],[Nombre del requerimiento]],'Cálculos Manual'!A:L,12,FALSE)), WORKDAY(PRIORIDAD_UNO[[#This Row],[Fin Calidad]],5,FERIADOS[Fecha]), VLOOKUP(PRIORIDAD_UNO[[#This Row],[Nombre del requerimiento]],'Cálculos Manual'!A:L,12,FALSE))) -> 46279 | V34: =IF(PRIORIDAD_UNO[[#This Row],[Comienzo Producción]]="","",IF(ISBLANK(VLOOKUP(PRIORIDAD_UNO[[#This Row],[Nombre del requerimiento]],'Cálculos Manual'!A:N,14,FALSE)), WORKDAY(PRIORIDAD_UNO[[#This Row],[Comienzo Producción]],IF(PRIORIDAD_UNO[[#This Row],[Tamaño]]="Grande",10,5),FERIADOS[Fecha]), VLOOKUP(PRIORIDAD_UNO[[#This Row],[Nombre del requerimiento]],'Cálculos Manual'!A:N,14,FALSE))) -> 46286 | W34: =IFERROR(PRIORIDAD_UNO[[#This Row],[Fin Producción]]-PRIORIDAD_UNO[[#This Row],[Comienzo Desarrollo]],"") -> 112 | X34: =IF(ISBLANK(PRIORIDAD_UNO[[#This Row],[Comienzo Desarrollo]]),"Sin Fecha","Con Fecha") -> Con Fecha | Y34: =IF(PRIORIDAD_UNO[[#This Row],[Esfuerzo Estimado Desarrollo]]="No definido","Sin esfuerzo","Con esfuerzo") -> Con esfuerzo | Z34: =IF(ISBLANK(PRIORIDAD_UNO[[#This Row],[Comienzo Desarrollo]]),"🔵 Sin Fecha", IF(PRIORIDAD_UNO[[#This Row],[Comienzo Desarrollo]]<TODAY(),"🔴 Vencido", IF(PRIORIDAD_UNO[[#This Row],[Comienzo Desarrollo]]=TODAY(),"🟡 Vence hoy", IF((PRIORIDAD_UNO[[#This Row],[Comienzo Desarrollo]]-TODAY())<=5,"🟠 Por vencer", "🟢 A tiempo")))) -> 🔴 Vencido | AA34: =IF(PRIORIDAD_UNO[[#This Row],[Comienzo Producción]]="","Por Definir",_xlfn.CONCAT(YEAR(PRIORIDAD_UNO[[#This Row],[Comienzo Producción]])," - ", MONTH(PRIORIDAD_UNO[[#This Row],[Comienzo Producción]]))) -> 2026 - 9 | AB34: No está
A35: Procesamiento de Credit Voucher and Merchandise Return | B35: 1 | C35: 8 | D35: 3 meses | E35: =IF(OR(ISBLANK(PRIORIDAD_UNO[[#This Row],[Esfuerzo Estimado Desarrollo]]),PRIORIDAD_UNO[[#This Row],[Esfuerzo Estimado Desarrollo]]="No definido"),"No definido", IF(VALUE(TRIM(LEFT(PRIORIDAD_UNO[[#This Row],[Esfuerzo Estimado Desarrollo]],2)))<=1,"Pequeño", IF(VALUE(TRIM(LEFT(PRIORIDAD_UNO[[#This Row],[Esfuerzo Estimado Desarrollo]],2)))<=3,"Mediano", IF(VALUE(TRIM(LEFT(PRIORIDAD_UNO[[#This Row],[Esfuerzo Estimado Desarrollo]],2)))<=5,"Grande", IF(VALUE(TRIM(LEFT(PRIORIDAD_UNO[[#This Row],[Esfuerzo Estimado Desarrollo]],2)))<=7,"Extra Grande","Proyecto"))))) -> Mediano | F35: Banca Digital | G35: Canales Alternos | H35: Canales Virtuales | I35: MEMORANDO N° 00000091 - 2026-BN/3252 | J35: Sí | K35: Mandatorio | L35: Pendiente de Atención | M35: Sistemas Bancarios | N35: Vladimir Cajavilca | O35: Omar Sarmiento | P35: La estimacion es realizada mediante el correo de maribel del viernes 15/05/2026 17:19 22/05/2026 En reunión con el área usuaria se informó que el anexo referenciado debe ser actualizado y dividido Tenía fecha de inicio 29/09/2026 pero no tiene anexo 2 | Q35: 46294 | R35: =IF(OR(PRIORIDAD_UNO[[#This Row],[Tamaño]]="No definido",ISBLANK(PRIORIDAD_UNO[[#This Row],[Comienzo Desarrollo]])),"",IF(ISBLANK( VLOOKUP(PRIORIDAD_UNO[[#This Row],[Nombre del requerimiento]],'Cálculos Manual'!A:F,6,FALSE)), WORKDAY(PRIORIDAD_UNO[[#This Row],[Comienzo Desarrollo]], IF(PRIORIDAD_UNO[[#This Row],[Tamaño]]="Pequeño",30,IF(PRIORIDAD_UNO[[#This Row],[Tamaño]]="Mediano",66,IF(PRIORIDAD_UNO[[#This Row],[Tamaño]]="Grande",110,IF(PRIORIDAD_UNO[[#This Row],[Tamaño]]="Extra Grande",154,176)))), FERIADOS[Fecha]), VLOOKUP(PRIORIDAD_UNO[[#This Row],[Nombre del requerimiento]],'Cálculos Manual'!A:F,6,FALSE))) -> 46393 | S35: =IF(PRIORIDAD_UNO[[#This Row],[Fin Desarrollo]]="","",IF(ISBLANK(VLOOKUP(PRIORIDAD_UNO[[#This Row],[Nombre del requerimiento]],'Cálculos Manual'!A:H,8,FALSE)),WORKDAY(PRIORIDAD_UNO[[#This Row],[Fin Desarrollo]],5,FERIADOS[Fecha]), VLOOKUP(PRIORIDAD_UNO[[#This Row],[Nombre del requerimiento]],'Cálculos Manual'!A:H,8,FALSE))) -> 46400 | T35: =IF(PRIORIDAD_UNO[[#This Row],[Comienzo Calidad]]="","",IF(ISBLANK(VLOOKUP(PRIORIDAD_UNO[[#This Row],[Nombre del requerimiento]],'Cálculos Manual'!A:J,10,FALSE)), WORKDAY(PRIORIDAD_UNO[[#This Row],[Comienzo Calidad]],IF(PRIORIDAD_UNO[[#This Row],[Tamaño]]="Pequeño",30,IF(PRIORIDAD_UNO[[#This Row],[Tamaño]]="Mediano",40,50)),FERIADOS[Fecha]), VLOOKUP(PRIORIDAD_UNO[[#This Row],[Nombre del requerimiento]],'Cálculos Manual'!A:J,10,FALSE))) -> 46456 | U35: =IF(PRIORIDAD_UNO[[#This Row],[Fin Calidad]]="","",IF(ISBLANK(VLOOKUP(PRIORIDAD_UNO[[#This Row],[Nombre del requerimiento]],'Cálculos Manual'!A:L,12,FALSE)), WORKDAY(PRIORIDAD_UNO[[#This Row],[Fin Calidad]],5,FERIADOS[Fecha]), VLOOKUP(PRIORIDAD_UNO[[#This Row],[Nombre del requerimiento]],'Cálculos Manual'!A:L,12,FALSE))) -> 46463 | V35: =IF(PRIORIDAD_UNO[[#This Row],[Comienzo Producción]]="","",IF(ISBLANK(VLOOKUP(PRIORIDAD_UNO[[#This Row],[Nombre del requerimiento]],'Cálculos Manual'!A:N,14,FALSE)), WORKDAY(PRIORIDAD_UNO[[#This Row],[Comienzo Producción]],IF(PRIORIDAD_UNO[[#This Row],[Tamaño]]="Grande",10,5),FERIADOS[Fecha]), VLOOKUP(PRIORIDAD_UNO[[#This Row],[Nombre del requerimiento]],'Cálculos Manual'!A:N,14,FALSE))) -> 46470 | W35: =IFERROR(PRIORIDAD_UNO[[#This Row],[Fin Producción]]-PRIORIDAD_UNO[[#This Row],[Comienzo Desarrollo]],"") -> 176 | X35: =IF(ISBLANK(PRIORIDAD_UNO[[#This Row],[Comienzo Desarrollo]]),"Sin Fecha","Con Fecha") -> Con Fecha | Y35: =IF(PRIORIDAD_UNO[[#This Row],[Esfuerzo Estimado Desarrollo]]="No definido","Sin esfuerzo","Con esfuerzo") -> Con esfuerzo | Z35: =IF(ISBLANK(PRIORIDAD_UNO[[#This Row],[Comienzo Desarrollo]]),"🔵 Sin Fecha", IF(PRIORIDAD_UNO[[#This Row],[Comienzo Desarrollo]]<TODAY(),"🔴 Vencido", IF(PRIORIDAD_UNO[[#This Row],[Comienzo Desarrollo]]=TODAY(),"🟡 Vence hoy", IF((PRIORIDAD_UNO[[#This Row],[Comienzo Desarrollo]]-TODAY())<=5,"🟠 Por vencer", "🟢 A tiempo")))) -> 🟢 A tiempo | AA35: =IF(PRIORIDAD_UNO[[#This Row],[Comienzo Producción]]="","Por Definir",_xlfn.CONCAT(YEAR(PRIORIDAD_UNO[[#This Row],[Comienzo Producción]])," - ", MONTH(PRIORIDAD_UNO[[#This Row],[Comienzo Producción]]))) -> 2027 - 3 | AB35: 3340
A36: Perdida de llaves Red de ATMs (Cód. 55) | B36: 1 | C36: 3 | D36: 3 meses | E36: =IF(OR(ISBLANK(PRIORIDAD_UNO[[#This Row],[Esfuerzo Estimado Desarrollo]]),PRIORIDAD_UNO[[#This Row],[Esfuerzo Estimado Desarrollo]]="No definido"),"No definido", IF(VALUE(TRIM(LEFT(PRIORIDAD_UNO[[#This Row],[Esfuerzo Estimado Desarrollo]],2)))<=1,"Pequeño", IF(VALUE(TRIM(LEFT(PRIORIDAD_UNO[[#This Row],[Esfuerzo Estimado Desarrollo]],2)))<=3,"Mediano", IF(VALUE(TRIM(LEFT(PRIORIDAD_UNO[[#This Row],[Esfuerzo Estimado Desarrollo]],2)))<=5,"Grande", IF(VALUE(TRIM(LEFT(PRIORIDAD_UNO[[#This Row],[Esfuerzo Estimado Desarrollo]],2)))<=7,"Extra Grande","Proyecto"))))) -> Mediano | F36: Banca Digital | G36: Canales Alternos | H36: Canales Presenciales | I36: MEMORANDO N° 00000044 - 2026-BN/3251 | J36: Sí | K36: Correctivo | L36: Pendiente de Atención | M36: Sistemas Bancarios | N36: Vladimir Cajavilca | O36: Omar Sarmiento | Q36: 46204 | R36: =IF(OR(PRIORIDAD_UNO[[#This Row],[Tamaño]]="No definido",ISBLANK(PRIORIDAD_UNO[[#This Row],[Comienzo Desarrollo]])),"",IF(ISBLANK( VLOOKUP(PRIORIDAD_UNO[[#This Row],[Nombre del requerimiento]],'Cálculos Manual'!A:F,6,FALSE)), WORKDAY(PRIORIDAD_UNO[[#This Row],[Comienzo Desarrollo]], IF(PRIORIDAD_UNO[[#This Row],[Tamaño]]="Pequeño",30,IF(PRIORIDAD_UNO[[#This Row],[Tamaño]]="Mediano",66,IF(PRIORIDAD_UNO[[#This Row],[Tamaño]]="Grande",110,IF(PRIORIDAD_UNO[[#This Row],[Tamaño]]="Extra Grande",154,176)))), FERIADOS[Fecha]), VLOOKUP(PRIORIDAD_UNO[[#This Row],[Nombre del requerimiento]],'Cálculos Manual'!A:F,6,FALSE))) -> 46302 | S36: =IF(PRIORIDAD_UNO[[#This Row],[Fin Desarrollo]]="","",IF(ISBLANK(VLOOKUP(PRIORIDAD_UNO[[#This Row],[Nombre del requerimiento]],'Cálculos Manual'!A:H,8,FALSE)),WORKDAY(PRIORIDAD_UNO[[#This Row],[Fin Desarrollo]],5,FERIADOS[Fecha]), VLOOKUP(PRIORIDAD_UNO[[#This Row],[Nombre del requerimiento]],'Cálculos Manual'!A:H,8,FALSE))) -> 46310 | T36: =IF(PRIORIDAD_UNO[[#This Row],[Comienzo Calidad]]="","",IF(ISBLANK(VLOOKUP(PRIORIDAD_UNO[[#This Row],[Nombre del requerimiento]],'Cálculos Manual'!A:J,10,FALSE)), WORKDAY(PRIORIDAD_UNO[[#This Row],[Comienzo Calidad]],IF(PRIORIDAD_UNO[[#This Row],[Tamaño]]="Pequeño",30,IF(PRIORIDAD_UNO[[#This Row],[Tamaño]]="Mediano",40,50)),FERIADOS[Fecha]), VLOOKUP(PRIORIDAD_UNO[[#This Row],[Nombre del requerimiento]],'Cálculos Manual'!A:J,10,FALSE))) -> 46370 | U36: =IF(PRIORIDAD_UNO[[#This Row],[Fin Calidad]]="","",IF(ISBLANK(VLOOKUP(PRIORIDAD_UNO[[#This Row],[Nombre del requerimiento]],'Cálculos Manual'!A:L,12,FALSE)), WORKDAY(PRIORIDAD_UNO[[#This Row],[Fin Calidad]],5,FERIADOS[Fecha]), VLOOKUP(PRIORIDAD_UNO[[#This Row],[Nombre del requerimiento]],'Cálculos Manual'!A:L,12,FALSE))) -> 46377 | V36: =IF(PRIORIDAD_UNO[[#This Row],[Comienzo Producción]]="","",IF(ISBLANK(VLOOKUP(PRIORIDAD_UNO[[#This Row],[Nombre del requerimiento]],'Cálculos Manual'!A:N,14,FALSE)), WORKDAY(PRIORIDAD_UNO[[#This Row],[Comienzo Producción]],IF(PRIORIDAD_UNO[[#This Row],[Tamaño]]="Grande",10,5),FERIADOS[Fecha]), VLOOKUP(PRIORIDAD_UNO[[#This Row],[Nombre del requerimiento]],'Cálculos Manual'!A:N,14,FALSE))) -> 46385 | W36: =IFERROR(PRIORIDAD_UNO[[#This Row],[Fin Producción]]-PRIORIDAD_UNO[[#This Row],[Comienzo Desarrollo]],"") -> 181 | X36: =IF(ISBLANK(PRIORIDAD_UNO[[#This Row],[Comienzo Desarrollo]]),"Sin Fecha","Con Fecha") -> Con Fecha | Y36: =IF(PRIORIDAD_UNO[[#This Row],[Esfuerzo Estimado Desarrollo]]="No definido","Sin esfuerzo","Con esfuerzo") -> Con esfuerzo | Z36: =IF(ISBLANK(PRIORIDAD_UNO[[#This Row],[Comienzo Desarrollo]]),"🔵 Sin Fecha", IF(PRIORIDAD_UNO[[#This Row],[Comienzo Desarrollo]]<TODAY(),"🔴 Vencido", IF(PRIORIDAD_UNO[[#This Row],[Comienzo Desarrollo]]=TODAY(),"🟡 Vence hoy", IF((PRIORIDAD_UNO[[#This Row],[Comienzo Desarrollo]]-TODAY())<=5,"🟠 Por vencer", "🟢 A tiempo")))) -> 🟢 A tiempo | AA36: =IF(PRIORIDAD_UNO[[#This Row],[Comienzo Producción]]="","Por Definir",_xlfn.CONCAT(YEAR(PRIORIDAD_UNO[[#This Row],[Comienzo Producción]])," - ", MONTH(PRIORIDAD_UNO[[#This Row],[Comienzo Producción]]))) -> 2026 - 12 | AB36: No está
A37: Pago electronico para embargos SUNAT, SUNAT-MEF-BN iniciaron acuerdos a fin de implementar el pago electónico para embargos de retenciones notificados por los ejecutores coactivos de la SUNAT a las unidades ejecutoras del sector público | B37: 1 | C37: 30 | D37: 3 meses | E37: =IF(OR(ISBLANK(PRIORIDAD_UNO[[#This Row],[Esfuerzo Estimado Desarrollo]]),PRIORIDAD_UNO[[#This Row],[Esfuerzo Estimado Desarrollo]]="No definido"),"No definido", IF(VALUE(TRIM(LEFT(PRIORIDAD_UNO[[#This Row],[Esfuerzo Estimado Desarrollo]],2)))<=1,"Pequeño", IF(VALUE(TRIM(LEFT(PRIORIDAD_UNO[[#This Row],[Esfuerzo Estimado Desarrollo]],2)))<=3,"Mediano", IF(VALUE(TRIM(LEFT(PRIORIDAD_UNO[[#This Row],[Esfuerzo Estimado Desarrollo]],2)))<=5,"Grande", IF(VALUE(TRIM(LEFT(PRIORIDAD_UNO[[#This Row],[Esfuerzo Estimado Desarrollo]],2)))<=7,"Extra Grande","Proyecto"))))) -> Mediano | F37: Operaciones | G37: Servicios Bancarios y Recaudación | H37: Recaudación y Corresponsalía | I37: MEMORANDO N° 00000255 - 2025-BN/3243 | J37: Sí | K37: Evolutivo | L37: Pendiente de Atención | M37: Sistemas Bancarios | N37: Fiorella Galván | O37: Junior Quicaño | Q37: 46216 | R37: =IF(OR(PRIORIDAD_UNO[[#This Row],[Tamaño]]="No definido",ISBLANK(PRIORIDAD_UNO[[#This Row],[Comienzo Desarrollo]])),"",IF(ISBLANK( VLOOKUP(PRIORIDAD_UNO[[#This Row],[Nombre del requerimiento]],'Cálculos Manual'!A:F,6,FALSE)), WORKDAY(PRIORIDAD_UNO[[#This Row],[Comienzo Desarrollo]], IF(PRIORIDAD_UNO[[#This Row],[Tamaño]]="Pequeño",30,IF(PRIORIDAD_UNO[[#This Row],[Tamaño]]="Mediano",66,IF(PRIORIDAD_UNO[[#This Row],[Tamaño]]="Grande",110,IF(PRIORIDAD_UNO[[#This Row],[Tamaño]]="Extra Grande",154,176)))), FERIADOS[Fecha]), VLOOKUP(PRIORIDAD_UNO[[#This Row],[Nombre del requerimiento]],'Cálculos Manual'!A:F,6,FALSE))) -> 46315 | S37: =IF(PRIORIDAD_UNO[[#This Row],[Fin Desarrollo]]="","",IF(ISBLANK(VLOOKUP(PRIORIDAD_UNO[[#This Row],[Nombre del requerimiento]],'Cálculos Manual'!A:H,8,FALSE)),WORKDAY(PRIORIDAD_UNO[[#This Row],[Fin Desarrollo]],5,FERIADOS[Fecha]), VLOOKUP(PRIORIDAD_UNO[[#This Row],[Nombre del requerimiento]],'Cálculos Manual'!A:H,8,FALSE))) -> 46322 | T37: =IF(PRIORIDAD_UNO[[#This Row],[Comienzo Calidad]]="","",IF(ISBLANK(VLOOKUP(PRIORIDAD_UNO[[#This Row],[Nombre del requerimiento]],'Cálculos Manual'!A:J,10,FALSE)), WORKDAY(PRIORIDAD_UNO[[#This Row],[Comienzo Calidad]],IF(PRIORIDAD_UNO[[#This Row],[Tamaño]]="Pequeño",30,IF(PRIORIDAD_UNO[[#This Row],[Tamaño]]="Mediano",40,50)),FERIADOS[Fecha]), VLOOKUP(PRIORIDAD_UNO[[#This Row],[Nombre del requerimiento]],'Cálculos Manual'!A:J,10,FALSE))) -> 46380 | U37: =IF(PRIORIDAD_UNO[[#This Row],[Fin Calidad]]="","",IF(ISBLANK(VLOOKUP(PRIORIDAD_UNO[[#This Row],[Nombre del requerimiento]],'Cálculos Manual'!A:L,12,FALSE)), WORKDAY(PRIORIDAD_UNO[[#This Row],[Fin Calidad]],5,FERIADOS[Fecha]), VLOOKUP(PRIORIDAD_UNO[[#This Row],[Nombre del requerimiento]],'Cálculos Manual'!A:L,12,FALSE))) -> 46391 | V37: =IF(PRIORIDAD_UNO[[#This Row],[Comienzo Producción]]="","",IF(ISBLANK(VLOOKUP(PRIORIDAD_UNO[[#This Row],[Nombre del requerimiento]],'Cálculos Manual'!A:N,14,FALSE)), WORKDAY(PRIORIDAD_UNO[[#This Row],[Comienzo Producción]],IF(PRIORIDAD_UNO[[#This Row],[Tamaño]]="Grande",10,5),FERIADOS[Fecha]), VLOOKUP(PRIORIDAD_UNO[[#This Row],[Nombre del requerimiento]],'Cálculos Manual'!A:N,14,FALSE))) -> 46398 | W37: =IFERROR(PRIORIDAD_UNO[[#This Row],[Fin Producción]]-PRIORIDAD_UNO[[#This Row],[Comienzo Desarrollo]],"") -> 182 | X37: =IF(ISBLANK(PRIORIDAD_UNO[[#This Row],[Comienzo Desarrollo]]),"Sin Fecha","Con Fecha") -> Con Fecha | Y37: =IF(PRIORIDAD_UNO[[#This Row],[Esfuerzo Estimado Desarrollo]]="No definido","Sin esfuerzo","Con esfuerzo") -> Con esfuerzo | Z37: =IF(ISBLANK(PRIORIDAD_UNO[[#This Row],[Comienzo Desarrollo]]),"🔵 Sin Fecha", IF(PRIORIDAD_UNO[[#This Row],[Comienzo Desarrollo]]<TODAY(),"🔴 Vencido", IF(PRIORIDAD_UNO[[#This Row],[Comienzo Desarrollo]]=TODAY(),"🟡 Vence hoy", IF((PRIORIDAD_UNO[[#This Row],[Comienzo Desarrollo]]-TODAY())<=5,"🟠 Por vencer", "🟢 A tiempo")))) -> 🟢 A tiempo | AA37: =IF(PRIORIDAD_UNO[[#This Row],[Comienzo Producción]]="","Por Definir",_xlfn.CONCAT(YEAR(PRIORIDAD_UNO[[#This Row],[Comienzo Producción]])," - ", MONTH(PRIORIDAD_UNO[[#This Row],[Comienzo Producción]]))) -> 2027 - 1 | AB37: 3135
A38: Nueva transacción para el control de Ingresos y devoluciones de Garantías | B38: 1 | C38: 2 | D38: No definido | E38: =IF(OR(ISBLANK(PRIORIDAD_UNO[[#This Row],[Esfuerzo Estimado Desarrollo]]),PRIORIDAD_UNO[[#This Row],[Esfuerzo Estimado Desarrollo]]="No definido"),"No definido", IF(VALUE(TRIM(LEFT(PRIORIDAD_UNO[[#This Row],[Esfuerzo Estimado Desarrollo]],2)))<=1,"Pequeño", IF(VALUE(TRIM(LEFT(PRIORIDAD_UNO[[#This Row],[Esfuerzo Estimado Desarrollo]],2)))<=3,"Mediano", IF(VALUE(TRIM(LEFT(PRIORIDAD_UNO[[#This Row],[Esfuerzo Estimado Desarrollo]],2)))<=5,"Grande", IF(VALUE(TRIM(LEFT(PRIORIDAD_UNO[[#This Row],[Esfuerzo Estimado Desarrollo]],2)))<=7,"Extra Grande","Proyecto"))))) -> No definido | F38: Operaciones | G38: Servicios Bancarios y Recaudación | H38: Recaudación y Corresponsalía | I38: MEMORANDO N° 00000028 - 2026-BN/3243 | J38: Sí | K38: Recomendación | L38: Por evaluar | M38: Sistemas Bancarios | N38: Jorge Rueda | O38: Junior Quicaño | P38: El requerimiento debe ser evaluado por el equipo de Construcción, se coordinará con Eduardo Cardenas para desiganar analista o supervisior responsable de atención. | R38: =IF(OR(PRIORIDAD_UNO[[#This Row],[Tamaño]]="No definido",ISBLANK(PRIORIDAD_UNO[[#This Row],[Comienzo Desarrollo]])),"",IF(ISBLANK( VLOOKUP(PRIORIDAD_UNO[[#This Row],[Nombre del requerimiento]],'Cálculos Manual'!A:F,6,FALSE)), WORKDAY(PRIORIDAD_UNO[[#This Row],[Comienzo Desarrollo]], IF(PRIORIDAD_UNO[[#This Row],[Tamaño]]="Pequeño",30,IF(PRIORIDAD_UNO[[#This Row],[Tamaño]]="Mediano",66,IF(PRIORIDAD_UNO[[#This Row],[Tamaño]]="Grande",110,IF(PRIORIDAD_UNO[[#This Row],[Tamaño]]="Extra Grande",154,176)))), FERIADOS[Fecha]), VLOOKUP(PRIORIDAD_UNO[[#This Row],[Nombre del requerimiento]],'Cálculos Manual'!A:F,6,FALSE))) | S38: =IF(PRIORIDAD_UNO[[#This Row],[Fin Desarrollo]]="","",IF(ISBLANK(VLOOKUP(PRIORIDAD_UNO[[#This Row],[Nombre del requerimiento]],'Cálculos Manual'!A:H,8,FALSE)),WORKDAY(PRIORIDAD_UNO[[#This Row],[Fin Desarrollo]],5,FERIADOS[Fecha]), VLOOKUP(PRIORIDAD_UNO[[#This Row],[Nombre del requerimiento]],'Cálculos Manual'!A:H,8,FALSE))) | T38: =IF(PRIORIDAD_UNO[[#This Row],[Comienzo Calidad]]="","",IF(ISBLANK(VLOOKUP(PRIORIDAD_UNO[[#This Row],[Nombre del requerimiento]],'Cálculos Manual'!A:J,10,FALSE)), WORKDAY(PRIORIDAD_UNO[[#This Row],[Comienzo Calidad]],IF(PRIORIDAD_UNO[[#This Row],[Tamaño]]="Pequeño",30,IF(PRIORIDAD_UNO[[#This Row],[Tamaño]]="Mediano",40,50)),FERIADOS[Fecha]), VLOOKUP(PRIORIDAD_UNO[[#This Row],[Nombre del requerimiento]],'Cálculos Manual'!A:J,10,FALSE))) | U38: =IF(PRIORIDAD_UNO[[#This Row],[Fin Calidad]]="","",IF(ISBLANK(VLOOKUP(PRIORIDAD_UNO[[#This Row],[Nombre del requerimiento]],'Cálculos Manual'!A:L,12,FALSE)), WORKDAY(PRIORIDAD_UNO[[#This Row],[Fin Calidad]],5,FERIADOS[Fecha]), VLOOKUP(PRIORIDAD_UNO[[#This Row],[Nombre del requerimiento]],'Cálculos Manual'!A:L,12,FALSE))) | V38: =IF(PRIORIDAD_UNO[[#This Row],[Comienzo Producción]]="","",IF(ISBLANK(VLOOKUP(PRIORIDAD_UNO[[#This Row],[Nombre del requerimiento]],'Cálculos Manual'!A:N,14,FALSE)), WORKDAY(PRIORIDAD_UNO[[#This Row],[Comienzo Producción]],IF(PRIORIDAD_UNO[[#This Row],[Tamaño]]="Grande",10,5),FERIADOS[Fecha]), VLOOKUP(PRIORIDAD_UNO[[#This Row],[Nombre del requerimiento]],'Cálculos Manual'!A:N,14,FALSE))) | W38: =IFERROR(PRIORIDAD_UNO[[#This Row],[Fin Producción]]-PRIORIDAD_UNO[[#This Row],[Comienzo Desarrollo]],"") | X38: =IF(ISBLANK(PRIORIDAD_UNO[[#This Row],[Comienzo Desarrollo]]),"Sin Fecha","Con Fecha") -> Sin Fecha | Y38: =IF(PRIORIDAD_UNO[[#This Row],[Esfuerzo Estimado Desarrollo]]="No definido","Sin esfuerzo","Con esfuerzo") -> Sin esfuerzo | Z38: =IF(ISBLANK(PRIORIDAD_UNO[[#This Row],[Comienzo Desarrollo]]),"🔵 Sin Fecha", IF(PRIORIDAD_UNO[[#This Row],[Comienzo Desarrollo]]<TODAY(),"🔴 Vencido", IF(PRIORIDAD_UNO[[#This Row],[Comienzo Desarrollo]]=TODAY(),"🟡 Vence hoy", IF((PRIORIDAD_UNO[[#This Row],[Comienzo Desarrollo]]-TODAY())<=5,"🟠 Por vencer", "🟢 A tiempo")))) -> 🔵 Sin Fecha | AA38: =IF(PRIORIDAD_UNO[[#This Row],[Comienzo Producción]]="","Por Definir",_xlfn.CONCAT(YEAR(PRIORIDAD_UNO[[#This Row],[Comienzo Producción]])," - ", MONTH(PRIORIDAD_UNO[[#This Row],[Comienzo Producción]]))) -> Por Definir | AB38: 3236
A39: Nueva estructura para la Apertura de cuentas de ahorro Masivas e Individuales | B39: 1 | C39: 31 | D39: 6 meses | E39: =IF(OR(ISBLANK(PRIORIDAD_UNO[[#This Row],[Esfuerzo Estimado Desarrollo]]),PRIORIDAD_UNO[[#This Row],[Esfuerzo Estimado Desarrollo]]="No definido"),"No definido", IF(VALUE(TRIM(LEFT(PRIORIDAD_UNO[[#This Row],[Esfuerzo Estimado Desarrollo]],2)))<=1,"Pequeño", IF(VALUE(TRIM(LEFT(PRIORIDAD_UNO[[#This Row],[Esfuerzo Estimado Desarrollo]],2)))<=3,"Mediano", IF(VALUE(TRIM(LEFT(PRIORIDAD_UNO[[#This Row],[Esfuerzo Estimado Desarrollo]],2)))<=5,"Grande", IF(VALUE(TRIM(LEFT(PRIORIDAD_UNO[[#This Row],[Esfuerzo Estimado Desarrollo]],2)))<=7,"Extra Grande","Proyecto"))))) -> Extra Grande | F39: Operaciones | G39: SubGerencia de Captaciones y Pagaduria | H39: Apertura de Cuentas | I39: MEMORANDO N° 00000150 - 2026-BN/3111 | J39: Sí | K39: Correctivo | L39: Pendiente de Atención | M39: Sistemas Bancarios | N39: Johnny Rocca | O39: Junior Quicaño | Q39: 46391 | R39: =IF(OR(PRIORIDAD_UNO[[#This Row],[Tamaño]]="No definido",ISBLANK(PRIORIDAD_UNO[[#This Row],[Comienzo Desarrollo]])),"",IF(ISBLANK( VLOOKUP(PRIORIDAD_UNO[[#This Row],[Nombre del requerimiento]],'Cálculos Manual'!A:F,6,FALSE)), WORKDAY(PRIORIDAD_UNO[[#This Row],[Comienzo Desarrollo]], IF(PRIORIDAD_UNO[[#This Row],[Tamaño]]="Pequeño",30,IF(PRIORIDAD_UNO[[#This Row],[Tamaño]]="Mediano",66,IF(PRIORIDAD_UNO[[#This Row],[Tamaño]]="Grande",110,IF(PRIORIDAD_UNO[[#This Row],[Tamaño]]="Extra Grande",154,176)))), FERIADOS[Fecha]), VLOOKUP(PRIORIDAD_UNO[[#This Row],[Nombre del requerimiento]],'Cálculos Manual'!A:F,6,FALSE))) -> 46617 | S39: =IF(PRIORIDAD_UNO[[#This Row],[Fin Desarrollo]]="","",IF(ISBLANK(VLOOKUP(PRIORIDAD_UNO[[#This Row],[Nombre del requerimiento]],'Cálculos Manual'!A:H,8,FALSE)),WORKDAY(PRIORIDAD_UNO[[#This Row],[Fin Desarrollo]],5,FERIADOS[Fecha]), VLOOKUP(PRIORIDAD_UNO[[#This Row],[Nombre del requerimiento]],'Cálculos Manual'!A:H,8,FALSE))) -> 46624 | T39: =IF(PRIORIDAD_UNO[[#This Row],[Comienzo Calidad]]="","",IF(ISBLANK(VLOOKUP(PRIORIDAD_UNO[[#This Row],[Nombre del requerimiento]],'Cálculos Manual'!A:J,10,FALSE)), WORKDAY(PRIORIDAD_UNO[[#This Row],[Comienzo Calidad]],IF(PRIORIDAD_UNO[[#This Row],[Tamaño]]="Pequeño",30,IF(PRIORIDAD_UNO[[#This Row],[Tamaño]]="Mediano",40,50)),FERIADOS[Fecha]), VLOOKUP(PRIORIDAD_UNO[[#This Row],[Nombre del requerimiento]],'Cálculos Manual'!A:J,10,FALSE))) -> 46699 | U39: =IF(PRIORIDAD_UNO[[#This Row],[Fin Calidad]]="","",IF(ISBLANK(VLOOKUP(PRIORIDAD_UNO[[#This Row],[Nombre del requerimiento]],'Cálculos Manual'!A:L,12,FALSE)), WORKDAY(PRIORIDAD_UNO[[#This Row],[Fin Calidad]],5,FERIADOS[Fecha]), VLOOKUP(PRIORIDAD_UNO[[#This Row],[Nombre del requerimiento]],'Cálculos Manual'!A:L,12,FALSE))) -> 46706 | V39: =IF(PRIORIDAD_UNO[[#This Row],[Comienzo Producción]]="","",IF(ISBLANK(VLOOKUP(PRIORIDAD_UNO[[#This Row],[Nombre del requerimiento]],'Cálculos Manual'!A:N,14,FALSE)), WORKDAY(PRIORIDAD_UNO[[#This Row],[Comienzo Producción]],IF(PRIORIDAD_UNO[[#This Row],[Tamaño]]="Grande",10,5),FERIADOS[Fecha]), VLOOKUP(PRIORIDAD_UNO[[#This Row],[Nombre del requerimiento]],'Cálculos Manual'!A:N,14,FALSE))) -> 46713 | W39: =IFERROR(PRIORIDAD_UNO[[#This Row],[Fin Producción]]-PRIORIDAD_UNO[[#This Row],[Comienzo Desarrollo]],"") -> 322 | X39: =IF(ISBLANK(PRIORIDAD_UNO[[#This Row],[Comienzo Desarrollo]]),"Sin Fecha","Con Fecha") -> Con Fecha | Y39: =IF(PRIORIDAD_UNO[[#This Row],[Esfuerzo Estimado Desarrollo]]="No definido","Sin esfuerzo","Con esfuerzo") -> Con esfuerzo | Z39: =IF(ISBLANK(PRIORIDAD_UNO[[#This Row],[Comienzo Desarrollo]]),"🔵 Sin Fecha", IF(PRIORIDAD_UNO[[#This Row],[Comienzo Desarrollo]]<TODAY(),"🔴 Vencido", IF(PRIORIDAD_UNO[[#This Row],[Comienzo Desarrollo]]=TODAY(),"🟡 Vence hoy", IF((PRIORIDAD_UNO[[#This Row],[Comienzo Desarrollo]]-TODAY())<=5,"🟠 Por vencer", "🟢 A tiempo")))) -> 🟢 A tiempo | AA39: =IF(PRIORIDAD_UNO[[#This Row],[Comienzo Producción]]="","Por Definir",_xlfn.CONCAT(YEAR(PRIORIDAD_UNO[[#This Row],[Comienzo Producción]])," - ", MONTH(PRIORIDAD_UNO[[#This Row],[Comienzo Producción]]))) -> 2027 - 11 | AB39: 3230
A40: Notificación de Operaciones de Retiro con tarjeta de Débito, crédito y transacciones que deben generar alertas – Canal Ventanilla | B40: 1 | C40: 1 | D40: 9 meses | E40: =IF(OR(ISBLANK(PRIORIDAD_UNO[[#This Row],[Esfuerzo Estimado Desarrollo]]),PRIORIDAD_UNO[[#This Row],[Esfuerzo Estimado Desarrollo]]="No definido"),"No definido", IF(VALUE(TRIM(LEFT(PRIORIDAD_UNO[[#This Row],[Esfuerzo Estimado Desarrollo]],2)))<=1,"Pequeño", IF(VALUE(TRIM(LEFT(PRIORIDAD_UNO[[#This Row],[Esfuerzo Estimado Desarrollo]],2)))<=3,"Mediano", IF(VALUE(TRIM(LEFT(PRIORIDAD_UNO[[#This Row],[Esfuerzo Estimado Desarrollo]],2)))<=5,"Grande", IF(VALUE(TRIM(LEFT(PRIORIDAD_UNO[[#This Row],[Esfuerzo Estimado Desarrollo]],2)))<=7,"Extra Grande","Proyecto"))))) -> Proyecto | F40: Red de Agencias | G40: Red de Agencias | H40: Red de Agencias | I40: MEMORANDO N° 00000321 - 2026-BN/9700 | J40: Sí | K40: Normativo | L40: Pendiente de Atención | M40: Sistemas Bancarios | N40: Rossana Rojas | O40: María Barboza | P40: Se atenderá con la FBS | Q40: 46266 | R40: =IF(OR(PRIORIDAD_UNO[[#This Row],[Tamaño]]="No definido",ISBLANK(PRIORIDAD_UNO[[#This Row],[Comienzo Desarrollo]])),"",IF(ISBLANK( VLOOKUP(PRIORIDAD_UNO[[#This Row],[Nombre del requerimiento]],'Cálculos Manual'!A:F,6,FALSE)), WORKDAY(PRIORIDAD_UNO[[#This Row],[Comienzo Desarrollo]], IF(PRIORIDAD_UNO[[#This Row],[Tamaño]]="Pequeño",30,IF(PRIORIDAD_UNO[[#This Row],[Tamaño]]="Mediano",66,IF(PRIORIDAD_UNO[[#This Row],[Tamaño]]="Grande",110,IF(PRIORIDAD_UNO[[#This Row],[Tamaño]]="Extra Grande",154,176)))), FERIADOS[Fecha]), VLOOKUP(PRIORIDAD_UNO[[#This Row],[Nombre del requerimiento]],'Cálculos Manual'!A:F,6,FALSE))) -> 46521 | S40: =IF(PRIORIDAD_UNO[[#This Row],[Fin Desarrollo]]="","",IF(ISBLANK(VLOOKUP(PRIORIDAD_UNO[[#This Row],[Nombre del requerimiento]],'Cálculos Manual'!A:H,8,FALSE)),WORKDAY(PRIORIDAD_UNO[[#This Row],[Fin Desarrollo]],5,FERIADOS[Fecha]), VLOOKUP(PRIORIDAD_UNO[[#This Row],[Nombre del requerimiento]],'Cálculos Manual'!A:H,8,FALSE))) -> 46528 | T40: =IF(PRIORIDAD_UNO[[#This Row],[Comienzo Calidad]]="","",IF(ISBLANK(VLOOKUP(PRIORIDAD_UNO[[#This Row],[Nombre del requerimiento]],'Cálculos Manual'!A:J,10,FALSE)), WORKDAY(PRIORIDAD_UNO[[#This Row],[Comienzo Calidad]],IF(PRIORIDAD_UNO[[#This Row],[Tamaño]]="Pequeño",30,IF(PRIORIDAD_UNO[[#This Row],[Tamaño]]="Mediano",40,50)),FERIADOS[Fecha]), VLOOKUP(PRIORIDAD_UNO[[#This Row],[Nombre del requerimiento]],'Cálculos Manual'!A:J,10,FALSE))) -> 46605 | U40: =IF(PRIORIDAD_UNO[[#This Row],[Fin Calidad]]="","",IF(ISBLANK(VLOOKUP(PRIORIDAD_UNO[[#This Row],[Nombre del requerimiento]],'Cálculos Manual'!A:L,12,FALSE)), WORKDAY(PRIORIDAD_UNO[[#This Row],[Fin Calidad]],5,FERIADOS[Fecha]), VLOOKUP(PRIORIDAD_UNO[[#This Row],[Nombre del requerimiento]],'Cálculos Manual'!A:L,12,FALSE))) -> 46615 | V40: =IF(PRIORIDAD_UNO[[#This Row],[Comienzo Producción]]="","",IF(ISBLANK(VLOOKUP(PRIORIDAD_UNO[[#This Row],[Nombre del requerimiento]],'Cálculos Manual'!A:N,14,FALSE)), WORKDAY(PRIORIDAD_UNO[[#This Row],[Comienzo Producción]],IF(PRIORIDAD_UNO[[#This Row],[Tamaño]]="Grande",10,5),FERIADOS[Fecha]), VLOOKUP(PRIORIDAD_UNO[[#This Row],[Nombre del requerimiento]],'Cálculos Manual'!A:N,14,FALSE))) -> 46622 | W40: =IFERROR(PRIORIDAD_UNO[[#This Row],[Fin Producción]]-PRIORIDAD_UNO[[#This Row],[Comienzo Desarrollo]],"") -> 356 | X40: =IF(ISBLANK(PRIORIDAD_UNO[[#This Row],[Comienzo Desarrollo]]),"Sin Fecha","Con Fecha") -> Con Fecha | Y40: =IF(PRIORIDAD_UNO[[#This Row],[Esfuerzo Estimado Desarrollo]]="No definido","Sin esfuerzo","Con esfuerzo") -> Con esfuerzo | Z40: =IF(ISBLANK(PRIORIDAD_UNO[[#This Row],[Comienzo Desarrollo]]),"🔵 Sin Fecha", IF(PRIORIDAD_UNO[[#This Row],[Comienzo Desarrollo]]<TODAY(),"🔴 Vencido", IF(PRIORIDAD_UNO[[#This Row],[Comienzo Desarrollo]]=TODAY(),"🟡 Vence hoy", IF((PRIORIDAD_UNO[[#This Row],[Comienzo Desarrollo]]-TODAY())<=5,"🟠 Por vencer", "🟢 A tiempo")))) -> 🟢 A tiempo | AA40: =IF(PRIORIDAD_UNO[[#This Row],[Comienzo Producción]]="","Por Definir",_xlfn.CONCAT(YEAR(PRIORIDAD_UNO[[#This Row],[Comienzo Producción]])," - ", MONTH(PRIORIDAD_UNO[[#This Row],[Comienzo Producción]]))) -> 2027 - 8 | AB40: No está
A41: Modificar regla de Negocio respecto al cobro de ITF EN OPERACIONES DE TRNASFERENCIAS ENTRE CUENTAS DEL MISMO TITULAR(Mismo Banco e Interbancarias) | B41: 1 | C41: 5 | D41: 4 meses | E41: =IF(OR(ISBLANK(PRIORIDAD_UNO[[#This Row],[Esfuerzo Estimado Desarrollo]]),PRIORIDAD_UNO[[#This Row],[Esfuerzo Estimado Desarrollo]]="No definido"),"No definido", IF(VALUE(TRIM(LEFT(PRIORIDAD_UNO[[#This Row],[Esfuerzo Estimado Desarrollo]],2)))<=1,"Pequeño", IF(VALUE(TRIM(LEFT(PRIORIDAD_UNO[[#This Row],[Esfuerzo Estimado Desarrollo]],2)))<=3,"Mediano", IF(VALUE(TRIM(LEFT(PRIORIDAD_UNO[[#This Row],[Esfuerzo Estimado Desarrollo]],2)))<=5,"Grande", IF(VALUE(TRIM(LEFT(PRIORIDAD_UNO[[#This Row],[Esfuerzo Estimado Desarrollo]],2)))<=7,"Extra Grande","Proyecto"))))) -> Grande | F41: Operaciones | G41: SubGerencia de Captaciones y Pagaduria | H41: Sistema de Pagos | I41: MEMORANDO N° 00000180 - 2025-BN/3116 | J41: Sí | K41: Recomendación | L41: Pendiente de Atención | M41: Sistemas Bancarios | N41: Adolfo Escobar | O41: Junior Quicaño | P41: Anexo 2 sale correctivo. | Q41: 46237 | R41: =IF(OR(PRIORIDAD_UNO[[#This Row],[Tamaño]]="No definido",ISBLANK(PRIORIDAD_UNO[[#This Row],[Comienzo Desarrollo]])),"",IF(ISBLANK( VLOOKUP(PRIORIDAD_UNO[[#This Row],[Nombre del requerimiento]],'Cálculos Manual'!A:F,6,FALSE)), WORKDAY(PRIORIDAD_UNO[[#This Row],[Comienzo Desarrollo]], IF(PRIORIDAD_UNO[[#This Row],[Tamaño]]="Pequeño",30,IF(PRIORIDAD_UNO[[#This Row],[Tamaño]]="Mediano",66,IF(PRIORIDAD_UNO[[#This Row],[Tamaño]]="Grande",110,IF(PRIORIDAD_UNO[[#This Row],[Tamaño]]="Extra Grande",154,176)))), FERIADOS[Fecha]), VLOOKUP(PRIORIDAD_UNO[[#This Row],[Nombre del requerimiento]],'Cálculos Manual'!A:F,6,FALSE))) -> 46399 | S41: =IF(PRIORIDAD_UNO[[#This Row],[Fin Desarrollo]]="","",IF(ISBLANK(VLOOKUP(PRIORIDAD_UNO[[#This Row],[Nombre del requerimiento]],'Cálculos Manual'!A:H,8,FALSE)),WORKDAY(PRIORIDAD_UNO[[#This Row],[Fin Desarrollo]],5,FERIADOS[Fecha]), VLOOKUP(PRIORIDAD_UNO[[#This Row],[Nombre del requerimiento]],'Cálculos Manual'!A:H,8,FALSE))) -> 46406 | T41: =IF(PRIORIDAD_UNO[[#This Row],[Comienzo Calidad]]="","",IF(ISBLANK(VLOOKUP(PRIORIDAD_UNO[[#This Row],[Nombre del requerimiento]],'Cálculos Manual'!A:J,10,FALSE)), WORKDAY(PRIORIDAD_UNO[[#This Row],[Comienzo Calidad]],IF(PRIORIDAD_UNO[[#This Row],[Tamaño]]="Pequeño",30,IF(PRIORIDAD_UNO[[#This Row],[Tamaño]]="Mediano",40,50)),FERIADOS[Fecha]), VLOOKUP(PRIORIDAD_UNO[[#This Row],[Nombre del requerimiento]],'Cálculos Manual'!A:J,10,FALSE))) -> 46478 | U41: =IF(PRIORIDAD_UNO[[#This Row],[Fin Calidad]]="","",IF(ISBLANK(VLOOKUP(PRIORIDAD_UNO[[#This Row],[Nombre del requerimiento]],'Cálculos Manual'!A:L,12,FALSE)), WORKDAY(PRIORIDAD_UNO[[#This Row],[Fin Calidad]],5,FERIADOS[Fecha]), VLOOKUP(PRIORIDAD_UNO[[#This Row],[Nombre del requerimiento]],'Cálculos Manual'!A:L,12,FALSE))) -> 46485 | V41: =IF(PRIORIDAD_UNO[[#This Row],[Comienzo Producción]]="","",IF(ISBLANK(VLOOKUP(PRIORIDAD_UNO[[#This Row],[Nombre del requerimiento]],'Cálculos Manual'!A:N,14,FALSE)), WORKDAY(PRIORIDAD_UNO[[#This Row],[Comienzo Producción]],IF(PRIORIDAD_UNO[[#This Row],[Tamaño]]="Grande",10,5),FERIADOS[Fecha]), VLOOKUP(PRIORIDAD_UNO[[#This Row],[Nombre del requerimiento]],'Cálculos Manual'!A:N,14,FALSE))) -> 46499 | W41: =IFERROR(PRIORIDAD_UNO[[#This Row],[Fin Producción]]-PRIORIDAD_UNO[[#This Row],[Comienzo Desarrollo]],"") -> 262 | X41: =IF(ISBLANK(PRIORIDAD_UNO[[#This Row],[Comienzo Desarrollo]]),"Sin Fecha","Con Fecha") -> Con Fecha | Y41: =IF(PRIORIDAD_UNO[[#This Row],[Esfuerzo Estimado Desarrollo]]="No definido","Sin esfuerzo","Con esfuerzo") -> Con esfuerzo | Z41: =IF(ISBLANK(PRIORIDAD_UNO[[#This Row],[Comienzo Desarrollo]]),"🔵 Sin Fecha", IF(PRIORIDAD_UNO[[#This Row],[Comienzo Desarrollo]]<TODAY(),"🔴 Vencido", IF(PRIORIDAD_UNO[[#This Row],[Comienzo Desarrollo]]=TODAY(),"🟡 Vence hoy", IF((PRIORIDAD_UNO[[#This Row],[Comienzo Desarrollo]]-TODAY())<=5,"🟠 Por vencer", "🟢 A tiempo")))) -> 🟢 A tiempo | AA41: =IF(PRIORIDAD_UNO[[#This Row],[Comienzo Producción]]="","Por Definir",_xlfn.CONCAT(YEAR(PRIORIDAD_UNO[[#This Row],[Comienzo Producción]])," - ", MONTH(PRIORIDAD_UNO[[#This Row],[Comienzo Producción]]))) -> 2027 - 4 | AB41: 3224
A42: Modificar información que se envía a los beneficiarios a través de mensajes SMS por abonos de Transferencias Interbancarias Inmediatas de entrada | B42: 1 | C42: 7 | D42: No definido | E42: =IF(OR(ISBLANK(PRIORIDAD_UNO[[#This Row],[Esfuerzo Estimado Desarrollo]]),PRIORIDAD_UNO[[#This Row],[Esfuerzo Estimado Desarrollo]]="No definido"),"No definido", IF(VALUE(TRIM(LEFT(PRIORIDAD_UNO[[#This Row],[Esfuerzo Estimado Desarrollo]],2)))<=1,"Pequeño", IF(VALUE(TRIM(LEFT(PRIORIDAD_UNO[[#This Row],[Esfuerzo Estimado Desarrollo]],2)))<=3,"Mediano", IF(VALUE(TRIM(LEFT(PRIORIDAD_UNO[[#This Row],[Esfuerzo Estimado Desarrollo]],2)))<=5,"Grande", IF(VALUE(TRIM(LEFT(PRIORIDAD_UNO[[#This Row],[Esfuerzo Estimado Desarrollo]],2)))<=7,"Extra Grande","Proyecto"))))) -> No definido | F42: Operaciones | G42: SubGerencia de Captaciones y Pagaduria | H42: Sistema de Pagos | I42: MEMORANDO N° 00000174 - 2025-BN/3116 | J42: Sí | K42: Normativo | L42: Observado | M42: Soluciones Digitales | N42: Mario Carbajo | O42: Junior Quicaño | P42: El tiempo estimado de implementación debe ser evaluado por el Proveedor Novatronic, coordinar con el área usuaria. Una vez nos confirmen la planificación de atención, estimaremos los plazos de atencion BN. | R42: =IF(OR(PRIORIDAD_UNO[[#This Row],[Tamaño]]="No definido",ISBLANK(PRIORIDAD_UNO[[#This Row],[Comienzo Desarrollo]])),"",IF(ISBLANK( VLOOKUP(PRIORIDAD_UNO[[#This Row],[Nombre del requerimiento]],'Cálculos Manual'!A:F,6,FALSE)), WORKDAY(PRIORIDAD_UNO[[#This Row],[Comienzo Desarrollo]], IF(PRIORIDAD_UNO[[#This Row],[Tamaño]]="Pequeño",30,IF(PRIORIDAD_UNO[[#This Row],[Tamaño]]="Mediano",66,IF(PRIORIDAD_UNO[[#This Row],[Tamaño]]="Grande",110,IF(PRIORIDAD_UNO[[#This Row],[Tamaño]]="Extra Grande",154,176)))), FERIADOS[Fecha]), VLOOKUP(PRIORIDAD_UNO[[#This Row],[Nombre del requerimiento]],'Cálculos Manual'!A:F,6,FALSE))) | S42: =IF(PRIORIDAD_UNO[[#This Row],[Fin Desarrollo]]="","",IF(ISBLANK(VLOOKUP(PRIORIDAD_UNO[[#This Row],[Nombre del requerimiento]],'Cálculos Manual'!A:H,8,FALSE)),WORKDAY(PRIORIDAD_UNO[[#This Row],[Fin Desarrollo]],5,FERIADOS[Fecha]), VLOOKUP(PRIORIDAD_UNO[[#This Row],[Nombre del requerimiento]],'Cálculos Manual'!A:H,8,FALSE))) | T42: =IF(PRIORIDAD_UNO[[#This Row],[Comienzo Calidad]]="","",IF(ISBLANK(VLOOKUP(PRIORIDAD_UNO[[#This Row],[Nombre del requerimiento]],'Cálculos Manual'!A:J,10,FALSE)), WORKDAY(PRIORIDAD_UNO[[#This Row],[Comienzo Calidad]],IF(PRIORIDAD_UNO[[#This Row],[Tamaño]]="Pequeño",30,IF(PRIORIDAD_UNO[[#This Row],[Tamaño]]="Mediano",40,50)),FERIADOS[Fecha]), VLOOKUP(PRIORIDAD_UNO[[#This Row],[Nombre del requerimiento]],'Cálculos Manual'!A:J,10,FALSE))) | U42: =IF(PRIORIDAD_UNO[[#This Row],[Fin Calidad]]="","",IF(ISBLANK(VLOOKUP(PRIORIDAD_UNO[[#This Row],[Nombre del requerimiento]],'Cálculos Manual'!A:L,12,FALSE)), WORKDAY(PRIORIDAD_UNO[[#This Row],[Fin Calidad]],5,FERIADOS[Fecha]), VLOOKUP(PRIORIDAD_UNO[[#This Row],[Nombre del requerimiento]],'Cálculos Manual'!A:L,12,FALSE))) | V42: =IF(PRIORIDAD_UNO[[#This Row],[Comienzo Producción]]="","",IF(ISBLANK(VLOOKUP(PRIORIDAD_UNO[[#This Row],[Nombre del requerimiento]],'Cálculos Manual'!A:N,14,FALSE)), WORKDAY(PRIORIDAD_UNO[[#This Row],[Comienzo Producción]],IF(PRIORIDAD_UNO[[#This Row],[Tamaño]]="Grande",10,5),FERIADOS[Fecha]), VLOOKUP(PRIORIDAD_UNO[[#This Row],[Nombre del requerimiento]],'Cálculos Manual'!A:N,14,FALSE))) | W42: =IFERROR(PRIORIDAD_UNO[[#This Row],[Fin Producción]]-PRIORIDAD_UNO[[#This Row],[Comienzo Desarrollo]],"") | X42: =IF(ISBLANK(PRIORIDAD_UNO[[#This Row],[Comienzo Desarrollo]]),"Sin Fecha","Con Fecha") -> Sin Fecha | Y42: =IF(PRIORIDAD_UNO[[#This Row],[Esfuerzo Estimado Desarrollo]]="No definido","Sin esfuerzo","Con esfuerzo") -> Sin esfuerzo | Z42: =IF(ISBLANK(PRIORIDAD_UNO[[#This Row],[Comienzo Desarrollo]]),"🔵 Sin Fecha", IF(PRIORIDAD_UNO[[#This Row],[Comienzo Desarrollo]]<TODAY(),"🔴 Vencido", IF(PRIORIDAD_UNO[[#This Row],[Comienzo Desarrollo]]=TODAY(),"🟡 Vence hoy", IF((PRIORIDAD_UNO[[#This Row],[Comienzo Desarrollo]]-TODAY())<=5,"🟠 Por vencer", "🟢 A tiempo")))) -> 🔵 Sin Fecha | AA42: =IF(PRIORIDAD_UNO[[#This Row],[Comienzo Producción]]="","Por Definir",_xlfn.CONCAT(YEAR(PRIORIDAD_UNO[[#This Row],[Comienzo Producción]])," - ", MONTH(PRIORIDAD_UNO[[#This Row],[Comienzo Producción]]))) -> Por Definir | AB42: 3240
A43: Modificación en la metodología de la capacidad de pago en la admisión del Préstamo Multired | B43: 1 | C43: 10 | D43: 6 meses | E43: =IF(OR(ISBLANK(PRIORIDAD_UNO[[#This Row],[Esfuerzo Estimado Desarrollo]]),PRIORIDAD_UNO[[#This Row],[Esfuerzo Estimado Desarrollo]]="No definido"),"No definido", IF(VALUE(TRIM(LEFT(PRIORIDAD_UNO[[#This Row],[Esfuerzo Estimado Desarrollo]],2)))<=1,"Pequeño", IF(VALUE(TRIM(LEFT(PRIORIDAD_UNO[[#This Row],[Esfuerzo Estimado Desarrollo]],2)))<=3,"Mediano", IF(VALUE(TRIM(LEFT(PRIORIDAD_UNO[[#This Row],[Esfuerzo Estimado Desarrollo]],2)))<=5,"Grande", IF(VALUE(TRIM(LEFT(PRIORIDAD_UNO[[#This Row],[Esfuerzo Estimado Desarrollo]],2)))<=7,"Extra Grande","Proyecto"))))) -> Extra Grande | F43: Productos e Inclusión Financiera | G43: Banca Personal | H43: Préstamo Multired | I43: No | J43: Sí | K43: Recomendación | L43: Pendiente de Atención | M43: Sistemas Bancarios | N43: Fiorella Galvan / Waldo Basurto | O43: Milagros Huamani | Q43: 46266 | R43: =IF(OR(PRIORIDAD_UNO[[#This Row],[Tamaño]]="No definido",ISBLANK(PRIORIDAD_UNO[[#This Row],[Comienzo Desarrollo]])),"",IF(ISBLANK( VLOOKUP(PRIORIDAD_UNO[[#This Row],[Nombre del requerimiento]],'Cálculos Manual'!A:F,6,FALSE)), WORKDAY(PRIORIDAD_UNO[[#This Row],[Comienzo Desarrollo]], IF(PRIORIDAD_UNO[[#This Row],[Tamaño]]="Pequeño",30,IF(PRIORIDAD_UNO[[#This Row],[Tamaño]]="Mediano",66,IF(PRIORIDAD_UNO[[#This Row],[Tamaño]]="Grande",110,IF(PRIORIDAD_UNO[[#This Row],[Tamaño]]="Extra Grande",154,176)))), FERIADOS[Fecha]), VLOOKUP(PRIORIDAD_UNO[[#This Row],[Nombre del requerimiento]],'Cálculos Manual'!A:F,6,FALSE))) -> 46491 | S43: =IF(PRIORIDAD_UNO[[#This Row],[Fin Desarrollo]]="","",IF(ISBLANK(VLOOKUP(PRIORIDAD_UNO[[#This Row],[Nombre del requerimiento]],'Cálculos Manual'!A:H,8,FALSE)),WORKDAY(PRIORIDAD_UNO[[#This Row],[Fin Desarrollo]],5,FERIADOS[Fecha]), VLOOKUP(PRIORIDAD_UNO[[#This Row],[Nombre del requerimiento]],'Cálculos Manual'!A:H,8,FALSE))) -> 46498 | T43: =IF(PRIORIDAD_UNO[[#This Row],[Comienzo Calidad]]="","",IF(ISBLANK(VLOOKUP(PRIORIDAD_UNO[[#This Row],[Nombre del requerimiento]],'Cálculos Manual'!A:J,10,FALSE)), WORKDAY(PRIORIDAD_UNO[[#This Row],[Comienzo Calidad]],IF(PRIORIDAD_UNO[[#This Row],[Tamaño]]="Pequeño",30,IF(PRIORIDAD_UNO[[#This Row],[Tamaño]]="Mediano",40,50)),FERIADOS[Fecha]), VLOOKUP(PRIORIDAD_UNO[[#This Row],[Nombre del requerimiento]],'Cálculos Manual'!A:J,10,FALSE))) -> 46569 | U43: =IF(PRIORIDAD_UNO[[#This Row],[Fin Calidad]]="","",IF(ISBLANK(VLOOKUP(PRIORIDAD_UNO[[#This Row],[Nombre del requerimiento]],'Cálculos Manual'!A:L,12,FALSE)), WORKDAY(PRIORIDAD_UNO[[#This Row],[Fin Calidad]],5,FERIADOS[Fecha]), VLOOKUP(PRIORIDAD_UNO[[#This Row],[Nombre del requerimiento]],'Cálculos Manual'!A:L,12,FALSE))) -> 46577 | V43: =IF(PRIORIDAD_UNO[[#This Row],[Comienzo Producción]]="","",IF(ISBLANK(VLOOKUP(PRIORIDAD_UNO[[#This Row],[Nombre del requerimiento]],'Cálculos Manual'!A:N,14,FALSE)), WORKDAY(PRIORIDAD_UNO[[#This Row],[Comienzo Producción]],IF(PRIORIDAD_UNO[[#This Row],[Tamaño]]="Grande",10,5),FERIADOS[Fecha]), VLOOKUP(PRIORIDAD_UNO[[#This Row],[Nombre del requerimiento]],'Cálculos Manual'!A:N,14,FALSE))) -> 46584 | W43: =IFERROR(PRIORIDAD_UNO[[#This Row],[Fin Producción]]-PRIORIDAD_UNO[[#This Row],[Comienzo Desarrollo]],"") -> 318 | X43: =IF(ISBLANK(PRIORIDAD_UNO[[#This Row],[Comienzo Desarrollo]]),"Sin Fecha","Con Fecha") -> Con Fecha | Y43: =IF(PRIORIDAD_UNO[[#This Row],[Esfuerzo Estimado Desarrollo]]="No definido","Sin esfuerzo","Con esfuerzo") -> Con esfuerzo | Z43: =IF(ISBLANK(PRIORIDAD_UNO[[#This Row],[Comienzo Desarrollo]]),"🔵 Sin Fecha", IF(PRIORIDAD_UNO[[#This Row],[Comienzo Desarrollo]]<TODAY(),"🔴 Vencido", IF(PRIORIDAD_UNO[[#This Row],[Comienzo Desarrollo]]=TODAY(),"🟡 Vence hoy", IF((PRIORIDAD_UNO[[#This Row],[Comienzo Desarrollo]]-TODAY())<=5,"🟠 Por vencer", "🟢 A tiempo")))) -> 🟢 A tiempo | AA43: =IF(PRIORIDAD_UNO[[#This Row],[Comienzo Producción]]="","Por Definir",_xlfn.CONCAT(YEAR(PRIORIDAD_UNO[[#This Row],[Comienzo Producción]])," - ", MONTH(PRIORIDAD_UNO[[#This Row],[Comienzo Producción]]))) -> 2027 - 7 | AB43: No está
A44: Modificación de las secuencias FISA de las Bóvedas de Tránsito BTs Hermes y Prosegur Lima | B44: 1 | C44: 44 | D44: No definido | E44: =IF(OR(ISBLANK(PRIORIDAD_UNO[[#This Row],[Esfuerzo Estimado Desarrollo]]),PRIORIDAD_UNO[[#This Row],[Esfuerzo Estimado Desarrollo]]="No definido"),"No definido", IF(VALUE(TRIM(LEFT(PRIORIDAD_UNO[[#This Row],[Esfuerzo Estimado Desarrollo]],2)))<=1,"Pequeño", IF(VALUE(TRIM(LEFT(PRIORIDAD_UNO[[#This Row],[Esfuerzo Estimado Desarrollo]],2)))<=3,"Mediano", IF(VALUE(TRIM(LEFT(PRIORIDAD_UNO[[#This Row],[Esfuerzo Estimado Desarrollo]],2)))<=5,"Grande", IF(VALUE(TRIM(LEFT(PRIORIDAD_UNO[[#This Row],[Esfuerzo Estimado Desarrollo]],2)))<=7,"Extra Grande","Proyecto"))))) -> No definido | F44: Operaciones | G44: Subgerencia Caja y Valores | H44: Caja y Valores en Custodia | I44: MEMORANDO N° 00000035 - 2026-BN/3131 | J44: Sí | K44: Evolutivo | L44: Descartado | M44: Sistemas Administrativos | N44: Ricardo Cuba | O44: Junior Quicaño | P44: Se devolverá el requerimiento, el alcance del anexo 2 debe ser divido y modificado. | R44: =IF(OR(PRIORIDAD_UNO[[#This Row],[Tamaño]]="No definido",ISBLANK(PRIORIDAD_UNO[[#This Row],[Comienzo Desarrollo]])),"",IF(ISBLANK( VLOOKUP(PRIORIDAD_UNO[[#This Row],[Nombre del requerimiento]],'Cálculos Manual'!A:F,6,FALSE)), WORKDAY(PRIORIDAD_UNO[[#This Row],[Comienzo Desarrollo]], IF(PRIORIDAD_UNO[[#This Row],[Tamaño]]="Pequeño",30,IF(PRIORIDAD_UNO[[#This Row],[Tamaño]]="Mediano",66,IF(PRIORIDAD_UNO[[#This Row],[Tamaño]]="Grande",110,IF(PRIORIDAD_UNO[[#This Row],[Tamaño]]="Extra Grande",154,176)))), FERIADOS[Fecha]), VLOOKUP(PRIORIDAD_UNO[[#This Row],[Nombre del requerimiento]],'Cálculos Manual'!A:F,6,FALSE))) | S44: =IF(PRIORIDAD_UNO[[#This Row],[Fin Desarrollo]]="","",IF(ISBLANK(VLOOKUP(PRIORIDAD_UNO[[#This Row],[Nombre del requerimiento]],'Cálculos Manual'!A:H,8,FALSE)),WORKDAY(PRIORIDAD_UNO[[#This Row],[Fin Desarrollo]],5,FERIADOS[Fecha]), VLOOKUP(PRIORIDAD_UNO[[#This Row],[Nombre del requerimiento]],'Cálculos Manual'!A:H,8,FALSE))) | T44: =IF(PRIORIDAD_UNO[[#This Row],[Comienzo Calidad]]="","",IF(ISBLANK(VLOOKUP(PRIORIDAD_UNO[[#This Row],[Nombre del requerimiento]],'Cálculos Manual'!A:J,10,FALSE)), WORKDAY(PRIORIDAD_UNO[[#This Row],[Comienzo Calidad]],IF(PRIORIDAD_UNO[[#This Row],[Tamaño]]="Pequeño",30,IF(PRIORIDAD_UNO[[#This Row],[Tamaño]]="Mediano",40,50)),FERIADOS[Fecha]), VLOOKUP(PRIORIDAD_UNO[[#This Row],[Nombre del requerimiento]],'Cálculos Manual'!A:J,10,FALSE))) | U44: =IF(PRIORIDAD_UNO[[#This Row],[Fin Calidad]]="","",IF(ISBLANK(VLOOKUP(PRIORIDAD_UNO[[#This Row],[Nombre del requerimiento]],'Cálculos Manual'!A:L,12,FALSE)), WORKDAY(PRIORIDAD_UNO[[#This Row],[Fin Calidad]],5,FERIADOS[Fecha]), VLOOKUP(PRIORIDAD_UNO[[#This Row],[Nombre del requerimiento]],'Cálculos Manual'!A:L,12,FALSE))) | V44: =IF(PRIORIDAD_UNO[[#This Row],[Comienzo Producción]]="","",IF(ISBLANK(VLOOKUP(PRIORIDAD_UNO[[#This Row],[Nombre del requerimiento]],'Cálculos Manual'!A:N,14,FALSE)), WORKDAY(PRIORIDAD_UNO[[#This Row],[Comienzo Producción]],IF(PRIORIDAD_UNO[[#This Row],[Tamaño]]="Grande",10,5),FERIADOS[Fecha]), VLOOKUP(PRIORIDAD_UNO[[#This Row],[Nombre del requerimiento]],'Cálculos Manual'!A:N,14,FALSE))) | W44: =IFERROR(PRIORIDAD_UNO[[#This Row],[Fin Producción]]-PRIORIDAD_UNO[[#This Row],[Comienzo Desarrollo]],"") | X44: =IF(ISBLANK(PRIORIDAD_UNO[[#This Row],[Comienzo Desarrollo]]),"Sin Fecha","Con Fecha") -> Sin Fecha | Y44: =IF(PRIORIDAD_UNO[[#This Row],[Esfuerzo Estimado Desarrollo]]="No definido","Sin esfuerzo","Con esfuerzo") -> Sin esfuerzo | Z44: =IF(ISBLANK(PRIORIDAD_UNO[[#This Row],[Comienzo Desarrollo]]),"🔵 Sin Fecha", IF(PRIORIDAD_UNO[[#This Row],[Comienzo Desarrollo]]<TODAY(),"🔴 Vencido", IF(PRIORIDAD_UNO[[#This Row],[Comienzo Desarrollo]]=TODAY(),"🟡 Vence hoy", IF((PRIORIDAD_UNO[[#This Row],[Comienzo Desarrollo]]-TODAY())<=5,"🟠 Por vencer", "🟢 A tiempo")))) -> 🔵 Sin Fecha | AA44: =IF(PRIORIDAD_UNO[[#This Row],[Comienzo Producción]]="","Por Definir",_xlfn.CONCAT(YEAR(PRIORIDAD_UNO[[#This Row],[Comienzo Producción]])," - ", MONTH(PRIORIDAD_UNO[[#This Row],[Comienzo Producción]]))) -> Por Definir | AB44: 3248
A45: Modificación de la Transacciones del cobro del proceso de Emisión y Reposición de Tarjeta de Débito | B45: 1 | C45: 15 | E45: =IF(OR(ISBLANK(PRIORIDAD_UNO[[#This Row],[Esfuerzo Estimado Desarrollo]]),PRIORIDAD_UNO[[#This Row],[Esfuerzo Estimado Desarrollo]]="No definido"),"No definido", IF(VALUE(TRIM(LEFT(PRIORIDAD_UNO[[#This Row],[Esfuerzo Estimado Desarrollo]],2)))<=1,"Pequeño", IF(VALUE(TRIM(LEFT(PRIORIDAD_UNO[[#This Row],[Esfuerzo Estimado Desarrollo]],2)))<=3,"Mediano", IF(VALUE(TRIM(LEFT(PRIORIDAD_UNO[[#This Row],[Esfuerzo Estimado Desarrollo]],2)))<=5,"Grande", IF(VALUE(TRIM(LEFT(PRIORIDAD_UNO[[#This Row],[Esfuerzo Estimado Desarrollo]],2)))<=7,"Extra Grande","Proyecto"))))) -> No definido | F45: Banca Digital | G45: Canales Alternos | H45: Canales Virtuales | I45: MEMORANDO N° 00000120 - 2026-BN/3252 | J45: Sí | K45: Evolutivo | L45: Por evaluar | M45: Sistemas Bancarios | N45: Waldo Basurto | O45: Omar Sarmiento | R45: =IF(OR(PRIORIDAD_UNO[[#This Row],[Tamaño]]="No definido",ISBLANK(PRIORIDAD_UNO[[#This Row],[Comienzo Desarrollo]])),"",IF(ISBLANK( VLOOKUP(PRIORIDAD_UNO[[#This Row],[Nombre del requerimiento]],'Cálculos Manual'!A:F,6,FALSE)), WORKDAY(PRIORIDAD_UNO[[#This Row],[Comienzo Desarrollo]], IF(PRIORIDAD_UNO[[#This Row],[Tamaño]]="Pequeño",30,IF(PRIORIDAD_UNO[[#This Row],[Tamaño]]="Mediano",66,IF(PRIORIDAD_UNO[[#This Row],[Tamaño]]="Grande",110,IF(PRIORIDAD_UNO[[#This Row],[Tamaño]]="Extra Grande",154,176)))), FERIADOS[Fecha]), VLOOKUP(PRIORIDAD_UNO[[#This Row],[Nombre del requerimiento]],'Cálculos Manual'!A:F,6,FALSE))) | S45: =IF(PRIORIDAD_UNO[[#This Row],[Fin Desarrollo]]="","",IF(ISBLANK(VLOOKUP(PRIORIDAD_UNO[[#This Row],[Nombre del requerimiento]],'Cálculos Manual'!A:H,8,FALSE)),WORKDAY(PRIORIDAD_UNO[[#This Row],[Fin Desarrollo]],5,FERIADOS[Fecha]), VLOOKUP(PRIORIDAD_UNO[[#This Row],[Nombre del requerimiento]],'Cálculos Manual'!A:H,8,FALSE))) | T45: =IF(PRIORIDAD_UNO[[#This Row],[Comienzo Calidad]]="","",IF(ISBLANK(VLOOKUP(PRIORIDAD_UNO[[#This Row],[Nombre del requerimiento]],'Cálculos Manual'!A:J,10,FALSE)), WORKDAY(PRIORIDAD_UNO[[#This Row],[Comienzo Calidad]],IF(PRIORIDAD_UNO[[#This Row],[Tamaño]]="Pequeño",30,IF(PRIORIDAD_UNO[[#This Row],[Tamaño]]="Mediano",40,50)),FERIADOS[Fecha]), VLOOKUP(PRIORIDAD_UNO[[#This Row],[Nombre del requerimiento]],'Cálculos Manual'!A:J,10,FALSE))) | U45: =IF(PRIORIDAD_UNO[[#This Row],[Fin Calidad]]="","",IF(ISBLANK(VLOOKUP(PRIORIDAD_UNO[[#This Row],[Nombre del requerimiento]],'Cálculos Manual'!A:L,12,FALSE)), WORKDAY(PRIORIDAD_UNO[[#This Row],[Fin Calidad]],5,FERIADOS[Fecha]), VLOOKUP(PRIORIDAD_UNO[[#This Row],[Nombre del requerimiento]],'Cálculos Manual'!A:L,12,FALSE))) | V45: =IF(PRIORIDAD_UNO[[#This Row],[Comienzo Producción]]="","",IF(ISBLANK(VLOOKUP(PRIORIDAD_UNO[[#This Row],[Nombre del requerimiento]],'Cálculos Manual'!A:N,14,FALSE)), WORKDAY(PRIORIDAD_UNO[[#This Row],[Comienzo Producción]],IF(PRIORIDAD_UNO[[#This Row],[Tamaño]]="Grande",10,5),FERIADOS[Fecha]), VLOOKUP(PRIORIDAD_UNO[[#This Row],[Nombre del requerimiento]],'Cálculos Manual'!A:N,14,FALSE))) | W45: =IFERROR(PRIORIDAD_UNO[[#This Row],[Fin Producción]]-PRIORIDAD_UNO[[#This Row],[Comienzo Desarrollo]],"") | X45: =IF(ISBLANK(PRIORIDAD_UNO[[#This Row],[Comienzo Desarrollo]]),"Sin Fecha","Con Fecha") -> Sin Fecha | Y45: =IF(PRIORIDAD_UNO[[#This Row],[Esfuerzo Estimado Desarrollo]]="No definido","Sin esfuerzo","Con esfuerzo") -> Con esfuerzo | Z45: =IF(ISBLANK(PRIORIDAD_UNO[[#This Row],[Comienzo Desarrollo]]),"🔵 Sin Fecha", IF(PRIORIDAD_UNO[[#This Row],[Comienzo Desarrollo]]<TODAY(),"🔴 Vencido", IF(PRIORIDAD_UNO[[#This Row],[Comienzo Desarrollo]]=TODAY(),"🟡 Vence hoy", IF((PRIORIDAD_UNO[[#This Row],[Comienzo Desarrollo]]-TODAY())<=5,"🟠 Por vencer", "🟢 A tiempo")))) -> 🔵 Sin Fecha | AA45: =IF(PRIORIDAD_UNO[[#This Row],[Comienzo Producción]]="","Por Definir",_xlfn.CONCAT(YEAR(PRIORIDAD_UNO[[#This Row],[Comienzo Producción]])," - ", MONTH(PRIORIDAD_UNO[[#This Row],[Comienzo Producción]]))) -> Por Definir | AB45: Revisar 3111
A46: MN: Proyecto migración y actualización CIIU REV. 4 - apertura de cuentas masivas | B46: 1 | C46: 42 | D46: 2 meses | E46: =IF(OR(ISBLANK(PRIORIDAD_UNO[[#This Row],[Esfuerzo Estimado Desarrollo]]),PRIORIDAD_UNO[[#This Row],[Esfuerzo Estimado Desarrollo]]="No definido"),"No definido", IF(VALUE(TRIM(LEFT(PRIORIDAD_UNO[[#This Row],[Esfuerzo Estimado Desarrollo]],2)))<=1,"Pequeño", IF(VALUE(TRIM(LEFT(PRIORIDAD_UNO[[#This Row],[Esfuerzo Estimado Desarrollo]],2)))<=3,"Mediano", IF(VALUE(TRIM(LEFT(PRIORIDAD_UNO[[#This Row],[Esfuerzo Estimado Desarrollo]],2)))<=5,"Grande", IF(VALUE(TRIM(LEFT(PRIORIDAD_UNO[[#This Row],[Esfuerzo Estimado Desarrollo]],2)))<=7,"Extra Grande","Proyecto"))))) -> Mediano | F46: Operaciones | G46: SubGerencia de Captaciones y Pagaduria | H46: Apertura de Cuentas | I46: MEMORANDO N° 00000567 - 2025-BN/3111 | J46: Sí | K46: Evolutivo | L46: Pendiente de Atención | M46: Sistemas Bancarios | N46: Johnny Rocca | O46: Junior Quicaño | Q46: 46727 | R46: =IF(OR(PRIORIDAD_UNO[[#This Row],[Tamaño]]="No definido",ISBLANK(PRIORIDAD_UNO[[#This Row],[Comienzo Desarrollo]])),"",IF(ISBLANK( VLOOKUP(PRIORIDAD_UNO[[#This Row],[Nombre del requerimiento]],'Cálculos Manual'!A:F,6,FALSE)), WORKDAY(PRIORIDAD_UNO[[#This Row],[Comienzo Desarrollo]], IF(PRIORIDAD_UNO[[#This Row],[Tamaño]]="Pequeño",30,IF(PRIORIDAD_UNO[[#This Row],[Tamaño]]="Mediano",66,IF(PRIORIDAD_UNO[[#This Row],[Tamaño]]="Grande",110,IF(PRIORIDAD_UNO[[#This Row],[Tamaño]]="Extra Grande",154,176)))), FERIADOS[Fecha]), VLOOKUP(PRIORIDAD_UNO[[#This Row],[Nombre del requerimiento]],'Cálculos Manual'!A:F,6,FALSE))) -> 46821 | S46: =IF(PRIORIDAD_UNO[[#This Row],[Fin Desarrollo]]="","",IF(ISBLANK(VLOOKUP(PRIORIDAD_UNO[[#This Row],[Nombre del requerimiento]],'Cálculos Manual'!A:H,8,FALSE)),WORKDAY(PRIORIDAD_UNO[[#This Row],[Fin Desarrollo]],5,FERIADOS[Fecha]), VLOOKUP(PRIORIDAD_UNO[[#This Row],[Nombre del requerimiento]],'Cálculos Manual'!A:H,8,FALSE))) -> 46828 | T46: =IF(PRIORIDAD_UNO[[#This Row],[Comienzo Calidad]]="","",IF(ISBLANK(VLOOKUP(PRIORIDAD_UNO[[#This Row],[Nombre del requerimiento]],'Cálculos Manual'!A:J,10,FALSE)), WORKDAY(PRIORIDAD_UNO[[#This Row],[Comienzo Calidad]],IF(PRIORIDAD_UNO[[#This Row],[Tamaño]]="Pequeño",30,IF(PRIORIDAD_UNO[[#This Row],[Tamaño]]="Mediano",40,50)),FERIADOS[Fecha]), VLOOKUP(PRIORIDAD_UNO[[#This Row],[Nombre del requerimiento]],'Cálculos Manual'!A:J,10,FALSE))) -> 46884 | U46: =IF(PRIORIDAD_UNO[[#This Row],[Fin Calidad]]="","",IF(ISBLANK(VLOOKUP(PRIORIDAD_UNO[[#This Row],[Nombre del requerimiento]],'Cálculos Manual'!A:L,12,FALSE)), WORKDAY(PRIORIDAD_UNO[[#This Row],[Fin Calidad]],5,FERIADOS[Fecha]), VLOOKUP(PRIORIDAD_UNO[[#This Row],[Nombre del requerimiento]],'Cálculos Manual'!A:L,12,FALSE))) -> 46891 | V46: =IF(PRIORIDAD_UNO[[#This Row],[Comienzo Producción]]="","",IF(ISBLANK(VLOOKUP(PRIORIDAD_UNO[[#This Row],[Nombre del requerimiento]],'Cálculos Manual'!A:N,14,FALSE)), WORKDAY(PRIORIDAD_UNO[[#This Row],[Comienzo Producción]],IF(PRIORIDAD_UNO[[#This Row],[Tamaño]]="Grande",10,5),FERIADOS[Fecha]), VLOOKUP(PRIORIDAD_UNO[[#This Row],[Nombre del requerimiento]],'Cálculos Manual'!A:N,14,FALSE))) -> 46898 | W46: =IFERROR(PRIORIDAD_UNO[[#This Row],[Fin Producción]]-PRIORIDAD_UNO[[#This Row],[Comienzo Desarrollo]],"") -> 171 | X46: =IF(ISBLANK(PRIORIDAD_UNO[[#This Row],[Comienzo Desarrollo]]),"Sin Fecha","Con Fecha") -> Con Fecha | Y46: =IF(PRIORIDAD_UNO[[#This Row],[Esfuerzo Estimado Desarrollo]]="No definido","Sin esfuerzo","Con esfuerzo") -> Con esfuerzo | Z46: =IF(ISBLANK(PRIORIDAD_UNO[[#This Row],[Comienzo Desarrollo]]),"🔵 Sin Fecha", IF(PRIORIDAD_UNO[[#This Row],[Comienzo Desarrollo]]<TODAY(),"🔴 Vencido", IF(PRIORIDAD_UNO[[#This Row],[Comienzo Desarrollo]]=TODAY(),"🟡 Vence hoy", IF((PRIORIDAD_UNO[[#This Row],[Comienzo Desarrollo]]-TODAY())<=5,"🟠 Por vencer", "🟢 A tiempo")))) -> 🟢 A tiempo | AA46: =IF(PRIORIDAD_UNO[[#This Row],[Comienzo Producción]]="","Por Definir",_xlfn.CONCAT(YEAR(PRIORIDAD_UNO[[#This Row],[Comienzo Producción]])," - ", MONTH(PRIORIDAD_UNO[[#This Row],[Comienzo Producción]]))) -> 2028 - 5 | AB46: 3246
